Workbook

Sheet Teacher Salary Data
A1: District | B1: State | C1: Education Level | D1: Years Experience | E1: Salary | F1: Last Verified
A2: Alief ISD | B2: TX | C2: Bachelor's | D2: 0 | E2: 64100 | F2: 2026-06-10
A3: Alief ISD | B3: TX | C3: Bachelor's | D3: 1 | E3: 64350 | F3: 2026-06-10
A4: Alief ISD | B4: TX | C4: Bachelor's | D4: 2 | E4: 64600 | F4: 2026-06-10
A5: Alief ISD | B5: TX | C5: Bachelor's | D5: 3 | E5: 64850 | F5: 2026-06-10
A6: Alief ISD | B6: TX | C6: Bachelor's | D6: 4 | E6: 65100 | F6: 2026-06-10
A7: Alief ISD | B7: TX | C7: Bachelor's | D7: 5 | E7: 65350 | F7: 2026-06-10
A8: Alief ISD | B8: TX | C8: Bachelor's | D8: 6 | E8: 65600 | F8: 2026-06-10
A9: Alief ISD | B9: TX | C9: Bachelor's | D9: 7 | E9: 65850 | F9: 2026-06-10
A10: Alief ISD | B10: TX | C10: Bachelor's | D10: 8 | E10: 66100 | F10: 2026-06-10
A11: Alief ISD | B11: TX | C11: Bachelor's | D11: 9 | E11: 66350 | F11: 2026-06-10
A12: Alief ISD | B12: TX | C12: Bachelor's | D12: 10 | E12: 66600 | F12: 2026-06-10
A13: Alief ISD | B13: TX | C13: Master's | D13: 0 | E13: 64600 | F13: 2026-06-10
... A1387: West Des Moines Community Schools | B1387: IA | C1387: Master's | D1387: 10 | E1387: 65512 | F1387: 2026-06-13

Sheet School District Profiles
A1: District | B1: State | C1: Region | D1: White % | E1: Hispanic % | F1: Asian % | G1: Black % | H1: Student Teacher Ratio | I1: Daily Sub Pay | J1: Other % | K1: Number of High Schools | L1: Number of Middle Schools | M1: Number of Elementary Schools | N1: Other / Specialty Schools | O1: Total Schools Counted | P1: Source URL | Q1: Last Verified | R1: Other %
A2: Alief ISD | B2: TX | C2: Houston | D2: 3 | E2: 62 | F2: 10 | G2: 24 | H2: 13 | I2: 125 | J2: =100-SUM(D2:G2) | K2: 6 | L2: 12 | M2: 27 | N2: 1 | O2: 46
A3: Arcadia Unified School District | B3: CA | C3: Southern California | D3: 26 | E3: 10 | F3: 61 | G3: 1 | H3: 24.58 | I3: 200 | J3: =100-SUM(D3:G3) | K3: 1 | L3: 3 | M3: 6 | N3: 1 | O3: 11 | P3: AUSD reports six elementary schools, three middle schools, one comprehensive high school, and one alternative school/outreach program. Master's degree alone appears in the same Column 1 as BA on the ATA schedule, so BA and MA entries use the same column unless additional semester units are earned.
A4: Austin ISD | B4: TX | C4: Austin | D4: 30.68 | E4: 54.14 | F4: 4.84 | G4: 6.01 | H4: 13.7 | I4: 155 | J4: =100-SUM(D4:G4) | K4: 13 | L4: 19 | M4: 78 | N4: 4 | O4: 114 | P4: School-directory pages include a 6-12 campus (Ann Richards) in both the middle and high lists; counts below are normalized to the district's cited 114 schools and classify Ann Richards with middle schools.
A5: Barbers Hill ISD | B5: TX | C5: Houston | D5: 57.2 | E5: 32.1 | F5: 1.9 | G5: 4.8 | H5: 13 | I5: 135 | J5: =100-SUM(D5:G5) | K5: 1 | L5: 2 | M5: 5 | N5: 0 | O5: 8 | P5: District schools page lists one traditional high school (Barbers Hill High School), two middle school campuses, five elementary/early childhood campuses, and no separate alternative high school counted for this prototype.
A6: Canyons School District | B6: UT | C6: Salt Lake Valley | D6: 71 | E6: 18 | F6: 3 | G6: 2 | H6: 21.35 | I6: 180 | J6: =100-SUM(D6:G6) | K6: 6 | L6: 8 | M6: 28 | N6: 8 | O6: 50 | P6: NCES lists 50 total schools; counts follow district school directory categories with 8 specialty schools.
A7: Chandler Unified School District | B7: AZ | C7: Phoenix / East Valley | D7: 47.7 | E7: 31.9 | F7: 12.5 | G7: 5.8 | H7: 17.59 | I7: 170 | J7: =100-SUM(D7:G7) | K7: 5 | L7: 7 | M7: 31 | N7: 6 | O7: 49 | P7: CUSD About page lists 31 elementary schools, 5 junior highs, 2 middle schools, 5 high schools, 4 alternatives, 1 secondary, and 1 online school.
A8: Chapel Hill-Carrboro City Schools | B8: NC | C8: Research Triangle | D8: 52.52 | E8: 14.4 | F8: 15.01 | G8: 11.28 | H8: 12.69 | I8: 135 | J8: =100-SUM(D8:G8) | K8: 4 | L8: 4 | M8: 11 | N8: 1 | O8: 20
A9: Cherry Creek School District | B9: CO | C9: Denver | D9: 44.8 | E9: 24.8 | F9: 8.4 | G9: 11.4 | H9: 16.18 | I9: 210 | J9: =100-SUM(D9:G9) | K9: 8 | L9: 11 | M9: 44 | N9: 4 | O9: 67
A10: Chicago Public Schools | B10: IL | C10: Chicago | D10: 11.8 | E10: 46.4 | F10: 4.9 | G10: 34.3 | H10: 13.77 | I10: 193 | J10: =100-SUM(D10:G10) | K10: 91 | M10: 423 | O10: 514 | P10: CPS Stats & Facts lists 423 district-run elementary/K-8 schools and 91 district-run high schools. The 157 high-school grand total includes charter, contract, and SAFE schools, so the prototype now displays the district-run count because CPS salary data applies to district-run teacher placement.
A11: Cobb County School District | B11: GA | C11: Atlanta | D11: 32 | E11: 26.6 | F11: 6.2 | G11: 29.2 | H11: 14.06 | I11: 150 | J11: =100-SUM(D11:G11) | K11: 17 | L11: 26 | M11: 66 | N11: 3 | O11: 112 | P11: District page lists 66 elementary schools, 26 middle schools, 17 high schools, plus one charter school, one special education center, and one adult education center. | Q11: 2026-06-13
A12: Denver Public Schools | B12: CO | C12: Denver | D12: 25 | E12: 52 | F12: 3 | G12: 13 | H12: 15 | I12: 186.42 | J12: =100-SUM(D12:G12) | K12: 18 | L12: 12 | M12: 76 | N12: 87 | O12: 193
A13: Eanes ISD | B13: TX | C13: Austin | D13: 62 | E13: 15.4 | F13: 14.7 | G13: 0.9 | H13: 12.28 | I13: 130 | J13: =100-SUM(D13:G13) | K13: 2 | L13: 2 | M13: 5 | N13: 1 | O13: 10
A14: Flagstaff Unified School District | B14: AZ | C14: Flagstaff | D14: 39.8 | E14: 30.9 | F14: 0.8 | G14: 0.8 | H14: 15.68 | I14: 140 | J14: =100-SUM(D14:G14) | K14: 3 | L14: 2 | M14: 10 | N14: 0 | O14: 15 | P14: FUSD official about page says 15 comprehensive school sites; district school list includes 3 high schools and 2 middle schools.
A15: Glendale Union High School District | B15: AZ | C15: Phoenix Metro | D15: 23.4 | E15: 59.7 | F15: 3.2 | G15: 9.3 | H15: 22.24 | I15: 145 | J15: =100-SUM(D15:G15) | K15: 11 | L15: 0 | M15: 0 | N15: 0 | O15: 11 | P15: NCES lists 11 total schools. GUHSD is a high-school-only district; all schools counted as high schools. Substitute rate uses $145 adjusted rate of published $123-$199 daily range.
A16: Glendora Unified School District | B16: CA | C16: Southern California | D16: 28 | E16: 49 | F16: 15 | G16: 1 | H16: 24 | I16: 200 | J16: =100-SUM(D16:G16) | K16: 2 | L16: 2 | M16: 5 | N16: 1 | O16: 10
A17: Gwinnett County Public Schools | B17: GA | C17: Atlanta | D17: 14.5 | E17: 36.2 | F17: 13.1 | G17: 31.6 | H17: 14.26 | I17: 130 | J17: =100-SUM(D17:G17) | K17: 24 | L17: 29 | M17: 81 | N17: 8 | O17: 142 | P17: GCPS by the Numbers lists 81 elementary schools, 29 middle schools, 24 high schools, 7 special entities, and 1 charter school. | Q17: 2026-06-13
A18: Jordan District | B18: UT | C18: Salt Lake Valley | D18: 70 | E18: 20 | F18: 2 | G18: 1 | H18: 21 | I18: 199 | J18: =100-SUM(D18:G18) | K18: 10 | L18: 13 | M18: 42 | N18: 3 | O18: 68
A19: Katy ISD | B19: TX | C19: Houston | D19: 27 | E19: 37 | F19: 17 | G19: 15 | H19: 14 | I19: 120 | J19: =100-SUM(D19:G19) | K19: 11 | L19: 18 | M19: 48 | N19: 3 | O19: 80
A20: La Cañada Unified School District | B20: CA | C20: Southern California | D20: 42 | E20: 12 | F20: 33 | G20: 0 | H20: 23.66 | I20: 200 | J20: =100-SUM(D20:G20) | K20: 1 | L20: 1 | M20: 3 | N20: 0 | O20: 4
A21: Lake Washington School District | B21: WA | C21: Seattle Eastside | D21: 35 | E21: 15 | F21: 38 | G21: 3 | H21: 17.91 | I21: 222 | J21: =100-SUM(D21:G21) | K21: 6 | L21: 11 | M21: 33 | N21: 7 | O21: 57 | P21: https://www.lwsd.org/employment/teachers-certificated-employees/salary-schedules ; https://nces.ed.gov/ccd/districtsearch/district_detail.asp?DistrictID=5304230 ; https://www.apartments.com/rent-market-trends/redmond-wa/ ; https://www.redfin.com/city/14913/WA/Redmond/housing-market ; https://www.lwsd.org/about/enrollment-report | Q21: 2026-06-13 | R21: 9
A22: Leander ISD | B22: TX | C22: Austin | D22: 46 | E22: 26 | F22: 17 | G22: 5 | H22: 14 | I22: 130 | J22: =100-SUM(D22:G22) | K22: 6 | L22: 9 | M22: 30 | N22: 4 | O22: 49
A23: Los Angeles Unified | B23: CA | C23: Southern California | D23: 10 | E23: 73 | F23: 4 | G23: 7 | H23: 19.2 | I23: 261.49 | J23: =100-SUM(D23:G23) | O23: 784
A24: Loudoun County Public Schools | B24: VA | C24: Northern VA/DC | D24: 38 | E24: 18 | F24: 26 | G24: 7 | H24: 12.13 | I24: 135.03 | J24: =100-SUM(D24:G24) | K24: 17 | L24: 18 | M24: 62 | N24: 5 | O24: 102 | P24: LCPS operates a very large PK-12 system; NCES lists 102 total schools, and the high-school list includes 17 traditional high schools. Counts use 17 high schools, 18 middle schools, 62 elementary schools, and 5 other/specialty campuses to reconcile to 102 total schools. | Q24: 2026-06-13
A25: Madison Metropolitan School District | B25: WI | C25: Madison | D25: 39 | E25: 25 | F25: 7 | G25: 18 | H25: 11.61 | I25: 195.44 | J25: 11 | K25: 8 | L25: 12 | M25: 32 | N25: 0 | O25: 52 | P25: https://www.madison.k12.wi.us/about | Q25: 2026-06-11 | R25: 11
A26: Metro Nashville Public Schools | B26: TN | C26: Nashville | D26: 24.4 | E26: 32.2 | F26: 3.8 | G26: 39.2 | H26: 16 | I26: 145 | J26: =100-SUM(D26:G26) | K26: 21 | L26: 28 | O26: 162 | P26: MNPS official schools directory high-school filter lists 21 high schools; middle/K-8 count remains from the public school-options list.
A27: Nassau County School District | B27: FL | C27: Northeast FL | D27: 75 | E27: 11 | F27: 2 | G27: 7 | H27: 15.55 | I27: 120 | J27: =100-SUM(D27:G27) | K27: 4 | L27: 3 | M27: 9 | N27: 1 | O27: 17 | P27: https://www.nassau.k12.fl.us/page/instructional-salaries ; https://files-backend.assets.thrillshare.com/documents/asset/uploaded_file/5569/Ncsd/f73c8433-23bf-4388-aa76-259dafad90d2/24-27_NTA_Ratified_Amended_with_Signatures__25.pdf ; https://nces.ed.gov/ccd/districtsearch/district_detail.asp?ID2=1201350 ; https://www.apartments.com/rent-market-trends/yulee-fl/ ; https://www.redfin.com/zipcode/32097/housing-market | Q27: 2026-06-13 | R27: 5
A28: North Clackamas School District | B28: OR | C28: Portland | D28: 56 | E28: 20 | F28: 12 | G28: 3 | H28: 19.32 | I28: 250 | J28: =100-SUM(D28:G28) | K28: 5 | L28: 4 | M28: 18 | N28: 5 | O28: 32 | P28: District page lists 32 schools total; counts entered as 18 elementary, 4 middle, 5 high, 5 charter/CTE/specialty.
A29: Oakland Unified School District | B29: CA | C29: Bay Area | D29: 12 | E29: 47 | F29: 11 | G29: 20 | H29: 19 | I29: 337 | J29: =100-SUM(D29:G29) | O29: 80
A30: Ocean Springs School District | B30: MS | C30: Mississippi Gulf Coast | D30: 69.19 | E30: 9.02 | F30: 2.89 | G30: 12.61 | H30: 13.65 | I30: 90 | J30: =100-SUM(D30:G30) | K30: 1 | L30: 1 | M30: 4 | N30: 1 | O30: 7 | P30: NCES lists 7 schools. Counts categorize Ocean Springs High as high, Ocean Springs Middle as middle, Ocean Springs Upper Elementary plus Magnolia/Oak/Pecan Park as elementary, and Keys Vocational Center as other/specialty. Demographic percentages are summed from NCES school-level race/ethnicity counts; Other includes American Indian/Alaska Native, Native Hawaiian/Pacific Islander, and Two or More Races.
A31: Oxnard Union High School District | B31: CA | C31: Southern California | D31: 15 | E31: 80 | F31: 2 | G31: 2 | H31: 25 | I31: 185 | J31: =100-SUM(D31:G31) | K31: 12 | L31: 0 | M31: 0 | N31: 0 | O31: 12
A32: Portland Public Schools | B32: OR | C32: Portland | D32: 53.3 | E32: 18.4 | F32: 5.7 | G32: 8.3 | H32: 16.04 | I32: 275.71 | J32: =100-SUM(D32:G32) | K32: 10 | L32: 15 | M32: 45 | N32: 11 | O32: 81 | P32: PPS 2025-26 overview: 45 elementary, 10 K-8, 15 middle, 10 high, 1 K-12; total 81.
A33: Provo City School District | B33: UT | C33: Salt Lake Valley | D33: 56 | E33: 33 | F33: 2 | G33: 1 | H33: 20 | I33: 185 | J33: =100-SUM(D33:G33) | K33: 3 | L33: 2 | M33: 13 | N33: 0 | O33: 18
A34: Royal ISD | B34: TX | C34: Houston | D34: 7.9 | E34: 72.1 | F34: 1.2 | G34: 16.5 | H34: 16.81 | I34: 125 | J34: =100-SUM(D34:G34) | K34: 1 | L34: 1 | M34: 3 | N34: 1 | O34: 6 | P34: Royal ISD is a fast-growth district. Current district page lists six campuses, including Royal Prairie Elementary and Royal STEM Academy; NCES/Texas Tribune school counts lag current district listings. Substitute pay is provisional because the public 2023-2024 Substitute Pay Schedule listing did not expose the actual rate in searchable text.
A35: Saint Helena Unified School District | B35: CA | C35: Northern California | D35: 42 | E35: 53 | F35: 2 | G35: 1 | H35: 13.32 | I35: 275 | J35: =100-SUM(D35:G35) | K35: 1 | L35: 1 | M35: 2 | N35: 1 | O35: 5 | P35: District site lists St. Helena High, Robert Louis Stevenson Middle, St. Helena Elementary, St. Helena Primary, and St. Helena Opportunities Program; NCES lists 5 total schools.
A36: Salt Lake School District | B36: UT | C36: Salt Lake Valley | D36: 40 | E36: 40 | F36: 5 | G36: 5 | H36: 17 | I36: 189 | J36: =100-SUM(D36:G36) | K36: 5 | L36: 5 | M36: 21 | N36: 4 | O36: 35
A37: San Antonio ISD | B37: TX | C37: San Antonio | D37: 3 | E37: 89.6 | F37: 1.4 | G37: 6 | H37: 14.95 | I37: 140 | J37: =100-SUM(D37:G37) | K37: 14 | L37: 12 | M37: 51 | N37: 6 | O37: 83 | P37: Campus counts from Texas Tribune Schools Explorer. Demographic fields use Hispanic share from Texas Tribune, Black share from Express-News, and remaining minority/white share estimated from Public School Review summary.
A38: San Diego Unified School District | B38: CA | C38: Southern California | D38: 24 | E38: 45 | F38: 14 | G38: 7 | H38: 22 | I38: 250 | J38: =100-SUM(D38:G38) | K38: 22 | L38: 24 | M38: 117 | N38: 13 | O38: 176
A39: San Jose Unified School District | B39: CA | C39: Bay Area | D39: 21 | E39: 54 | F39: 16 | G39: 2 | H39: 21 | I39: 200 | J39: =100-SUM(D39:G39) | K39: 6 | L39: 6 | M39: 26 | N39: 3 | O39: 41
A40: Scarsdale Union Free School District | B40: NY | C40: Westchester NY | D40: 55 | E40: 9 | F40: 27 | G40: 1 | H40: 11.21 | I40: 163 | J40: 8 | K40: 1 | L40: 1 | M40: 5 | N40: 0 | O40: 7 | P40: https://www.scarsdaleschools.k12.ny.us/119192_3 ; https://go.boarddocs.com/ny/scarsdale/Board.nsf/files/D5WQJL66FCE9/%24file/MOA%20with%20Scarsdale%20Teachers%20Association%20%28STA%29.pdf ; https://www.scarsdaleschools.org/index.php?articleID=74973066&pageID=smartSiteFeed&psqFeed=true ; https://nces.ed.gov/ccd/districtsearch/district_detail.asp?ID2=3625950 ; https://www.redfin.com/city/16773/NY/Scarsdale/housing-market ; https://www.realtor.com/local/market/new-york/westchester-county/scarsdale ; https://www.indeed.com/cmp/Scarsdale-Public-Schools/salaries/Substitute-Teacher/Scarsdale-NY | Q40: 2026-06-11 | R40: 8
A41: South Pasadena Unified School District | B41: CA | C41: Southern California | D41: 21.6 | E41: 23.2 | F41: 33.8 | G41: 1 | H41: 24.37 | I41: 200 | J41: =100-SUM(D41:G41) | K41: 1 | L41: 1 | M41: 3 | N41: 0 | O41: 5 | P41: NCES lists 5 total schools. SPUSD website lists three elementary schools, one middle school, and one high school. Substitute rate uses latest public EdJoin posting found ($200 full-day daily rate; posting year 2022-23, so verify before relying on current hiring).
A42: Syosset Central School District | B42: NY | C42: Long Island | D42: 39.4 | E42: 4.6 | F42: 52.4 | G42: 0.6 | H42: 10.28 | I42: 160 | J42: =100-SUM(D42:G42) | K42: 1 | L42: 2 | M42: 7 | N42: 0 | O42: 10 | P42: NCES lists 10 total schools; district school list shows seven elementary schools, two middle schools, and one high school.
A43: West Des Moines Community Schools | B43: IA | C43: Des Moines | D43: 53.2 | E43: 21.5 | F43: 5.9 | G43: 11.7 | H43: 14.5 | I43: 170 | J43: =100-SUM(D43:G43) | K43: 2 | L43: 2 | M43: 8 | N43: 1 | O43: 13 | P43: https://www.wdmcs.org/our-district/departments/human-resources ; https://resources.finalsite.net/images/v1745950877/wdmcsorg/ak8isa1vu50msa93nxgy/CombinedSalarySchedule.pdf ; https://www.kcci.com/article/west-des-moines-school-board-substitute-teacher-pay-increase/62347446 ; https://nces.ed.gov/ccd/districtsearch/district_detail.asp?ID2=1930930 ; https://www.niche.com/k12/d/west-des-moines-community-school-district-ia/students/ ; https://www.redfin.com/city/20722/IA/West-Des-Moines/housing-market ; https://www.apartments.com/rent-market-trends/west-des-moines-ia/ | Q43: 2026-06-13 | R43: 7.7
A44: Middleton-Cross Plains Area School District | B44: WI | C44: Madison Area | D44: 62 | E44: 10 | F44: 8 | G44: 7 | H44: 13.3 | I44: 175 | J44: 13 | K44: 1 | L44: 3 | M44: 7 | N44: 1 | O44: 12 | P44: https://www.mcpasd.k12.wi.us/documents/services/employee-services/16682317 ; https://files-backend.assets.thrillshare.com/documents/asset/uploaded_file/1905/Mcpasd/69c6add5-b8ae-4b2e-8319-08609921f255/2025-2026-Certified-Staff-BA-%2455%2C000-Model---10.20.2025---Google-Sheets.pdf?disposition=inline | Q44: 2026-06-15 | R44: 13
A45: Sun Prairie Area School District | B45: WI | C45: Madison Area | D45: 54 | E45: 14 | F45: 9 | G45: 10 | H45: 13.2 | I45: 181 | J45: 13 | K45: 2 | L45: 3 | M45: 9 | N45: 1 | O45: 15 | P45: https://www.sunprairieschools.org/departments/human-resources/substitutes ; https://www.sunprairieschools.org/ | Q45: 2026-06-15 | R45: 13
A46: Waunakee Community School District | B46: WI | C46: Madison Area | D46: 79 | E46: 5 | F46: 5 | G46: 3 | H46: 14 | I46: 168 | J46: 8 | K46: 1 | L46: 1 | M46: 5 | N46: 1 | O46: 8 | P46: https://www.waunakee.k12.wi.us/departments/human-resources/substitute-resources ; https://www.waunakee.k12.wi.us/ | Q46: 2026-06-15 | R46: 8
A47: Verona Area School District | B47: WI | C47: Madison Area | D47: 63 | E47: 10 | F47: 13 | G47: 6 | H47: 13 | I47: 150 | J47: 8 | K47: 1 | L47: 2 | M47: 4 | N47: 1 | O47: 8 | P47: https://www.verona.k12.wi.us/departments/humanresources/compensation ; https://www.verona.k12.wi.us/departments/humanresources/careers/substitute-opportunities | Q47: 2026-06-15 | R47: 8
A48: Beaverton School District | B48: OR | C48: Portland Metro | D48: 43 | E48: 25 | F48: 14 | G48: 3 | H48: 18.5 | I48: 246 | J48: 15 | K48: 6 | L48: 8 | M48: 34 | N48: 4 | O48: 52 | P48: https://resources.finalsite.net/images/v1749503218/beavertonk12orus/gd7r4u3u8hlfjssjnbnh/25-26FINALCERTwExtResp.pdf ; https://www.beaverton.k12.or.us/departments/human-resources/applicants/beas | Q48: 2026-06-15 | R48: 15
A49: Indian Prairie School District 204 | B49: IL | C49: Chicago Suburbs | D49: 38 | E49: 18 | F49: 28 | G49: 10 | H49: 14 | I49: 258 | J49: 6 | K49: 4 | L49: 7 | M49: 21 | N49: 1 | O49: 33 | P49: https://www.ipsd.org/resources/data-transparency/contracts-and-agreements ; https://resources.finalsite.net/images/v1746461433/ipsdorg/ydag27zq4d3atey63stv/IPEA_2025-2026v3_12025.pdf ; Indeed substitute-teacher estimate first pass | Q49: 2026-06-15 | R49: 6
A50: Glenbrook High School District 225 | B50: IL | C50: Chicago North Shore | D50: 55 | E50: 16 | F50: 19 | G50: 4 | H50: 11.5 | I50: 246 | J50: 6 | K50: 2 | L50: 0 | M50: 0 | N50: 0 | O50: 2 | P50: https://www.glenbrook225.org/departments/human-resources/pay-transparency ; https://staff.glenbrook225.org/fs/resource-manager/view/beb41775-feea-40a8-83be-839d1aa2f9ee ; Indeed substitute/day first pass | Q50: 2026-06-15 | R50: 6
A51: Mounds View Public Schools | B51: MN | C51: Twin Cities | D51: 55 | E51: 12 | F51: 15 | G51: 10 | H51: 16.2 | I51: 200 | J51: 8 | K51: 2 | L51: 3 | M51: 8 | N51: 0 | O51: 13 | P51: https://resources.finalsite.net/images/v1767030040/moundsviewschoolsorg/krhc4zxvinezdkxxh8ik/Teachers25-27.pdf ; https://www.mvpschools.org/employment | Q51: 2026-06-15 | R51: 8
A52: Eden Prairie Schools | B52: MN | C52: Twin Cities | D52: 50 | E52: 11 | F52: 24 | G52: 6 | H52: 14.6 | I52: 183 | J52: 9 | K52: 1 | L52: 2 | M52: 5 | N52: 1 | O52: 9 | P52: https://resources.finalsite.net/images/v1757436498/edenprorg/llnxrprxcuuikx1elsuq/EPEA2025-2027FINALCONTRACT.pdf ; https://www.applitrack.com/edenpr/OnlineApp/default.aspx?AppliTrackJobID=3655&ref= | Q52: 2026-06-15 | R52: 9
A53: Naperville CUSD 203 | B53: IL | C53: Chicago Suburbs | D53: 47 | E53: 14 | F53: 30 | G53: 3 | H53: 13.3 | I53: 130 | J53: 6 | K53: 2 | L53: 5 | M53: 15 | N53: 1 | O53: 23 | P53: https://www.naperville203.org/departments-services/human-resources/collective-bargaining-agreements ; https://resources.finalsite.net/images/v1756143021/naperville203org/yzetsbkynvoe9x6mjgl7/importantsubstituteinformation-26.pdf | Q53: 2026-06-15 | R53: 6
A54: Minnetonka Public Schools | B54: MN | C54: Twin Cities Suburbs | D54: 73 | E54: 8 | F54: 11 | G54: 4 | H54: 17 | I54: 180 | J54: 4 | K54: 1 | L54: 3 | M54: 6 | N54: 2 | O54: 12 | P54: https://www.minnetonkaschools.org/district/departments/hr/employee-contracts | Q54: 2026-06-16 | R54: First-pass profile; substitute pay estimated pending direct HR verification.
A55: Wayzata Public Schools | B55: MN | C55: Twin Cities Suburbs | D55: 64 | E55: 9 | F55: 19 | G55: 4 | H55: 17 | I55: 165 | J55: 4 | K55: 1 | L55: 3 | M55: 9 | N55: 1 | O55: 14 | P55: https://www.wayzataschools.org/careers/reserve-teachers | Q55: 2026-06-16 | R55: District site lists 14 schools; reserve-teacher daily pay used for licensed sub pay.
A56: Rosemount-Apple Valley-Eagan ISD 196 | B56: MN | C56: Twin Cities Suburbs | D56: 54 | E56: 13 | F56: 14 | G56: 12 | H56: 15 | I56: 180 | J56: 7 | K56: 5 | L56: 6 | M56: 19 | N56: 3 | O56: 33 | P56: https://www.district196.org/services/human-resources/bargainingagreements | Q56: 2026-06-16 | R56: First-pass profile; substitute pay estimated pending direct HR verification.
A57: Edina Public Schools | B57: MN | C57: Twin Cities Suburbs | D57: 70 | E57: 7 | F57: 14 | G57: 5 | H57: 16.5 | I57: 170 | J57: 4 | K57: 1 | L57: 2 | M57: 6 | N57: 1 | O57: 10 | P57: https://www.edinaschools.org/careers | Q57: 2026-06-16 | R57: Edina partners with Kelly Education for substitutes; daily sub pay estimated pending Kelly/HR verification.
A58: New Trier Township High School District 203 | B58: IL | C58: Chicago North Shore | D58: 68 | E58: 8 | F58: 13 | G58: 3 | H58: 12 | I58: 147 | J58: 8 | K58: 2 | L58: 0 | M58: 0 | N58: 0 | O58: 2 | P58: https://www.newtrier.k12.il.us/our-district/administrative-departments/human-resources/employee-agreements | Q58: 2026-06-16 | R58: High-school-only district; salary lane is first-pass estimate from agreement/compensation sources; sub pay estimated from hourly public posting.
A59: Tahoe-Truckee Unified School District | B59: CA | C59: Northern California | D59: 57.6 | E59: 34.7 | F59: 0.6 | G59: 0.2 | H59: 18.81 | I59: 200 | J59: =100-SUM(D59:G59) | K59: 2 | L59: 2 | M59: 6 | N59: 2 | O59: 12 | P59: CDE 2025-26 DataQuest ethnicity; NCES 2024-25 ratio and total schools; CDE school directory lists active public schools; TTUSD substitute rates page lists $200 full-day base rate. | Q59: 2026-06-16
A60: Channelview ISD | B60: TX | C60: Houston | D60: 4 | E60: 84.6 | F60: 1 | G60: 8 | H60: 15.6 | I60: 140 | J60: 2.4 | K60: 2 | L60: 3 | M60: 6 | N60: 1 | O60: 12 | P60: https://www.cvisd.org/documents/departments/human-resources/23858250 ; https://schools.texastribune.org/districts/channelview-isd/ ; https://nces.ed.gov/ccd/districtsearch/district_detail.asp?ID2=4813590 ; https://www.redfin.com/city/22005/TX/Channelview/housing-market ; https://www.zillow.com/rental-manager/market-trends/channelview-tx/ | Q60: 2026-06-16 | R60: First-pass entry. Salary entered from Channelview's 2025-2026 classroom teacher hiring chart listing; verify exact step/lane values before final ranking. NCES total schools differs slightly from Texas Tribune campus count; NCES total used for total schools counted.
A61: Plano ISD | B61: TX | C61: Dallas-Fort Worth | D61: 31 | E61: 30.1 | F61: 24 | G61: 12 | H61: 13.75 | I61: 130 | J61: 2.9 | K61: 11 | L61: 11 | M61: 46 | N61: 9 | O61: 77 | P61: https://www.pisd.edu/employment/join-our-team/new-hire-salary-schedule-2026-2027 ; https://schools.texastribune.org/districts/plano-isd/ ; https://nces.ed.gov/ccd/districtsearch/district_detail.asp?ID2=4835100 ; https://www.redfin.com/city/30868/TX/Plano/housing-market ; https://www.zillow.com/rental-manager/market-trends/plano-tx/ ; https://www.pisd.edu/employment/join-our-team/substitutes | Q61: 2026-06-16 | R61: Uses Plano ISD 2026-27 new-hire certified teacher schedule because that current public schedule was available; verify if you want strict 2025-26 comparability. NCES total schools used; Texas Tribune campus counts shown in source.
A62: Galena Park ISD | B62: TX | C62: Houston | D62: 4 | E62: 82.3 | F62: 1 | G62: 10 | H62: 14.97 | I62: 125 | J62: 2.7 | K62: 6 | L62: 5 | M62: 15 | N62: 0 | O62: 26 | P62: https://resources.finalsite.net/images/v1750951951/galenaparkisdcom/jww1mosc7efiovvg7fwq/Compensation2025-2026-6.pdf ; https://schools.texastribune.org/districts/galena-park-isd/ ; https://nces.ed.gov/ccd/districtsearch/district_detail.asp?ID2=4820250 ; https://www.redfin.com/city/7154/TX/Galena-Park/housing-market ; https://www.realtor.com/local/market/texas/harris-county/galena-park | Q62: 2026-06-16 | R62: Official 2025-26 new-hire guide lists salary by experience and master's stipend. Housing uses a first-pass blend of Redfin sale price and Realtor.com rent/listing data.
A63: Deer Park ISD | B63: TX | C63: Houston | D63: 23 | E63: 66 | F63: 2 | G63: 6 | H63: 14.17 | I63: 130 | J63: 3 | K63: 2 | L63: 4 | M63: 8 | N63: 0 | O63: 14 | P63: https://www.dpisd.org/apps/pages/index.jsp?pREC_ID=1697247&type=d&uREC_ID=1567862 ; https://4.files.edl.io/534b/02/20/26/194807-9703d67d-bdec-48cd-88d6-613f9adb963b.pdf ; https://schools.texastribune.org/districts/deer-park-isd/ ; https://nces.ed.gov/ccd/districtsearch/district_detail.asp?ID2=4816530 ; https://www.redfin.com/city/5059/TX/Deer-Park/housing-market ; https://www.zillow.com/home-values/4324/deer-park-tx/ | Q63: 2026-06-16 | R63: Official DPISD compensation page provides 2025-26 instructional/professional range rather than a detailed new-hire step table; salary progression entered as first-pass estimate within published min/mid/max range.
A64: Port Arthur ISD | B64: TX | C64: Beaumont-Port Arthur | D64: 3 | E64: 54.4 | F64: 2 | G64: 39 | H64: 13.19 | I64: 115 | J64: 1.6 | K64: 2 | L64: 2 | M64: 9 | N64: 2 | O64: 15 | P64: https://www.paisd.org/departments/human-resources/teacher ; https://www.facebook.com/portarthurisd/photos/-big-news-from-paisd-20252026-pay-increase-new-teacher-starting-salary-55500-pay/1243011057838639/ ; https://schools.texastribune.org/districts/port-arthur-isd/ ; https://nces.ed.gov/ccd/districtsearch/district_detail.asp?ID2=4835400&Search=2 ; https://www.redfin.com/city/35689/TX/Port-Arthur/housing-market ; https://www.zillow.com/home-values/13364/port-arthur-tx/ ; https://www.mykelly.com/job/10237246-substitute-teacher-port-arthur-isd-port-arthur-tx-united-states/ | Q64: 2026-06-16 | R64: First-pass entry. Official PAISD page links a Google Drive salary schedule that was not machine-readable here; starting salary / increase bands and master's stipend were taken from the district's public announcement and should be verified against the actual schedule before final ranking.

Sheet Median Home and Rent Prices
A1: District | B1: State | C1: Area | D1: Median Home Price | E1: Median Rent | F1: Median Home Price per Sq Ft | G1: PPSF Source URL
A2: Alief ISD | B2: TX | C2: Alief, TX | D2: 215000 | E2: 1350 | F2: 113
A3: Arcadia Unified School District | B3: CA | C3: Arcadia, CA | D3: 1800000 | E3: 3290 | F3: 736
A4: Austin ISD | B4: TX | C4: Austin, TX | D4: 506276 | E4: 1956 | F4: 294
A5: Barbers Hill ISD | B5: TX | C5: Mont Belvieu, TX | D5: 457726 | E5: 1496 | F5: 190 | G5: https://www.redfin.com/city/12568/TX/Mont-Belvieu/housing-market ; https://www.apartments.com/rent-market-trends/mont-belvieu-tx/
A6: Canyons School District | B6: UT | C6: Sandy / Canyons District, UT | D6: 660000 | E6: 2084 | F6: 252
A7: Chandler Unified School District | B7: AZ | C7: Chandler, AZ | D7: 520000 | E7: 2388 | F7: 286
A8: Chapel Hill-Carrboro City Schools | B8: NC | C8: Chapel Hill, NC | D8: 634403 | E8: 1850 | F8: 296
A9: Cherry Creek School District | B9: CO | C9: Aurora & Centennial, CO average | D9: 556984 | E9: 2208 | F9: 255
A10: Chicago Public Schools | B10: IL | C10: Chicago, IL | D10: 419749 | E10: 2406 | F10: 303
A11: Cobb County School District | B11: GA | C11: Marietta / Cobb County, GA | D11: 475000 | E11: 1534 | F11: 212 | G11: https://media.cobbk12.org/media/WWWCobb/medialib/teacher-salary-schedule.56404f113440.pdf ; https://www.cobbk12.org/the-district ; https://www.cobbk12.org/cobb-schools-delivers-balanced-budget-focused-on-classrooms-safety-and-long-term-stability.128573 ; https://www.cobbk12.org/substitute-teacher ; https://nces.ed.gov/ccd/districtsearch/district_detail.asp?ID2=1301290 ; https://www.apartments.com/rent-market-trends/marietta-ga/ ; https://www.redfin.com/city/12766/GA/Marietta/housing-market
A12: Denver Public Schools | B12: CO | C12: Denver, CO | D12: 542000 | E12: 2000 | F12: 367
A13: Eanes ISD | B13: TX | C13: Austin 78746 / West Lake Hills, TX | D13: 1724921 | E13: 3900 | F13: 558
A14: Flagstaff Unified School District | B14: AZ | C14: Flagstaff, AZ | D14: 710000 | E14: 2300 | F14: 368
A15: Glendale Union High School District | B15: AZ | C15: Glendale, AZ | D15: 408630 | E15: 1987 | F15: 211
A16: Glendora Unified School District | B16: CA | C16: Glendora, CA | D16: 900000 | E16: 2700 | F16: 583
A17: Gwinnett County Public Schools | B17: GA | C17: Lawrenceville / Gwinnett County, GA | D17: 365000 | E17: 1718 | F17: 165 | G17: https://resources.finalsite.net/images/v1719000691/gcpsk12org/lmrrhx4bc5hdy3ivppap/2024-2025_Teacher_Salary_Scheduleeq.pdf ; https://www.gcpsk12.org/about-us/gcps-by-the-numbers ; https://www.gcpsk12.org/about-us/careers/hr-support/substitute-management/general-information ; https://nces.ed.gov/ccd/districtsearch/district_detail.asp?ID2=1302550 ; https://www.apartments.com/rent-market-trends/lawrenceville-ga/ ; https://www.redfin.com/city/11598/GA/Lawrenceville/housing-market
A18: Jordan District | B18: UT | C18: West Jordan, UT | D18: 580000 | E18: 1689 | F18: 232
A19: Katy ISD | B19: TX | C19: Katy, TX | D19: 350000 | E19: 1650 | F19: 160
A20: La Cañada Unified School District | B20: CA | C20: La Cañada Flintridge, CA | D20: 2499891 | E20: 5900 | F20: 1030
A21: Lake Washington School District | B21: WA | C21: Redmond / Kirkland, WA | D21: 1299222 | E21: 3061 | F21: 650 | G21: https://www.lwsd.org/employment/teachers-certificated-employees/salary-schedules ; https://nces.ed.gov/ccd/districtsearch/district_detail.asp?DistrictID=5304230 ; https://www.apartments.com/rent-market-trends/redmond-wa/ ; https://www.redfin.com/city/14913/WA/Redmond/housing-market ; https://www.lwsd.org/about/enrollment-report
A22: Leander ISD | B22: TX | C22: Austin, TX | D22: 512000 | E22: 1500 | F22: 190
A23: Los Angeles Unified | B23: CA | C23: Los Angeles, CA | D23: 956465 | E23: 2650 | F23: 634
A24: Loudoun County Public Schools | B24: VA | C24: Ashburn / Loudoun County, VA | D24: 679593 | E24: 2680 | F24: 309 | G24: https://www.redfin.com/city/29015/VA/Ashburn/housing-market
A25: Madison Metropolitan School District | B25: WI | C25: Madison, WI | D25: 439737 | E25: 1655 | F25: 261
A26: Metro Nashville Public Schools | B26: TN | C26: Nashville, TN | D26: 436355 | E26: 2195 | F26: 274
A27: Nassau County School District | B27: FL | C27: Yulee / Nassau County, FL | D27: 421075 | E27: 1834 | F27: 212 | G27: https://www.nassau.k12.fl.us/page/instructional-salaries ; https://files-backend.assets.thrillshare.com/documents/asset/uploaded_file/5569/Ncsd/f73c8433-23bf-4388-aa76-259dafad90d2/24-27_NTA_Ratified_Amended_with_Signatures__25.pdf ; https://nces.ed.gov/ccd/districtsearch/district_detail.asp?ID2=1201350 ; https://www.apartments.com/rent-market-trends/yulee-fl/ ; https://www.redfin.com/zipcode/32097/housing-market
A28: North Clackamas School District | B28: OR | C28: Milwaukie / North Clackamas, OR | D28: 518000 | E28: 1699 | F28: 279
A29: Oakland Unified School District | B29: CA | C29: Oakland, CA | D29: 850000 | E29: 2700 | F29: 577
A30: Ocean Springs School District | B30: MS | C30: Ocean Springs, MS | D30: 294824 | E30: 2100 | F30: 201
A31: Oxnard Union High School District | B31: CA | C31: Oxnard, CA | D31: 767000 | E31: 2912 | F31: 514
A32: Portland Public Schools | B32: OR | C32: Portland, OR | D32: 538687 | E32: 1725 | F32: 328
A33: Provo City School District | B33: UT | C33: Provo, UT | D33: 533000 | E33: 1550 | F33: 267
A34: Royal ISD | B34: TX | C34: Brookshire/Pattison, TX | D34: 335000 | E34: 2245 | F34: 161
A35: Saint Helena Unified School District | B35: CA | C35: St. Helena, CA | D35: 2323609 | E35: 5995 | F35: 903
A36: Salt Lake School District | B36: UT | C36: Salt Lake City, UT | D36: 580000 | E36: 1600 | F36: 372
A37: San Antonio ISD | B37: TX | C37: San Antonio, TX | D37: 260000 | E37: 1372 | F37: 151
A38: San Diego Unified School District | B38: CA | C38: San Diego, CA | D38: 1000000 | E38: 3039 | F38: 687
A39: San Jose Unified School District | B39: CA | C39: San Jose, CA | D39: 1500000 | E39: 3300 | F39: 878
A40: Scarsdale Union Free School District | B40: NY | C40: Scarsdale, NY | D40: 2088750 | E40: 5500 | F40: 752 | G40: https://www.redfin.com/city/16773/NY/Scarsdale/housing-market ; https://www.realtor.com/local/market/new-york/westchester-county/scarsdale
A41: South Pasadena Unified School District | B41: CA | C41: South Pasadena, CA | D41: 1918852 | E41: 2695 | F41: 962
A42: Syosset Central School District | B42: NY | C42: Syosset, NY | D42: 1096329 | E42: 5200 | F42: 559
A43: West Des Moines Community Schools | B43: IA | C43: West Des Moines, IA | D43: 327554 | E43: 1126 | F43: 211 | G43: https://www.wdmcs.org/our-district/departments/human-resources ; https://resources.finalsite.net/images/v1745950877/wdmcsorg/ak8isa1vu50msa93nxgy/CombinedSalarySchedule.pdf ; https://www.kcci.com/article/west-des-moines-school-board-substitute-teacher-pay-increase/62347446 ; https://nces.ed.gov/ccd/districtsearch/district_detail.asp?ID2=1930930 ; https://www.niche.com/k12/d/west-des-moines-community-school-district-ia/students/ ; https://www.redfin.com/city/20722/IA/West-Des-Moines/housing-market ; https://www.apartments.com/rent-market-trends/west-des-moines-ia/
A44: Middleton-Cross Plains Area School District | B44: WI | C44: Middleton, WI | D44: 568000 | E44: 1900 | F44: 254 | G44: Redfin/Apartments first-pass market lookup, 2026-06-15
A45: Sun Prairie Area School District | B45: WI | C45: Sun Prairie, WI | D45: 455000 | E45: 1550 | F45: 210 | G45: Redfin/Apartments first-pass market lookup, 2026-06-15
A46: Waunakee Community School District | B46: WI | C46: Waunakee, WI | D46: 540000 | E46: 1650 | F46: 220 | G46: Redfin/Apartments first-pass market lookup, 2026-06-15
A47: Verona Area School District | B47: WI | C47: Verona, WI | D47: 531000 | E47: 1735 | F47: 224 | G47: Redfin/Apartments first-pass market lookup, 2026-06-15
A48: Beaverton School District | B48: OR | C48: Beaverton, OR | D48: 575000 | E48: 1850 | F48: 299 | G48: Redfin/Apartments first-pass market lookup, 2026-06-15
A49: Indian Prairie School District 204 | B49: IL | C49: Naperville / Aurora, IL | D49: 475000 | E49: 1831 | F49: 250 | G49: Redfin/Apartments first-pass market lookup, 2026-06-15
A50: Glenbrook High School District 225 | B50: IL | C50: Glenview / Northbrook, IL | D50: 811015 | E50: 1957 | F50: 350 | G50: https://www.redfin.com/city/7628/IL/Glenview/housing-market ; https://www.apartments.com/rent-market-trends/glenview-il/
A51: Mounds View Public Schools | B51: MN | C51: Shoreview / Mounds View, MN | D51: 425000 | E51: 1500 | F51: 198 | G51: Redfin/Apartments first-pass market lookup, 2026-06-15
A52: Eden Prairie Schools | B52: MN | C52: Twin Cities / Eden Prairie, MN | D52: 515000 | E52: 1650 | F52: 221 | G52: Redfin/Apartments first-pass market lookup, 2026-06-15
A53: Naperville CUSD 203 | B53: IL | C53: Naperville, IL | D53: 600000 | E53: 1831 | F53: 265 | G53: https://www.apartments.com/rent-market-trends/naperville-il/ ; Redfin first-pass market lookup, 2026-06-15
A54: Minnetonka Public Schools | B54: MN | C54: Minnetonka, MN | D54: 512000 | E54: 1730 | F54: 240 | G54: First-pass market estimate; verify with preferred housing/rent source.
... A64: Port Arthur ISD | B64: TX | C64: Port Arthur, TX | D64: 154907 | E64: 1331 | F64: 96 | G64: https://www.paisd.org/departments/human-resources/teacher ; https://www.facebook.com/portarthurisd/photos/-big-news-from-paisd-20252026-pay-increase-new-teacher-starting-salary-55500-pay/1243011057838639/ ; https://schools.texastribune.org/districts/port-arthur-isd/ ; https://nces.ed.gov/ccd/districtsearch/district_detail.asp?ID2=4835400&Search=2 ; https://www.redfin.com/city/35689/TX/Port-Arthur/housing-market ; https://www.zillow.com/home-values/13364/port-arthur-tx/ ; https://www.mykelly.com/job/10237246-substitute-teacher-port-arthur-isd-port-arthur-tx-united-states/

Sheet District Value Scores
A1: District | B1: State | C1: Region | D1: BA Start | E1: BA 5-Year | F1: BA 10-Year | G1: MA Start | H1: MA 5-Year | I1: MA 10-Year | J1: Avg Start Salary | K1: Avg 10-Year Salary | L1: Avg Growth % | M1: Master's Premium | N1: Median Home Price | O1: Median Rent | P1: Student-Teacher Ratio | Q1: Licensed Sub Pay | R1: Salary Level Score | S1: Growth Score | T1: Master's Premium Score | U1: Salary Score | V1: Affordability Score | W1: Student-Teacher Ratio Score | X1: Sub Pay Score | Y1: Demographic Balance Score | Z1: Overall Value Score | AA1: Median Home Price per Sq Ft | AB1: Price per Sq Ft Score | AC1: Other % | AD1: Sub Pay Housing Power | AE1: Stability Score | AF1: Pre-Risk Overall | AG1: Risk Multiplier | AH1: Risk-Adjusted Note
A2: Alief ISD | B2: =IFERROR(INDEX('School District Profiles'!$B$2:$B$58,MATCH($A2,'School District Profiles'!$A$2:$A$58,0)),"") | C2: =IFERROR(INDEX('School District Profiles'!$C$2:$C$58,MATCH($A2,'School District Profiles'!$A$2:$A$58,0)),"") | D2: =SUMIFS('Teacher Salary Data'!$E$2:$E$1277,'Teacher Salary Data'!$A$2:$A$1277,$A2,'Teacher Salary Data'!$C$2:$C$1277,"Bachelor's",'Teacher Salary Data'!$D$2:$D$1277,0) | E2: =SUMIFS('Teacher Salary Data'!$E$2:$E$1277,'Teacher Salary Data'!$A$2:$A$1277,$A2,'Teacher Salary Data'!$C$2:$C$1277,"Bachelor's",'Teacher Salary Data'!$D$2:$D$1277,5) | F2: =SUMIFS('Teacher Salary Data'!$E$2:$E$1277,'Teacher Salary Data'!$A$2:$A$1277,$A2,'Teacher Salary Data'!$C$2:$C$1277,"Bachelor's",'Teacher Salary Data'!$D$2:$D$1277,10) | G2: =SUMIFS('Teacher Salary Data'!$E$2:$E$1277,'Teacher Salary Data'!$A$2:$A$1277,$A2,'Teacher Salary Data'!$C$2:$C$1277,"Master's",'Teacher Salary Data'!$D$2:$D$1277,0) | H2: =SUMIFS('Teacher Salary Data'!$E$2:$E$1277,'Teacher Salary Data'!$A$2:$A$1277,$A2,'Teacher Salary Data'!$C$2:$C$1277,"Master's",'Teacher Salary Data'!$D$2:$D$1277,5) | I2: =SUMIFS('Teacher Salary Data'!$E$2:$E$1277,'Teacher Salary Data'!$A$2:$A$1277,$A2,'Teacher Salary Data'!$C$2:$C$1277,"Master's",'Teacher Salary Data'!$D$2:$D$1277,10) | J2: =AVERAGE(D2,G2) | K2: =AVERAGE(F2,I2) | L2: =IFERROR((K2-J2)/J2,0) | M2: =G2-D2 | N2: =IFERROR(INDEX('Median Home and Rent Prices'!$D$2:$D$58,MATCH($A2,'Median Home and Rent Prices'!$A$2:$A$58,0)),0) | O2: =IFERROR(INDEX('Median Home and Rent Prices'!$E$2:$E$58,MATCH($A2,'Median Home and Rent Prices'!$A$2:$A$58,0)),0) | P2: =IFERROR(INDEX('School District Profiles'!$H$2:$H$58,MATCH($A2,'School District Profiles'!$A$2:$A$58,0)),0) | Q2: =IFERROR(INDEX('School District Profiles'!$I$2:$I$58,MATCH($A2,'School District Profiles'!$A$2:$A$58,0)),0) | R2: =IFERROR(MAX(0,MIN(100,(K2-50000)/(110000-50000)*100)),0) | S2: =IFERROR(MAX(0,MIN(100,L2/0.6*100)),0) | T2: =IFERROR(MAX(0,MIN(100,M2/15000*100)),0) | U2: =IFERROR(0.45*R2+0.4*S2+0.15*T2,0) | V2: =IFERROR(0.4*MAX(0,MIN(100,(((J2/12)/O2)-2)/(4-2)*100))+0.35*MAX(0,MIN(100,(8-(N2/K2))/(8-3)*100))+0.25*AB2,0) | W2: =IFERROR(MAX(0,MIN(100,(25-P2)/(25-12)*100)),0) | X2: =IFERROR(MAX(0,MIN(100,(AD2-1)/(3-1)*100))*IF(OR($A2="North Clackamas School District",$A2="Provo City School District"),0.6,1),0) | Y2: =IFERROR(MAX(0,MIN(100,(1-((IFERROR(INDEX('School District Profiles'!$D$2:$D$58,MATCH($A2,'School District Profiles'!$A$2:$A$58,0)),0)/100)^2+(IFERROR(INDEX('School District Profiles'!$E$2:$E$58,MATCH($A2,'School District Profiles'!$A$2:$A$58,0)),0)/100)^2+(IFERROR(INDEX('School District Profiles'!$F$2:$F$58,MATCH($A2,'School District Profiles'!$A$2:$A$58,0)),0)/100)^2+(IFERROR(INDEX('School District Profiles'!$G$2:$G$58,MATCH($A2,'School District Profiles'!$A$2:$A$58,0)),0)/100)^2+(AC2/100)^2))/0.8*100)),0) | Z2: =IFERROR(AF2*AG2,0) | AA2: =IFERROR(INDEX('Median Home and Rent Prices'!$F$2:$F$58,MATCH($A2,'Median Home and Rent Prices'!$A$2:$A$58,0)),0) | AB2: =IFERROR(MAX(0,MIN(100,(800-AA2)/(800-150)*100)),0) | AC2: =IFERROR(INDEX('School District Profiles'!$J$2:$J$58,MATCH($A2,'School District Profiles'!$A$2:$A$58,0)),0) | AD2: =IFERROR(Q2*20/O2,0) | AE2: =IFERROR(IF(AG2>=1,100,IF(AG2>=0.95,75,IF(AG2>=0.9,60,IF(AG2>=0.85,40,IF(AG2>=0.8,25,0))))),0) | AF2: =IFERROR(0.4*U2+0.3*V2+0.1*W2+0.1*X2+0.1*Y2,0) | AG2: 0.9 | AH2: 10% employment-stability penalty due to enrollment-loss pressure, charter competition, and budget-cut concerns.
A3: Arcadia Unified School District | B3: =IFERROR(INDEX('School District Profiles'!$B$2:$B$58,MATCH($A3,'School District Profiles'!$A$2:$A$58,0)),"") | C3: =IFERROR(INDEX('School District Profiles'!$C$2:$C$58,MATCH($A3,'School District Profiles'!$A$2:$A$58,0)),"") | D3: =SUMIFS('Teacher Salary Data'!$E$2:$E$1277,'Teacher Salary Data'!$A$2:$A$1277,$A3,'Teacher Salary Data'!$C$2:$C$1277,"Bachelor's",'Teacher Salary Data'!$D$2:$D$1277,0) | E3: =SUMIFS('Teacher Salary Data'!$E$2:$E$1277,'Teacher Salary Data'!$A$2:$A$1277,$A3,'Teacher Salary Data'!$C$2:$C$1277,"Bachelor's",'Teacher Salary Data'!$D$2:$D$1277,5) | F3: =SUMIFS('Teacher Salary Data'!$E$2:$E$1277,'Teacher Salary Data'!$A$2:$A$1277,$A3,'Teacher Salary Data'!$C$2:$C$1277,"Bachelor's",'Teacher Salary Data'!$D$2:$D$1277,10) | G3: =SUMIFS('Teacher Salary Data'!$E$2:$E$1277,'Teacher Salary Data'!$A$2:$A$1277,$A3,'Teacher Salary Data'!$C$2:$C$1277,"Master's",'Teacher Salary Data'!$D$2:$D$1277,0) | H3: =SUMIFS('Teacher Salary Data'!$E$2:$E$1277,'Teacher Salary Data'!$A$2:$A$1277,$A3,'Teacher Salary Data'!$C$2:$C$1277,"Master's",'Teacher Salary Data'!$D$2:$D$1277,5) | I3: =SUMIFS('Teacher Salary Data'!$E$2:$E$1277,'Teacher Salary Data'!$A$2:$A$1277,$A3,'Teacher Salary Data'!$C$2:$C$1277,"Master's",'Teacher Salary Data'!$D$2:$D$1277,10) | J3: =AVERAGE(D3,G3) | K3: =AVERAGE(F3,I3) | L3: =IFERROR((K3-J3)/J3,0) | M3: =G3-D3 | N3: =IFERROR(INDEX('Median Home and Rent Prices'!$D$2:$D$58,MATCH($A3,'Median Home and Rent Prices'!$A$2:$A$58,0)),0) | O3: =IFERROR(INDEX('Median Home and Rent Prices'!$E$2:$E$58,MATCH($A3,'Median Home and Rent Prices'!$A$2:$A$58,0)),0) | P3: =IFERROR(INDEX('School District Profiles'!$H$2:$H$58,MATCH($A3,'School District Profiles'!$A$2:$A$58,0)),0) | Q3: =IFERROR(INDEX('School District Profiles'!$I$2:$I$58,MATCH($A3,'School District Profiles'!$A$2:$A$58,0)),0) | R3: =IFERROR(MAX(0,MIN(100,(K3-50000)/(110000-50000)*100)),0) | S3: =IFERROR(MAX(0,MIN(100,L3/0.6*100)),0) | T3: =IFERROR(MAX(0,MIN(100,M3/15000*100)),0) | U3: =IFERROR(0.45*R3+0.4*S3+0.15*T3,0) | V3: =IFERROR(0.4*MAX(0,MIN(100,(((J3/12)/O3)-2)/(4-2)*100))+0.35*MAX(0,MIN(100,(8-(N3/K3))/(8-3)*100))+0.25*AB3,0) | W3: =IFERROR(MAX(0,MIN(100,(25-P3)/(25-12)*100)),0) | X3: =IFERROR(MAX(0,MIN(100,(AD3-1)/(3-1)*100))*IF(OR($A3="North Clackamas School District",$A3="Provo City School District"),0.6,1),0) | Y3: =IFERROR(MAX(0,MIN(100,(1-((IFERROR(INDEX('School District Profiles'!$D$2:$D$58,MATCH($A3,'School District Profiles'!$A$2:$A$58,0)),0)/100)^2+(IFERROR(INDEX('School District Profiles'!$E$2:$E$58,MATCH($A3,'School District Profiles'!$A$2:$A$58,0)),0)/100)^2+(IFERROR(INDEX('School District Profiles'!$F$2:$F$58,MATCH($A3,'School District Profiles'!$A$2:$A$58,0)),0)/100)^2+(IFERROR(INDEX('School District Profiles'!$G$2:$G$58,MATCH($A3,'School District Profiles'!$A$2:$A$58,0)),0)/100)^2+(AC3/100)^2))/0.8*100)),0) | Z3: =IFERROR(AF3*AG3,0) | AA3: =IFERROR(INDEX('Median Home and Rent Prices'!$F$2:$F$58,MATCH($A3,'Median Home and Rent Prices'!$A$2:$A$58,0)),0) | AB3: =IFERROR(MAX(0,MIN(100,(800-AA3)/(800-150)*100)),0) | AC3: =IFERROR(INDEX('School District Profiles'!$J$2:$J$58,MATCH($A3,'School District Profiles'!$A$2:$A$58,0)),0) | AD3: =IFERROR(Q3*20/O3,0) | AE3: =IFERROR(IF(AG3>=1,100,IF(AG3>=0.95,75,IF(AG3>=0.9,60,IF(AG3>=0.85,40,IF(AG3>=0.8,25,0))))),0) | AF3: =IFERROR(0.4*U3+0.3*V3+0.1*W3+0.1*X3+0.1*Y3,0) | AG3: 0.85 | AH3: 15% employment-stability penalty because district budget updates indicated teacher-layoff risk unless local funding support fills the gap.
A4: Austin ISD | B4: =IFERROR(INDEX('School District Profiles'!$B$2:$B$58,MATCH($A4,'School District Profiles'!$A$2:$A$58,0)),"") | C4: =IFERROR(INDEX('School District Profiles'!$C$2:$C$58,MATCH($A4,'School District Profiles'!$A$2:$A$58,0)),"") | D4: =SUMIFS('Teacher Salary Data'!$E$2:$E$1277,'Teacher Salary Data'!$A$2:$A$1277,$A4,'Teacher Salary Data'!$C$2:$C$1277,"Bachelor's",'Teacher Salary Data'!$D$2:$D$1277,0) | E4: =SUMIFS('Teacher Salary Data'!$E$2:$E$1277,'Teacher Salary Data'!$A$2:$A$1277,$A4,'Teacher Salary Data'!$C$2:$C$1277,"Bachelor's",'Teacher Salary Data'!$D$2:$D$1277,5) | F4: =SUMIFS('Teacher Salary Data'!$E$2:$E$1277,'Teacher Salary Data'!$A$2:$A$1277,$A4,'Teacher Salary Data'!$C$2:$C$1277,"Bachelor's",'Teacher Salary Data'!$D$2:$D$1277,10) | G4: =SUMIFS('Teacher Salary Data'!$E$2:$E$1277,'Teacher Salary Data'!$A$2:$A$1277,$A4,'Teacher Salary Data'!$C$2:$C$1277,"Master's",'Teacher Salary Data'!$D$2:$D$1277,0) | H4: =SUMIFS('Teacher Salary Data'!$E$2:$E$1277,'Teacher Salary Data'!$A$2:$A$1277,$A4,'Teacher Salary Data'!$C$2:$C$1277,"Master's",'Teacher Salary Data'!$D$2:$D$1277,5) | I4: =SUMIFS('Teacher Salary Data'!$E$2:$E$1277,'Teacher Salary Data'!$A$2:$A$1277,$A4,'Teacher Salary Data'!$C$2:$C$1277,"Master's",'Teacher Salary Data'!$D$2:$D$1277,10) | J4: =AVERAGE(D4,G4) | K4: =AVERAGE(F4,I4) | L4: =IFERROR((K4-J4)/J4,0) | M4: =G4-D4 | N4: =IFERROR(INDEX('Median Home and Rent Prices'!$D$2:$D$58,MATCH($A4,'Median Home and Rent Prices'!$A$2:$A$58,0)),0) | O4: =IFERROR(INDEX('Median Home and Rent Prices'!$E$2:$E$58,MATCH($A4,'Median Home and Rent Prices'!$A$2:$A$58,0)),0) | P4: =IFERROR(INDEX('School District Profiles'!$H$2:$H$58,MATCH($A4,'School District Profiles'!$A$2:$A$58,0)),0) | Q4: =IFERROR(INDEX('School District Profiles'!$I$2:$I$58,MATCH($A4,'School District Profiles'!$A$2:$A$58,0)),0) | R4: =IFERROR(MAX(0,MIN(100,(K4-50000)/(110000-50000)*100)),0) | S4: =IFERROR(MAX(0,MIN(100,L4/0.6*100)),0) | T4: =IFERROR(MAX(0,MIN(100,M4/15000*100)),0) | U4: =IFERROR(0.45*R4+0.4*S4+0.15*T4,0) | V4: =IFERROR(0.4*MAX(0,MIN(100,(((J4/12)/O4)-2)/(4-2)*100))+0.35*MAX(0,MIN(100,(8-(N4/K4))/(8-3)*100))+0.25*AB4,0) | W4: =IFERROR(MAX(0,MIN(100,(25-P4)/(25-12)*100)),0) | X4: =IFERROR(MAX(0,MIN(100,(AD4-1)/(3-1)*100))*IF(OR($A4="North Clackamas School District",$A4="Provo City School District"),0.6,1),0) | Y4: =IFERROR(MAX(0,MIN(100,(1-((IFERROR(INDEX('School District Profiles'!$D$2:$D$58,MATCH($A4,'School District Profiles'!$A$2:$A$58,0)),0)/100)^2+(IFERROR(INDEX('School District Profiles'!$E$2:$E$58,MATCH($A4,'School District Profiles'!$A$2:$A$58,0)),0)/100)^2+(IFERROR(INDEX('School District Profiles'!$F$2:$F$58,MATCH($A4,'School District Profiles'!$A$2:$A$58,0)),0)/100)^2+(IFERROR(INDEX('School District Profiles'!$G$2:$G$58,MATCH($A4,'School District Profiles'!$A$2:$A$58,0)),0)/100)^2+(AC4/100)^2))/0.8*100)),0) | Z4: =IFERROR(AF4*AG4,0) | AA4: =IFERROR(INDEX('Median Home and Rent Prices'!$F$2:$F$58,MATCH($A4,'Median Home and Rent Prices'!$A$2:$A$58,0)),0) | AB4: =IFERROR(MAX(0,MIN(100,(800-AA4)/(800-150)*100)),0) | AC4: =IFERROR(INDEX('School District Profiles'!$J$2:$J$58,MATCH($A4,'School District Profiles'!$A$2:$A$58,0)),0) | AD4: =IFERROR(Q4*20/O4,0) | AE4: =IFERROR(IF(AG4>=1,100,IF(AG4>=0.95,75,IF(AG4>=0.9,60,IF(AG4>=0.85,40,IF(AG4>=0.8,25,0))))),0) | AF4: =IFERROR(0.4*U4+0.3*V4+0.1*W4+0.1*X4+0.1*Y4,0) | AG4: 0.8 | AH4: 20% employment-stability penalty due to very large projected budget gap, planned job cuts, school-closure discussions, and possible governance/fiscal instability.
A5: Barbers Hill ISD | B5: =IFERROR(INDEX('School District Profiles'!$B$2:$B$58,MATCH($A5,'School District Profiles'!$A$2:$A$58,0)),"") | C5: =IFERROR(INDEX('School District Profiles'!$C$2:$C$58,MATCH($A5,'School District Profiles'!$A$2:$A$58,0)),"") | D5: =SUMIFS('Teacher Salary Data'!$E$2:$E$1277,'Teacher Salary Data'!$A$2:$A$1277,$A5,'Teacher Salary Data'!$C$2:$C$1277,"Bachelor's",'Teacher Salary Data'!$D$2:$D$1277,0) | E5: =SUMIFS('Teacher Salary Data'!$E$2:$E$1277,'Teacher Salary Data'!$A$2:$A$1277,$A5,'Teacher Salary Data'!$C$2:$C$1277,"Bachelor's",'Teacher Salary Data'!$D$2:$D$1277,5) | F5: =SUMIFS('Teacher Salary Data'!$E$2:$E$1277,'Teacher Salary Data'!$A$2:$A$1277,$A5,'Teacher Salary Data'!$C$2:$C$1277,"Bachelor's",'Teacher Salary Data'!$D$2:$D$1277,10) | G5: =SUMIFS('Teacher Salary Data'!$E$2:$E$1277,'Teacher Salary Data'!$A$2:$A$1277,$A5,'Teacher Salary Data'!$C$2:$C$1277,"Master's",'Teacher Salary Data'!$D$2:$D$1277,0) | H5: =SUMIFS('Teacher Salary Data'!$E$2:$E$1277,'Teacher Salary Data'!$A$2:$A$1277,$A5,'Teacher Salary Data'!$C$2:$C$1277,"Master's",'Teacher Salary Data'!$D$2:$D$1277,5) | I5: =SUMIFS('Teacher Salary Data'!$E$2:$E$1277,'Teacher Salary Data'!$A$2:$A$1277,$A5,'Teacher Salary Data'!$C$2:$C$1277,"Master's",'Teacher Salary Data'!$D$2:$D$1277,10) | J5: =AVERAGE(D5,G5) | K5: =AVERAGE(F5,I5) | L5: =IFERROR((K5-J5)/J5,0) | M5: =G5-D5 | N5: =IFERROR(INDEX('Median Home and Rent Prices'!$D$2:$D$58,MATCH($A5,'Median Home and Rent Prices'!$A$2:$A$58,0)),0) | O5: =IFERROR(INDEX('Median Home and Rent Prices'!$E$2:$E$58,MATCH($A5,'Median Home and Rent Prices'!$A$2:$A$58,0)),0) | P5: =IFERROR(INDEX('School District Profiles'!$H$2:$H$58,MATCH($A5,'School District Profiles'!$A$2:$A$58,0)),0) | Q5: =IFERROR(INDEX('School District Profiles'!$I$2:$I$58,MATCH($A5,'School District Profiles'!$A$2:$A$58,0)),0) | R5: =IFERROR(MAX(0,MIN(100,(K5-50000)/(110000-50000)*100)),0) | S5: =IFERROR(MAX(0,MIN(100,L5/0.6*100)),0) | T5: =IFERROR(MAX(0,MIN(100,M5/15000*100)),0) | U5: =IFERROR(0.45*R5+0.4*S5+0.15*T5,0) | V5: =IFERROR(0.4*MAX(0,MIN(100,(((J5/12)/O5)-2)/(4-2)*100))+0.35*MAX(0,MIN(100,(8-(N5/K5))/(8-3)*100))+0.25*AB5,0) | W5: =IFERROR(MAX(0,MIN(100,(25-P5)/(25-12)*100)),0) | X5: =IFERROR(MAX(0,MIN(100,(AD5-1)/(3-1)*100))*IF(OR($A5="North Clackamas School District",$A5="Provo City School District"),0.6,1),0) | Y5: =IFERROR(MAX(0,MIN(100,(1-((IFERROR(INDEX('School District Profiles'!$D$2:$D$58,MATCH($A5,'School District Profiles'!$A$2:$A$58,0)),0)/100)^2+(IFERROR(INDEX('School District Profiles'!$E$2:$E$58,MATCH($A5,'School District Profiles'!$A$2:$A$58,0)),0)/100)^2+(IFERROR(INDEX('School District Profiles'!$F$2:$F$58,MATCH($A5,'School District Profiles'!$A$2:$A$58,0)),0)/100)^2+(IFERROR(INDEX('School District Profiles'!$G$2:$G$58,MATCH($A5,'School District Profiles'!$A$2:$A$58,0)),0)/100)^2+(AC5/100)^2))/0.8*100)),0) | Z5: =IFERROR(AF5*AG5,0) | AA5: =IFERROR(INDEX('Median Home and Rent Prices'!$F$2:$F$58,MATCH($A5,'Median Home and Rent Prices'!$A$2:$A$58,0)),0) | AB5: =IFERROR(MAX(0,MIN(100,(800-AA5)/(800-150)*100)),0) | AC5: =IFERROR(INDEX('School District Profiles'!$J$2:$J$58,MATCH($A5,'School District Profiles'!$A$2:$A$58,0)),0) | AD5: =IFERROR(Q5*20/O5,0) | AE5: =IFERROR(IF(AG5>=1,100,IF(AG5>=0.95,75,IF(AG5>=0.9,60,IF(AG5>=0.85,40,IF(AG5>=0.8,25,0))))),0) | AF5: =IFERROR(0.4*U5+0.3*V5+0.1*W5+0.1*X5+0.1*Y5,0) | AG5: 1 | AH5: No penalty applied. Low current layoff risk: Barbers Hill shows strong enrollment growth and public-facing hiring/retention language; no current public evidence found of broad layoffs, closures, or fiscal-crisis cuts in this pass.
A6: Canyons School District | B6: =IFERROR(INDEX('School District Profiles'!$B$2:$B$58,MATCH($A6,'School District Profiles'!$A$2:$A$58,0)),"") | C6: =IFERROR(INDEX('School District Profiles'!$C$2:$C$58,MATCH($A6,'School District Profiles'!$A$2:$A$58,0)),"") | D6: =SUMIFS('Teacher Salary Data'!$E$2:$E$1277,'Teacher Salary Data'!$A$2:$A$1277,$A6,'Teacher Salary Data'!$C$2:$C$1277,"Bachelor's",'Teacher Salary Data'!$D$2:$D$1277,0) | E6: =SUMIFS('Teacher Salary Data'!$E$2:$E$1277,'Teacher Salary Data'!$A$2:$A$1277,$A6,'Teacher Salary Data'!$C$2:$C$1277,"Bachelor's",'Teacher Salary Data'!$D$2:$D$1277,5) | F6: =SUMIFS('Teacher Salary Data'!$E$2:$E$1277,'Teacher Salary Data'!$A$2:$A$1277,$A6,'Teacher Salary Data'!$C$2:$C$1277,"Bachelor's",'Teacher Salary Data'!$D$2:$D$1277,10) | G6: =SUMIFS('Teacher Salary Data'!$E$2:$E$1277,'Teacher Salary Data'!$A$2:$A$1277,$A6,'Teacher Salary Data'!$C$2:$C$1277,"Master's",'Teacher Salary Data'!$D$2:$D$1277,0) | H6: =SUMIFS('Teacher Salary Data'!$E$2:$E$1277,'Teacher Salary Data'!$A$2:$A$1277,$A6,'Teacher Salary Data'!$C$2:$C$1277,"Master's",'Teacher Salary Data'!$D$2:$D$1277,5) | I6: =SUMIFS('Teacher Salary Data'!$E$2:$E$1277,'Teacher Salary Data'!$A$2:$A$1277,$A6,'Teacher Salary Data'!$C$2:$C$1277,"Master's",'Teacher Salary Data'!$D$2:$D$1277,10) | J6: =AVERAGE(D6,G6) | K6: =AVERAGE(F6,I6) | L6: =IFERROR((K6-J6)/J6,0) | M6: =G6-D6 | N6: =IFERROR(INDEX('Median Home and Rent Prices'!$D$2:$D$58,MATCH($A6,'Median Home and Rent Prices'!$A$2:$A$58,0)),0) | O6: =IFERROR(INDEX('Median Home and Rent Prices'!$E$2:$E$58,MATCH($A6,'Median Home and Rent Prices'!$A$2:$A$58,0)),0) | P6: =IFERROR(INDEX('School District Profiles'!$H$2:$H$58,MATCH($A6,'School District Profiles'!$A$2:$A$58,0)),0) | Q6: =IFERROR(INDEX('School District Profiles'!$I$2:$I$58,MATCH($A6,'School District Profiles'!$A$2:$A$58,0)),0) | R6: =IFERROR(MAX(0,MIN(100,(K6-50000)/(110000-50000)*100)),0) | S6: =IFERROR(MAX(0,MIN(100,L6/0.6*100)),0) | T6: =IFERROR(MAX(0,MIN(100,M6/15000*100)),0) | U6: =IFERROR(0.45*R6+0.4*S6+0.15*T6,0) | V6: =IFERROR(0.4*MAX(0,MIN(100,(((J6/12)/O6)-2)/(4-2)*100))+0.35*MAX(0,MIN(100,(8-(N6/K6))/(8-3)*100))+0.25*AB6,0) | W6: =IFERROR(MAX(0,MIN(100,(25-P6)/(25-12)*100)),0) | X6: =IFERROR(MAX(0,MIN(100,(AD6-1)/(3-1)*100))*IF(OR($A6="North Clackamas School District",$A6="Provo City School District"),0.6,1),0) | Y6: =IFERROR(MAX(0,MIN(100,(1-((IFERROR(INDEX('School District Profiles'!$D$2:$D$58,MATCH($A6,'School District Profiles'!$A$2:$A$58,0)),0)/100)^2+(IFERROR(INDEX('School District Profiles'!$E$2:$E$58,MATCH($A6,'School District Profiles'!$A$2:$A$58,0)),0)/100)^2+(IFERROR(INDEX('School District Profiles'!$F$2:$F$58,MATCH($A6,'School District Profiles'!$A$2:$A$58,0)),0)/100)^2+(IFERROR(INDEX('School District Profiles'!$G$2:$G$58,MATCH($A6,'School District Profiles'!$A$2:$A$58,0)),0)/100)^2+(AC6/100)^2))/0.8*100)),0) | Z6: =IFERROR(AF6*AG6,0) | AA6: =IFERROR(INDEX('Median Home and Rent Prices'!$F$2:$F$58,MATCH($A6,'Median Home and Rent Prices'!$A$2:$A$58,0)),0) | AB6: =IFERROR(MAX(0,MIN(100,(800-AA6)/(800-150)*100)),0) | AC6: =IFERROR(INDEX('School District Profiles'!$J$2:$J$58,MATCH($A6,'School District Profiles'!$A$2:$A$58,0)),0) | AD6: =IFERROR(Q6*20/O6,0) | AE6: =IFERROR(IF(AG6>=1,100,IF(AG6>=0.95,75,IF(AG6>=0.9,60,IF(AG6>=0.85,40,IF(AG6>=0.8,25,0))))),0) | AF6: =IFERROR(0.4*U6+0.3*V6+0.1*W6+0.1*X6+0.1*Y6,0) | AG6: 0.9 | AH6: 10% employment-stability penalty due to declining enrollment and possible elementary-school changes/closures; no broad layoff evidence found in first pass.
A7: Chandler Unified School District | B7: =IFERROR(INDEX('School District Profiles'!$B$2:$B$58,MATCH($A7,'School District Profiles'!$A$2:$A$58,0)),"") | C7: =IFERROR(INDEX('School District Profiles'!$C$2:$C$58,MATCH($A7,'School District Profiles'!$A$2:$A$58,0)),"") | D7: =SUMIFS('Teacher Salary Data'!$E$2:$E$1277,'Teacher Salary Data'!$A$2:$A$1277,$A7,'Teacher Salary Data'!$C$2:$C$1277,"Bachelor's",'Teacher Salary Data'!$D$2:$D$1277,0) | E7: =SUMIFS('Teacher Salary Data'!$E$2:$E$1277,'Teacher Salary Data'!$A$2:$A$1277,$A7,'Teacher Salary Data'!$C$2:$C$1277,"Bachelor's",'Teacher Salary Data'!$D$2:$D$1277,5) | F7: =SUMIFS('Teacher Salary Data'!$E$2:$E$1277,'Teacher Salary Data'!$A$2:$A$1277,$A7,'Teacher Salary Data'!$C$2:$C$1277,"Bachelor's",'Teacher Salary Data'!$D$2:$D$1277,10) | G7: =SUMIFS('Teacher Salary Data'!$E$2:$E$1277,'Teacher Salary Data'!$A$2:$A$1277,$A7,'Teacher Salary Data'!$C$2:$C$1277,"Master's",'Teacher Salary Data'!$D$2:$D$1277,0) | H7: =SUMIFS('Teacher Salary Data'!$E$2:$E$1277,'Teacher Salary Data'!$A$2:$A$1277,$A7,'Teacher Salary Data'!$C$2:$C$1277,"Master's",'Teacher Salary Data'!$D$2:$D$1277,5) | I7: =SUMIFS('Teacher Salary Data'!$E$2:$E$1277,'Teacher Salary Data'!$A$2:$A$1277,$A7,'Teacher Salary Data'!$C$2:$C$1277,"Master's",'Teacher Salary Data'!$D$2:$D$1277,10) | J7: =AVERAGE(D7,G7) | K7: =AVERAGE(F7,I7) | L7: =IFERROR((K7-J7)/J7,0) | M7: =G7-D7 | N7: =IFERROR(INDEX('Median Home and Rent Prices'!$D$2:$D$58,MATCH($A7,'Median Home and Rent Prices'!$A$2:$A$58,0)),0) | O7: =IFERROR(INDEX('Median Home and Rent Prices'!$E$2:$E$58,MATCH($A7,'Median Home and Rent Prices'!$A$2:$A$58,0)),0) | P7: =IFERROR(INDEX('School District Profiles'!$H$2:$H$58,MATCH($A7,'School District Profiles'!$A$2:$A$58,0)),0) | Q7: =IFERROR(INDEX('School District Profiles'!$I$2:$I$58,MATCH($A7,'School District Profiles'!$A$2:$A$58,0)),0) | R7: =IFERROR(MAX(0,MIN(100,(K7-50000)/(110000-50000)*100)),0) | S7: =IFERROR(MAX(0,MIN(100,L7/0.6*100)),0) | T7: =IFERROR(MAX(0,MIN(100,M7/15000*100)),0) | U7: =IFERROR(0.45*R7+0.4*S7+0.15*T7,0) | V7: =IFERROR(0.4*MAX(0,MIN(100,(((J7/12)/O7)-2)/(4-2)*100))+0.35*MAX(0,MIN(100,(8-(N7/K7))/(8-3)*100))+0.25*AB7,0) | W7: =IFERROR(MAX(0,MIN(100,(25-P7)/(25-12)*100)),0) | X7: =IFERROR(MAX(0,MIN(100,(AD7-1)/(3-1)*100))*IF(OR($A7="North Clackamas School District",$A7="Provo City School District"),0.6,1),0) | Y7: =IFERROR(MAX(0,MIN(100,(1-((IFERROR(INDEX('School District Profiles'!$D$2:$D$58,MATCH($A7,'School District Profiles'!$A$2:$A$58,0)),0)/100)^2+(IFERROR(INDEX('School District Profiles'!$E$2:$E$58,MATCH($A7,'School District Profiles'!$A$2:$A$58,0)),0)/100)^2+(IFERROR(INDEX('School District Profiles'!$F$2:$F$58,MATCH($A7,'School District Profiles'!$A$2:$A$58,0)),0)/100)^2+(IFERROR(INDEX('School District Profiles'!$G$2:$G$58,MATCH($A7,'School District Profiles'!$A$2:$A$58,0)),0)/100)^2+(AC7/100)^2))/0.8*100)),0) | Z7: =IFERROR(AF7*AG7,0) | AA7: =IFERROR(INDEX('Median Home and Rent Prices'!$F$2:$F$58,MATCH($A7,'Median Home and Rent Prices'!$A$2:$A$58,0)),0) | AB7: =IFERROR(MAX(0,MIN(100,(800-AA7)/(800-150)*100)),0) | AC7: =IFERROR(INDEX('School District Profiles'!$J$2:$J$58,MATCH($A7,'School District Profiles'!$A$2:$A$58,0)),0) | AD7: =IFERROR(Q7*20/O7,0) | AE7: =IFERROR(IF(AG7>=1,100,IF(AG7>=0.95,75,IF(AG7>=0.9,60,IF(AG7>=0.85,40,IF(AG7>=0.8,25,0))))),0) | AF7: =IFERROR(0.4*U7+0.3*V7+0.1*W7+0.1*X7+0.1*Y7,0) | AG7: 0.85 | AH7: 15% employment-stability penalty due to declining enrollment, budget shortfall, and staffing-reduction/job-cut plan.
A8: Chapel Hill-Carrboro City Schools | B8: =IFERROR(INDEX('School District Profiles'!$B$2:$B$58,MATCH($A8,'School District Profiles'!$A$2:$A$58,0)),"") | C8: =IFERROR(INDEX('School District Profiles'!$C$2:$C$58,MATCH($A8,'School District Profiles'!$A$2:$A$58,0)),"") | D8: =SUMIFS('Teacher Salary Data'!$E$2:$E$1277,'Teacher Salary Data'!$A$2:$A$1277,$A8,'Teacher Salary Data'!$C$2:$C$1277,"Bachelor's",'Teacher Salary Data'!$D$2:$D$1277,0) | E8: =SUMIFS('Teacher Salary Data'!$E$2:$E$1277,'Teacher Salary Data'!$A$2:$A$1277,$A8,'Teacher Salary Data'!$C$2:$C$1277,"Bachelor's",'Teacher Salary Data'!$D$2:$D$1277,5) | F8: =SUMIFS('Teacher Salary Data'!$E$2:$E$1277,'Teacher Salary Data'!$A$2:$A$1277,$A8,'Teacher Salary Data'!$C$2:$C$1277,"Bachelor's",'Teacher Salary Data'!$D$2:$D$1277,10) | G8: =SUMIFS('Teacher Salary Data'!$E$2:$E$1277,'Teacher Salary Data'!$A$2:$A$1277,$A8,'Teacher Salary Data'!$C$2:$C$1277,"Master's",'Teacher Salary Data'!$D$2:$D$1277,0) | H8: =SUMIFS('Teacher Salary Data'!$E$2:$E$1277,'Teacher Salary Data'!$A$2:$A$1277,$A8,'Teacher Salary Data'!$C$2:$C$1277,"Master's",'Teacher Salary Data'!$D$2:$D$1277,5) | I8: =SUMIFS('Teacher Salary Data'!$E$2:$E$1277,'Teacher Salary Data'!$A$2:$A$1277,$A8,'Teacher Salary Data'!$C$2:$C$1277,"Master's",'Teacher Salary Data'!$D$2:$D$1277,10) | J8: =AVERAGE(D8,G8) | K8: =AVERAGE(F8,I8) | L8: =IFERROR((K8-J8)/J8,0) | M8: =G8-D8 | N8: =IFERROR(INDEX('Median Home and Rent Prices'!$D$2:$D$58,MATCH($A8,'Median Home and Rent Prices'!$A$2:$A$58,0)),0) | O8: =IFERROR(INDEX('Median Home and Rent Prices'!$E$2:$E$58,MATCH($A8,'Median Home and Rent Prices'!$A$2:$A$58,0)),0) | P8: =IFERROR(INDEX('School District Profiles'!$H$2:$H$58,MATCH($A8,'School District Profiles'!$A$2:$A$58,0)),0) | Q8: =IFERROR(INDEX('School District Profiles'!$I$2:$I$58,MATCH($A8,'School District Profiles'!$A$2:$A$58,0)),0) | R8: =IFERROR(MAX(0,MIN(100,(K8-50000)/(110000-50000)*100)),0) | S8: =IFERROR(MAX(0,MIN(100,L8/0.6*100)),0) | T8: =IFERROR(MAX(0,MIN(100,M8/15000*100)),0) | U8: =IFERROR(0.45*R8+0.4*S8+0.15*T8,0) | V8: =IFERROR(0.4*MAX(0,MIN(100,(((J8/12)/O8)-2)/(4-2)*100))+0.35*MAX(0,MIN(100,(8-(N8/K8))/(8-3)*100))+0.25*AB8,0) | W8: =IFERROR(MAX(0,MIN(100,(25-P8)/(25-12)*100)),0) | X8: =IFERROR(MAX(0,MIN(100,(AD8-1)/(3-1)*100))*IF(OR($A8="North Clackamas School District",$A8="Provo City School District"),0.6,1),0) | Y8: =IFERROR(MAX(0,MIN(100,(1-((IFERROR(INDEX('School District Profiles'!$D$2:$D$58,MATCH($A8,'School District Profiles'!$A$2:$A$58,0)),0)/100)^2+(IFERROR(INDEX('School District Profiles'!$E$2:$E$58,MATCH($A8,'School District Profiles'!$A$2:$A$58,0)),0)/100)^2+(IFERROR(INDEX('School District Profiles'!$F$2:$F$58,MATCH($A8,'School District Profiles'!$A$2:$A$58,0)),0)/100)^2+(IFERROR(INDEX('School District Profiles'!$G$2:$G$58,MATCH($A8,'School District Profiles'!$A$2:$A$58,0)),0)/100)^2+(AC8/100)^2))/0.8*100)),0) | Z8: =IFERROR(AF8*AG8,0) | AA8: =IFERROR(INDEX('Median Home and Rent Prices'!$F$2:$F$58,MATCH($A8,'Median Home and Rent Prices'!$A$2:$A$58,0)),0) | AB8: =IFERROR(MAX(0,MIN(100,(800-AA8)/(800-150)*100)),0) | AC8: =IFERROR(INDEX('School District Profiles'!$J$2:$J$58,MATCH($A8,'School District Profiles'!$A$2:$A$58,0)),0) | AD8: =IFERROR(Q8*20/O8,0) | AE8: =IFERROR(IF(AG8>=1,100,IF(AG8>=0.95,75,IF(AG8>=0.9,60,IF(AG8>=0.85,40,IF(AG8>=0.8,25,0))))),0) | AF8: =IFERROR(0.4*U8+0.3*V8+0.1*W8+0.1*X8+0.1*Y8,0) | AG8: 0.85 | AH8: 15% employment-stability penalty due to staff cuts, school-closure discussions, declining enrollment, and budget shortfall concerns.
A9: Cherry Creek School District | B9: =IFERROR(INDEX('School District Profiles'!$B$2:$B$58,MATCH($A9,'School District Profiles'!$A$2:$A$58,0)),"") | C9: =IFERROR(INDEX('School District Profiles'!$C$2:$C$58,MATCH($A9,'School District Profiles'!$A$2:$A$58,0)),"") | D9: =SUMIFS('Teacher Salary Data'!$E$2:$E$1277,'Teacher Salary Data'!$A$2:$A$1277,$A9,'Teacher Salary Data'!$C$2:$C$1277,"Bachelor's",'Teacher Salary Data'!$D$2:$D$1277,0) | E9: =SUMIFS('Teacher Salary Data'!$E$2:$E$1277,'Teacher Salary Data'!$A$2:$A$1277,$A9,'Teacher Salary Data'!$C$2:$C$1277,"Bachelor's",'Teacher Salary Data'!$D$2:$D$1277,5) | F9: =SUMIFS('Teacher Salary Data'!$E$2:$E$1277,'Teacher Salary Data'!$A$2:$A$1277,$A9,'Teacher Salary Data'!$C$2:$C$1277,"Bachelor's",'Teacher Salary Data'!$D$2:$D$1277,10) | G9: =SUMIFS('Teacher Salary Data'!$E$2:$E$1277,'Teacher Salary Data'!$A$2:$A$1277,$A9,'Teacher Salary Data'!$C$2:$C$1277,"Master's",'Teacher Salary Data'!$D$2:$D$1277,0) | H9: =SUMIFS('Teacher Salary Data'!$E$2:$E$1277,'Teacher Salary Data'!$A$2:$A$1277,$A9,'Teacher Salary Data'!$C$2:$C$1277,"Master's",'Teacher Salary Data'!$D$2:$D$1277,5) | I9: =SUMIFS('Teacher Salary Data'!$E$2:$E$1277,'Teacher Salary Data'!$A$2:$A$1277,$A9,'Teacher Salary Data'!$C$2:$C$1277,"Master's",'Teacher Salary Data'!$D$2:$D$1277,10) | J9: =AVERAGE(D9,G9) | K9: =AVERAGE(F9,I9) | L9: =IFERROR((K9-J9)/J9,0) | M9: =G9-D9 | N9: =IFERROR(INDEX('Median Home and Rent Prices'!$D$2:$D$58,MATCH($A9,'Median Home and Rent Prices'!$A$2:$A$58,0)),0) | O9: =IFERROR(INDEX('Median Home and Rent Prices'!$E$2:$E$58,MATCH($A9,'Median Home and Rent Prices'!$A$2:$A$58,0)),0) | P9: =IFERROR(INDEX('School District Profiles'!$H$2:$H$58,MATCH($A9,'School District Profiles'!$A$2:$A$58,0)),0) | Q9: =IFERROR(INDEX('School District Profiles'!$I$2:$I$58,MATCH($A9,'School District Profiles'!$A$2:$A$58,0)),0) | R9: =IFERROR(MAX(0,MIN(100,(K9-50000)/(110000-50000)*100)),0) | S9: =IFERROR(MAX(0,MIN(100,L9/0.6*100)),0) | T9: =IFERROR(MAX(0,MIN(100,M9/15000*100)),0) | U9: =IFERROR(0.45*R9+0.4*S9+0.15*T9,0) | V9: =IFERROR(0.4*MAX(0,MIN(100,(((J9/12)/O9)-2)/(4-2)*100))+0.35*MAX(0,MIN(100,(8-(N9/K9))/(8-3)*100))+0.25*AB9,0) | W9: =IFERROR(MAX(0,MIN(100,(25-P9)/(25-12)*100)),0) | X9: =IFERROR(MAX(0,MIN(100,(AD9-1)/(3-1)*100))*IF(OR($A9="North Clackamas School District",$A9="Provo City School District"),0.6,1),0) | Y9: =IFERROR(MAX(0,MIN(100,(1-((IFERROR(INDEX('School District Profiles'!$D$2:$D$58,MATCH($A9,'School District Profiles'!$A$2:$A$58,0)),0)/100)^2+(IFERROR(INDEX('School District Profiles'!$E$2:$E$58,MATCH($A9,'School District Profiles'!$A$2:$A$58,0)),0)/100)^2+(IFERROR(INDEX('School District Profiles'!$F$2:$F$58,MATCH($A9,'School District Profiles'!$A$2:$A$58,0)),0)/100)^2+(IFERROR(INDEX('School District Profiles'!$G$2:$G$58,MATCH($A9,'School District Profiles'!$A$2:$A$58,0)),0)/100)^2+(AC9/100)^2))/0.8*100)),0) | Z9: =IFERROR(AF9*AG9,0) | AA9: =IFERROR(INDEX('Median Home and Rent Prices'!$F$2:$F$58,MATCH($A9,'Median Home and Rent Prices'!$A$2:$A$58,0)),0) | AB9: =IFERROR(MAX(0,MIN(100,(800-AA9)/(800-150)*100)),0) | AC9: =IFERROR(INDEX('School District Profiles'!$J$2:$J$58,MATCH($A9,'School District Profiles'!$A$2:$A$58,0)),0) | AD9: =IFERROR(Q9*20/O9,0) | AE9: =IFERROR(IF(AG9>=1,100,IF(AG9>=0.95,75,IF(AG9>=0.9,60,IF(AG9>=0.85,40,IF(AG9>=0.8,25,0))))),0) | AF9: =IFERROR(0.4*U9+0.3*V9+0.1*W9+0.1*X9+0.1*Y9,0) | AG9: 0.85 | AH9: 15% employment-stability penalty due to announced job reductions and districtwide budget-cut plan.
A10: Chicago Public Schools | B10: =IFERROR(INDEX('School District Profiles'!$B$2:$B$58,MATCH($A10,'School District Profiles'!$A$2:$A$58,0)),"") | C10: =IFERROR(INDEX('School District Profiles'!$C$2:$C$58,MATCH($A10,'School District Profiles'!$A$2:$A$58,0)),"") | D10: =SUMIFS('Teacher Salary Data'!$E$2:$E$1277,'Teacher Salary Data'!$A$2:$A$1277,$A10,'Teacher Salary Data'!$C$2:$C$1277,"Bachelor's",'Teacher Salary Data'!$D$2:$D$1277,0) | E10: =SUMIFS('Teacher Salary Data'!$E$2:$E$1277,'Teacher Salary Data'!$A$2:$A$1277,$A10,'Teacher Salary Data'!$C$2:$C$1277,"Bachelor's",'Teacher Salary Data'!$D$2:$D$1277,5) | F10: =SUMIFS('Teacher Salary Data'!$E$2:$E$1277,'Teacher Salary Data'!$A$2:$A$1277,$A10,'Teacher Salary Data'!$C$2:$C$1277,"Bachelor's",'Teacher Salary Data'!$D$2:$D$1277,10) | G10: =SUMIFS('Teacher Salary Data'!$E$2:$E$1277,'Teacher Salary Data'!$A$2:$A$1277,$A10,'Teacher Salary Data'!$C$2:$C$1277,"Master's",'Teacher Salary Data'!$D$2:$D$1277,0) | H10: =SUMIFS('Teacher Salary Data'!$E$2:$E$1277,'Teacher Salary Data'!$A$2:$A$1277,$A10,'Teacher Salary Data'!$C$2:$C$1277,"Master's",'Teacher Salary Data'!$D$2:$D$1277,5) | I10: =SUMIFS('Teacher Salary Data'!$E$2:$E$1277,'Teacher Salary Data'!$A$2:$A$1277,$A10,'Teacher Salary Data'!$C$2:$C$1277,"Master's",'Teacher Salary Data'!$D$2:$D$1277,10) | J10: =AVERAGE(D10,G10) | K10: =AVERAGE(F10,I10) | L10: =IFERROR((K10-J10)/J10,0) | M10: =G10-D10 | N10: =IFERROR(INDEX('Median Home and Rent Prices'!$D$2:$D$58,MATCH($A10,'Median Home and Rent Prices'!$A$2:$A$58,0)),0) | O10: =IFERROR(INDEX('Median Home and Rent Prices'!$E$2:$E$58,MATCH($A10,'Median Home and Rent Prices'!$A$2:$A$58,0)),0) | P10: =IFERROR(INDEX('School District Profiles'!$H$2:$H$58,MATCH($A10,'School District Profiles'!$A$2:$A$58,0)),0) | Q10: =IFERROR(INDEX('School District Profiles'!$I$2:$I$58,MATCH($A10,'School District Profiles'!$A$2:$A$58,0)),0) | R10: =IFERROR(MAX(0,MIN(100,(K10-50000)/(110000-50000)*100)),0) | S10: =IFERROR(MAX(0,MIN(100,L10/0.6*100)),0) | T10: =IFERROR(MAX(0,MIN(100,M10/15000*100)),0) | U10: =IFERROR(0.45*R10+0.4*S10+0.15*T10,0) | V10: =IFERROR(0.4*MAX(0,MIN(100,(((J10/12)/O10)-2)/(4-2)*100))+0.35*MAX(0,MIN(100,(8-(N10/K10))/(8-3)*100))+0.25*AB10,0) | W10: =IFERROR(MAX(0,MIN(100,(25-P10)/(25-12)*100)),0) | X10: =IFERROR(MAX(0,MIN(100,(AD10-1)/(3-1)*100))*IF(OR($A10="North Clackamas School District",$A10="Provo City School District"),0.6,1),0) | Y10: =IFERROR(MAX(0,MIN(100,(1-((IFERROR(INDEX('School District Profiles'!$D$2:$D$58,MATCH($A10,'School District Profiles'!$A$2:$A$58,0)),0)/100)^2+(IFERROR(INDEX('School District Profiles'!$E$2:$E$58,MATCH($A10,'School District Profiles'!$A$2:$A$58,0)),0)/100)^2+(IFERROR(INDEX('School District Profiles'!$F$2:$F$58,MATCH($A10,'School District Profiles'!$A$2:$A$58,0)),0)/100)^2+(IFERROR(INDEX('School District Profiles'!$G$2:$G$58,MATCH($A10,'School District Profiles'!$A$2:$A$58,0)),0)/100)^2+(AC10/100)^2))/0.8*100)),0) | Z10: =IFERROR(AF10*AG10,0) | AA10: =IFERROR(INDEX('Median Home and Rent Prices'!$F$2:$F$58,MATCH($A10,'Median Home and Rent Prices'!$A$2:$A$58,0)),0) | AB10: =IFERROR(MAX(0,MIN(100,(800-AA10)/(800-150)*100)),0) | AC10: =IFERROR(INDEX('School District Profiles'!$J$2:$J$58,MATCH($A10,'School District Profiles'!$A$2:$A$58,0)),0) | AD10: =IFERROR(Q10*20/O10,0) | AE10: =IFERROR(IF(AG10>=1,100,IF(AG10>=0.95,75,IF(AG10>=0.9,60,IF(AG10>=0.85,40,IF(AG10>=0.8,25,0))))),0) | AF10: =IFERROR(0.4*U10+0.3*V10+0.1*W10+0.1*X10+0.1*Y10,0) | AG10: 0.85 | AH10: 15% employment-stability penalty due to structural deficit and reported teacher-position reductions / higher class-size planning.
A11: Cobb County School District | B11: =IFERROR(INDEX('School District Profiles'!$B$2:$B$58,MATCH($A11,'School District Profiles'!$A$2:$A$58,0)),"") | C11: =IFERROR(INDEX('School District Profiles'!$C$2:$C$58,MATCH($A11,'School District Profiles'!$A$2:$A$58,0)),"") | D11: =SUMIFS('Teacher Salary Data'!$E$2:$E$1277,'Teacher Salary Data'!$A$2:$A$1277,$A11,'Teacher Salary Data'!$C$2:$C$1277,"Bachelor's",'Teacher Salary Data'!$D$2:$D$1277,0) | E11: =SUMIFS('Teacher Salary Data'!$E$2:$E$1277,'Teacher Salary Data'!$A$2:$A$1277,$A11,'Teacher Salary Data'!$C$2:$C$1277,"Bachelor's",'Teacher Salary Data'!$D$2:$D$1277,5) | F11: =SUMIFS('Teacher Salary Data'!$E$2:$E$1277,'Teacher Salary Data'!$A$2:$A$1277,$A11,'Teacher Salary Data'!$C$2:$C$1277,"Bachelor's",'Teacher Salary Data'!$D$2:$D$1277,10) | G11: =SUMIFS('Teacher Salary Data'!$E$2:$E$1277,'Teacher Salary Data'!$A$2:$A$1277,$A11,'Teacher Salary Data'!$C$2:$C$1277,"Master's",'Teacher Salary Data'!$D$2:$D$1277,0) | H11: =SUMIFS('Teacher Salary Data'!$E$2:$E$1277,'Teacher Salary Data'!$A$2:$A$1277,$A11,'Teacher Salary Data'!$C$2:$C$1277,"Master's",'Teacher Salary Data'!$D$2:$D$1277,5) | I11: =SUMIFS('Teacher Salary Data'!$E$2:$E$1277,'Teacher Salary Data'!$A$2:$A$1277,$A11,'Teacher Salary Data'!$C$2:$C$1277,"Master's",'Teacher Salary Data'!$D$2:$D$1277,10) | J11: =AVERAGE(D11,G11) | K11: =AVERAGE(F11,I11) | L11: =IFERROR((K11-J11)/J11,0) | M11: =G11-D11 | N11: =IFERROR(INDEX('Median Home and Rent Prices'!$D$2:$D$58,MATCH($A11,'Median Home and Rent Prices'!$A$2:$A$58,0)),0) | O11: =IFERROR(INDEX('Median Home and Rent Prices'!$E$2:$E$58,MATCH($A11,'Median Home and Rent Prices'!$A$2:$A$58,0)),0) | P11: =IFERROR(INDEX('School District Profiles'!$H$2:$H$58,MATCH($A11,'School District Profiles'!$A$2:$A$58,0)),0) | Q11: =IFERROR(INDEX('School District Profiles'!$I$2:$I$58,MATCH($A11,'School District Profiles'!$A$2:$A$58,0)),0) | R11: =IFERROR(MAX(0,MIN(100,(K11-50000)/(110000-50000)*100)),0) | S11: =IFERROR(MAX(0,MIN(100,L11/0.6*100)),0) | T11: =IFERROR(MAX(0,MIN(100,M11/15000*100)),0) | U11: =IFERROR(0.45*R11+0.4*S11+0.15*T11,0) | V11: =IFERROR(0.4*MAX(0,MIN(100,(((J11/12)/O11)-2)/(4-2)*100))+0.35*MAX(0,MIN(100,(8-(N11/K11))/(8-3)*100))+0.25*AB11,0) | W11: =IFERROR(MAX(0,MIN(100,(25-P11)/(25-12)*100)),0) | X11: =IFERROR(MAX(0,MIN(100,(AD11-1)/(3-1)*100))*IF(OR($A11="North Clackamas School District",$A11="Provo City School District"),0.6,1),0) | Y11: =IFERROR(MAX(0,MIN(100,(1-((IFERROR(INDEX('School District Profiles'!$D$2:$D$58,MATCH($A11,'School District Profiles'!$A$2:$A$58,0)),0)/100)^2+(IFERROR(INDEX('School District Profiles'!$E$2:$E$58,MATCH($A11,'School District Profiles'!$A$2:$A$58,0)),0)/100)^2+(IFERROR(INDEX('School District Profiles'!$F$2:$F$58,MATCH($A11,'School District Profiles'!$A$2:$A$58,0)),0)/100)^2+(IFERROR(INDEX('School District Profiles'!$G$2:$G$58,MATCH($A11,'School District Profiles'!$A$2:$A$58,0)),0)/100)^2+(AC11/100)^2))/0.8*100)),0) | Z11: =IFERROR(AF11*AG11,0) | AA11: =IFERROR(INDEX('Median Home and Rent Prices'!$F$2:$F$58,MATCH($A11,'Median Home and Rent Prices'!$A$2:$A$58,0)),0) | AB11: =IFERROR(MAX(0,MIN(100,(800-AA11)/(800-150)*100)),0) | AC11: =IFERROR(INDEX('School District Profiles'!$J$2:$J$58,MATCH($A11,'School District Profiles'!$A$2:$A$58,0)),0) | AD11: =IFERROR(Q11*20/O11,0) | AE11: =IFERROR(IF(AG11>=1,100,IF(AG11>=0.95,75,IF(AG11>=0.9,60,IF(AG11>=0.85,40,IF(AG11>=0.8,25,0))))),0) | AF11: =IFERROR(0.4*U11+0.3*V11+0.1*W11+0.1*X11+0.1*Y11,0) | AG11: 1 | AH11: No penalty applied. Cobb's FY2027 public budget messaging states no teacher layoffs and emphasizes classroom stability; local reporting notes staffing reductions are handled through attrition/reassignment rather than layoffs.
A12: Denver Public Schools | B12: =IFERROR(INDEX('School District Profiles'!$B$2:$B$58,MATCH($A12,'School District Profiles'!$A$2:$A$58,0)),"") | C12: =IFERROR(INDEX('School District Profiles'!$C$2:$C$58,MATCH($A12,'School District Profiles'!$A$2:$A$58,0)),"") | D12: =SUMIFS('Teacher Salary Data'!$E$2:$E$1277,'Teacher Salary Data'!$A$2:$A$1277,$A12,'Teacher Salary Data'!$C$2:$C$1277,"Bachelor's",'Teacher Salary Data'!$D$2:$D$1277,0) | E12: =SUMIFS('Teacher Salary Data'!$E$2:$E$1277,'Teacher Salary Data'!$A$2:$A$1277,$A12,'Teacher Salary Data'!$C$2:$C$1277,"Bachelor's",'Teacher Salary Data'!$D$2:$D$1277,5) | F12: =SUMIFS('Teacher Salary Data'!$E$2:$E$1277,'Teacher Salary Data'!$A$2:$A$1277,$A12,'Teacher Salary Data'!$C$2:$C$1277,"Bachelor's",'Teacher Salary Data'!$D$2:$D$1277,10) | G12: =SUMIFS('Teacher Salary Data'!$E$2:$E$1277,'Teacher Salary Data'!$A$2:$A$1277,$A12,'Teacher Salary Data'!$C$2:$C$1277,"Master's",'Teacher Salary Data'!$D$2:$D$1277,0) | H12: =SUMIFS('Teacher Salary Data'!$E$2:$E$1277,'Teacher Salary Data'!$A$2:$A$1277,$A12,'Teacher Salary Data'!$C$2:$C$1277,"Master's",'Teacher Salary Data'!$D$2:$D$1277,5) | I12: =SUMIFS('Teacher Salary Data'!$E$2:$E$1277,'Teacher Salary Data'!$A$2:$A$1277,$A12,'Teacher Salary Data'!$C$2:$C$1277,"Master's",'Teacher Salary Data'!$D$2:$D$1277,10) | J12: =AVERAGE(D12,G12) | K12: =AVERAGE(F12,I12) | L12: =IFERROR((K12-J12)/J12,0) | M12: =G12-D12 | N12: =IFERROR(INDEX('Median Home and Rent Prices'!$D$2:$D$58,MATCH($A12,'Median Home and Rent Prices'!$A$2:$A$58,0)),0) | O12: =IFERROR(INDEX('Median Home and Rent Prices'!$E$2:$E$58,MATCH($A12,'Median Home and Rent Prices'!$A$2:$A$58,0)),0) | P12: =IFERROR(INDEX('School District Profiles'!$H$2:$H$58,MATCH($A12,'School District Profiles'!$A$2:$A$58,0)),0) | Q12: =IFERROR(INDEX('School District Profiles'!$I$2:$I$58,MATCH($A12,'School District Profiles'!$A$2:$A$58,0)),0) | R12: =IFERROR(MAX(0,MIN(100,(K12-50000)/(110000-50000)*100)),0) | S12: =IFERROR(MAX(0,MIN(100,L12/0.6*100)),0) | T12: =IFERROR(MAX(0,MIN(100,M12/15000*100)),0) | U12: =IFERROR(0.45*R12+0.4*S12+0.15*T12,0) | V12: =IFERROR(0.4*MAX(0,MIN(100,(((J12/12)/O12)-2)/(4-2)*100))+0.35*MAX(0,MIN(100,(8-(N12/K12))/(8-3)*100))+0.25*AB12,0) | W12: =IFERROR(MAX(0,MIN(100,(25-P12)/(25-12)*100)),0) | X12: =IFERROR(MAX(0,MIN(100,(AD12-1)/(3-1)*100))*IF(OR($A12="North Clackamas School District",$A12="Provo City School District"),0.6,1),0) | Y12: =IFERROR(MAX(0,MIN(100,(1-((IFERROR(INDEX('School District Profiles'!$D$2:$D$58,MATCH($A12,'School District Profiles'!$A$2:$A$58,0)),0)/100)^2+(IFERROR(INDEX('School District Profiles'!$E$2:$E$58,MATCH($A12,'School District Profiles'!$A$2:$A$58,0)),0)/100)^2+(IFERROR(INDEX('School District Profiles'!$F$2:$F$58,MATCH($A12,'School District Profiles'!$A$2:$A$58,0)),0)/100)^2+(IFERROR(INDEX('School District Profiles'!$G$2:$G$58,MATCH($A12,'School District Profiles'!$A$2:$A$58,0)),0)/100)^2+(AC12/100)^2))/0.8*100)),0) | Z12: =IFERROR(AF12*AG12,0) | AA12: =IFERROR(INDEX('Median Home and Rent Prices'!$F$2:$F$58,MATCH($A12,'Median Home and Rent Prices'!$A$2:$A$58,0)),0) | AB12: =IFERROR(MAX(0,MIN(100,(800-AA12)/(800-150)*100)),0) | AC12: =IFERROR(INDEX('School District Profiles'!$J$2:$J$58,MATCH($A12,'School District Profiles'!$A$2:$A$58,0)),0) | AD12: =IFERROR(Q12*20/O12,0) | AE12: =IFERROR(IF(AG12>=1,100,IF(AG12>=0.95,75,IF(AG12>=0.9,60,IF(AG12>=0.85,40,IF(AG12>=0.8,25,0))))),0) | AF12: =IFERROR(0.4*U12+0.3*V12+0.1*W12+0.1*X12+0.1*Y12,0) | AG12: 0.9 | AH12: 10% employment-stability penalty due to central-office layoffs, declining enrollment pressure, and warnings about possible additional school closures.
A13: Eanes ISD | B13: =IFERROR(INDEX('School District Profiles'!$B$2:$B$58,MATCH($A13,'School District Profiles'!$A$2:$A$58,0)),"") | C13: =IFERROR(INDEX('School District Profiles'!$C$2:$C$58,MATCH($A13,'School District Profiles'!$A$2:$A$58,0)),"") | D13: =SUMIFS('Teacher Salary Data'!$E$2:$E$1277,'Teacher Salary Data'!$A$2:$A$1277,$A13,'Teacher Salary Data'!$C$2:$C$1277,"Bachelor's",'Teacher Salary Data'!$D$2:$D$1277,0) | E13: =SUMIFS('Teacher Salary Data'!$E$2:$E$1277,'Teacher Salary Data'!$A$2:$A$1277,$A13,'Teacher Salary Data'!$C$2:$C$1277,"Bachelor's",'Teacher Salary Data'!$D$2:$D$1277,5) | F13: =SUMIFS('Teacher Salary Data'!$E$2:$E$1277,'Teacher Salary Data'!$A$2:$A$1277,$A13,'Teacher Salary Data'!$C$2:$C$1277,"Bachelor's",'Teacher Salary Data'!$D$2:$D$1277,10) | G13: =SUMIFS('Teacher Salary Data'!$E$2:$E$1277,'Teacher Salary Data'!$A$2:$A$1277,$A13,'Teacher Salary Data'!$C$2:$C$1277,"Master's",'Teacher Salary Data'!$D$2:$D$1277,0) | H13: =SUMIFS('Teacher Salary Data'!$E$2:$E$1277,'Teacher Salary Data'!$A$2:$A$1277,$A13,'Teacher Salary Data'!$C$2:$C$1277,"Master's",'Teacher Salary Data'!$D$2:$D$1277,5) | I13: =SUMIFS('Teacher Salary Data'!$E$2:$E$1277,'Teacher Salary Data'!$A$2:$A$1277,$A13,'Teacher Salary Data'!$C$2:$C$1277,"Master's",'Teacher Salary Data'!$D$2:$D$1277,10) | J13: =AVERAGE(D13,G13) | K13: =AVERAGE(F13,I13) | L13: =IFERROR((K13-J13)/J13,0) | M13: =G13-D13 | N13: =IFERROR(INDEX('Median Home and Rent Prices'!$D$2:$D$58,MATCH($A13,'Median Home and Rent Prices'!$A$2:$A$58,0)),0) | O13: =IFERROR(INDEX('Median Home and Rent Prices'!$E$2:$E$58,MATCH($A13,'Median Home and Rent Prices'!$A$2:$A$58,0)),0) | P13: =IFERROR(INDEX('School District Profiles'!$H$2:$H$58,MATCH($A13,'School District Profiles'!$A$2:$A$58,0)),0) | Q13: =IFERROR(INDEX('School District Profiles'!$I$2:$I$58,MATCH($A13,'School District Profiles'!$A$2:$A$58,0)),0) | R13: =IFERROR(MAX(0,MIN(100,(K13-50000)/(110000-50000)*100)),0) | S13: =IFERROR(MAX(0,MIN(100,L13/0.6*100)),0) | T13: =IFERROR(MAX(0,MIN(100,M13/15000*100)),0) | U13: =IFERROR(0.45*R13+0.4*S13+0.15*T13,0) | V13: =IFERROR(0.4*MAX(0,MIN(100,(((J13/12)/O13)-2)/(4-2)*100))+0.35*MAX(0,MIN(100,(8-(N13/K13))/(8-3)*100))+0.25*AB13,0) | W13: =IFERROR(MAX(0,MIN(100,(25-P13)/(25-12)*100)),0) | X13: =IFERROR(MAX(0,MIN(100,(AD13-1)/(3-1)*100))*IF(OR($A13="North Clackamas School District",$A13="Provo City School District"),0.6,1),0) | Y13: =IFERROR(MAX(0,MIN(100,(1-((IFERROR(INDEX('School District Profiles'!$D$2:$D$58,MATCH($A13,'School District Profiles'!$A$2:$A$58,0)),0)/100)^2+(IFERROR(INDEX('School District Profiles'!$E$2:$E$58,MATCH($A13,'School District Profiles'!$A$2:$A$58,0)),0)/100)^2+(IFERROR(INDEX('School District Profiles'!$F$2:$F$58,MATCH($A13,'School District Profiles'!$A$2:$A$58,0)),0)/100)^2+(IFERROR(INDEX('School District Profiles'!$G$2:$G$58,MATCH($A13,'School District Profiles'!$A$2:$A$58,0)),0)/100)^2+(AC13/100)^2))/0.8*100)),0) | Z13: =IFERROR(AF13*AG13,0) | AA13: =IFERROR(INDEX('Median Home and Rent Prices'!$F$2:$F$58,MATCH($A13,'Median Home and Rent Prices'!$A$2:$A$58,0)),0) | AB13: =IFERROR(MAX(0,MIN(100,(800-AA13)/(800-150)*100)),0) | AC13: =IFERROR(INDEX('School District Profiles'!$J$2:$J$58,MATCH($A13,'School District Profiles'!$A$2:$A$58,0)),0) | AD13: =IFERROR(Q13*20/O13,0) | AE13: =IFERROR(IF(AG13>=1,100,IF(AG13>=0.95,75,IF(AG13>=0.9,60,IF(AG13>=0.85,40,IF(AG13>=0.8,25,0))))),0) | AF13: =IFERROR(0.4*U13+0.3*V13+0.1*W13+0.1*X13+0.1*Y13,0) | AG13: 0.9 | AH13: 10% employment-stability penalty due to shortfall concerns, consolidation/closure actions, and cost-saving measures; recent cuts may partially stabilize the outlook.
... A58: New Trier Township High School District 203 | B58: =IFERROR(INDEX('School District Profiles'!$B$2:$B$58,MATCH($A58,'School District Profiles'!$A$2:$A$58,0)),"") | C58: =IFERROR(INDEX('School District Profiles'!$C$2:$C$58,MATCH($A58,'School District Profiles'!$A$2:$A$58,0)),"") | D58: =SUMIFS('Teacher Salary Data'!$E$2:$E$1277,'Teacher Salary Data'!$A$2:$A$1277,$A58,'Teacher Salary Data'!$C$2:$C$1277,"Bachelor's",'Teacher Salary Data'!$D$2:$D$1277,0) | E58: =SUMIFS('Teacher Salary Data'!$E$2:$E$1277,'Teacher Salary Data'!$A$2:$A$1277,$A58,'Teacher Salary Data'!$C$2:$C$1277,"Bachelor's",'Teacher Salary Data'!$D$2:$D$1277,5) | F58: =SUMIFS('Teacher Salary Data'!$E$2:$E$1277,'Teacher Salary Data'!$A$2:$A$1277,$A58,'Teacher Salary Data'!$C$2:$C$1277,"Bachelor's",'Teacher Salary Data'!$D$2:$D$1277,10) | G58: =SUMIFS('Teacher Salary Data'!$E$2:$E$1277,'Teacher Salary Data'!$A$2:$A$1277,$A58,'Teacher Salary Data'!$C$2:$C$1277,"Master's",'Teacher Salary Data'!$D$2:$D$1277,0) | H58: =SUMIFS('Teacher Salary Data'!$E$2:$E$1277,'Teacher Salary Data'!$A$2:$A$1277,$A58,'Teacher Salary Data'!$C$2:$C$1277,"Master's",'Teacher Salary Data'!$D$2:$D$1277,5) | I58: =SUMIFS('Teacher Salary Data'!$E$2:$E$1277,'Teacher Salary Data'!$A$2:$A$1277,$A58,'Teacher Salary Data'!$C$2:$C$1277,"Master's",'Teacher Salary Data'!$D$2:$D$1277,10) | J58: =AVERAGE(D58,G58) | K58: =AVERAGE(F58,I58) | L58: =IFERROR((K58-J58)/J58,0) | M58: =G58-D58 | N58: =IFERROR(INDEX('Median Home and Rent Prices'!$D$2:$D$58,MATCH($A58,'Median Home and Rent Prices'!$A$2:$A$58,0)),0) | O58: =IFERROR(INDEX('Median Home and Rent Prices'!$E$2:$E$58,MATCH($A58,'Median Home and Rent Prices'!$A$2:$A$58,0)),0) | P58: =IFERROR(INDEX('School District Profiles'!$H$2:$H$58,MATCH($A58,'School District Profiles'!$A$2:$A$58,0)),0) | Q58: =IFERROR(INDEX('School District Profiles'!$I$2:$I$58,MATCH($A58,'School District Profiles'!$A$2:$A$58,0)),0) | R58: =IFERROR(MAX(0,MIN(100,(K58-50000)/(110000-50000)*100)),0) | S58: =IFERROR(MAX(0,MIN(100,L58/0.6*100)),0) | T58: =IFERROR(MAX(0,MIN(100,M58/15000*100)),0) | U58: =IFERROR(0.45*R58+0.4*S58+0.15*T58,0) | V58: =IFERROR(0.4*MAX(0,MIN(100,(((J58/12)/O58)-2)/(4-2)*100))+0.35*MAX(0,MIN(100,(8-(N58/K58))/(8-3)*100))+0.25*AB58,0) | W58: =IFERROR(MAX(0,MIN(100,(25-P58)/(25-12)*100)),0) | X58: =IFERROR(MAX(0,MIN(100,(AD58-1)/(3-1)*100))*IF(OR($A58="North Clackamas School District",$A58="Provo City School District"),0.6,1),0) | Y58: =IFERROR(MAX(0,MIN(100,(1-((IFERROR(INDEX('School District Profiles'!$D$2:$D$58,MATCH($A58,'School District Profiles'!$A$2:$A$58,0)),0)/100)^2+(IFERROR(INDEX('School District Profiles'!$E$2:$E$58,MATCH($A58,'School District Profiles'!$A$2:$A$58,0)),0)/100)^2+(IFERROR(INDEX('School District Profiles'!$F$2:$F$58,MATCH($A58,'School District Profiles'!$A$2:$A$58,0)),0)/100)^2+(IFERROR(INDEX('School District Profiles'!$G$2:$G$58,MATCH($A58,'School District Profiles'!$A$2:$A$58,0)),0)/100)^2+(AC58/100)^2))/0.8*100)),0) | Z58: =IFERROR(AF58*AG58,0) | AA58: =IFERROR(INDEX('Median Home and Rent Prices'!$F$2:$F$58,MATCH($A58,'Median Home and Rent Prices'!$A$2:$A$58,0)),0) | AB58: =IFERROR(MAX(0,MIN(100,(800-AA58)/(800-150)*100)),0) | AC58: =IFERROR(INDEX('School District Profiles'!$J$2:$J$58,MATCH($A58,'School District Profiles'!$A$2:$A$58,0)),0) | AD58: =IFERROR(Q58*20/O58,0) | AE58: =IFERROR(IF(AG58>=1,100,IF(AG58>=0.95,75,IF(AG58>=0.9,60,IF(AG58>=0.85,40,IF(AG58>=0.8,25,0))))),0) | AF58: =IFERROR(0.4*U58+0.3*V58+0.1*W58+0.1*X58+0.1*Y58,0) | AG58: 1 | AH58: Round 3 first-pass entry; New Trier salary lane is estimated and housing affordability is very high-cost.
A59: Tahoe-Truckee Unified School District | B59: =IFERROR(INDEX('School District Profiles'!$B$2:$B$59,MATCH($A59,'School District Profiles'!$A$2:$A$59,0)),"") | C59: =IFERROR(INDEX('School District Profiles'!$C$2:$C$59,MATCH($A59,'School District Profiles'!$A$2:$A$59,0)),"") | D59: =SUMIFS('Teacher Salary Data'!$E$2:$E$1299,'Teacher Salary Data'!$A$2:$A$1299,$A59,'Teacher Salary Data'!$C$2:$C$1299,"Bachelor's",'Teacher Salary Data'!$D$2:$D$1299,0) | E59: =SUMIFS('Teacher Salary Data'!$E$2:$E$1299,'Teacher Salary Data'!$A$2:$A$1299,$A59,'Teacher Salary Data'!$C$2:$C$1299,"Bachelor's",'Teacher Salary Data'!$D$2:$D$1299,5) | F59: =SUMIFS('Teacher Salary Data'!$E$2:$E$1299,'Teacher Salary Data'!$A$2:$A$1299,$A59,'Teacher Salary Data'!$C$2:$C$1299,"Bachelor's",'Teacher Salary Data'!$D$2:$D$1299,10) | G59: =SUMIFS('Teacher Salary Data'!$E$2:$E$1299,'Teacher Salary Data'!$A$2:$A$1299,$A59,'Teacher Salary Data'!$C$2:$C$1299,"Master's",'Teacher Salary Data'!$D$2:$D$1299,0) | H59: =SUMIFS('Teacher Salary Data'!$E$2:$E$1299,'Teacher Salary Data'!$A$2:$A$1299,$A59,'Teacher Salary Data'!$C$2:$C$1299,"Master's",'Teacher Salary Data'!$D$2:$D$1299,5) | I59: =SUMIFS('Teacher Salary Data'!$E$2:$E$1299,'Teacher Salary Data'!$A$2:$A$1299,$A59,'Teacher Salary Data'!$C$2:$C$1299,"Master's",'Teacher Salary Data'!$D$2:$D$1299,10) | J59: =AVERAGE(D59,G59) | K59: =AVERAGE(F59,I59) | L59: =IFERROR((K59-J59)/J59,0) | M59: =G59-D59 | N59: =IFERROR(INDEX('Median Home and Rent Prices'!$D$2:$D$59,MATCH($A59,'Median Home and Rent Prices'!$A$2:$A$59,0)),0) | O59: =IFERROR(INDEX('Median Home and Rent Prices'!$E$2:$E$59,MATCH($A59,'Median Home and Rent Prices'!$A$2:$A$59,0)),0) | P59: =IFERROR(INDEX('School District Profiles'!$H$2:$H$59,MATCH($A59,'School District Profiles'!$A$2:$A$59,0)),0) | Q59: =IFERROR(INDEX('School District Profiles'!$I$2:$I$59,MATCH($A59,'School District Profiles'!$A$2:$A$59,0)),0) | R59: =IFERROR(MAX(0,MIN(100,(K59-50000)/(110000-50000)*100)),0) | S59: =IFERROR(MAX(0,MIN(100,L59/0.6*100)),0) | T59: =IFERROR(MAX(0,MIN(100,M59/15000*100)),0) | U59: =IFERROR(0.45*R59+0.4*S59+0.15*T59,0) | V59: =IFERROR(0.4*MAX(0,MIN(100,(((J59/12)/O59)-2)/(4-2)*100))+0.35*MAX(0,MIN(100,(8-(N59/K59))/(8-3)*100))+0.25*AB59,0) | W59: =IFERROR(MAX(0,MIN(100,(25-P59)/(25-12)*100)),0) | X59: =IFERROR(MAX(0,MIN(100,(AD59-1)/(3-1)*100))*IF(OR($A59="North Clackamas School District",$A59="Provo City School District"),0.6,1),0) | Y59: =IFERROR(MAX(0,MIN(100,(1-((IFERROR(INDEX('School District Profiles'!$D$2:$D$59,MATCH($A59,'School District Profiles'!$A$2:$A$59,0)),0)/100)^2+(IFERROR(INDEX('School District Profiles'!$E$2:$E$59,MATCH($A59,'School District Profiles'!$A$2:$A$59,0)),0)/100)^2+(IFERROR(INDEX('School District Profiles'!$F$2:$F$59,MATCH($A59,'School District Profiles'!$A$2:$A$59,0)),0)/100)^2+(IFERROR(INDEX('School District Profiles'!$G$2:$G$59,MATCH($A59,'School District Profiles'!$A$2:$A$59,0)),0)/100)^2+(AC59/100)^2))/0.8*100)),0) | Z59: =IFERROR(AF59*AG59,0) | AA59: =IFERROR(INDEX('Median Home and Rent Prices'!$F$2:$F$59,MATCH($A59,'Median Home and Rent Prices'!$A$2:$A$59,0)),0) | AB59: =IFERROR(MAX(0,MIN(100,(800-AA59)/(800-150)*100)),0) | AC59: =IFERROR(INDEX('School District Profiles'!$J$2:$J$59,MATCH($A59,'School District Profiles'!$A$2:$A$59,0)),0) | AD59: =IFERROR(Q59*20/O59,0) | AE59: =IFERROR(IF(AG59>=1,100,IF(AG59>=0.95,75,IF(AG59>=0.9,60,IF(AG59>=0.85,40,IF(AG59>=0.8,25,0))))),0) | AF59: =IFERROR(0.4*U59+0.3*V59+0.1*W59+0.1*X59+0.1*Y59,0) | AG59: 1 | AH59: No current employment-stability penalty applied; TTUSD is a Basic Aid/community-funded district and first-pass research did not find current broad layoff or closure evidence.
A60: Channelview ISD | B60: =IFERROR(INDEX('School District Profiles'!$B$2:$B$64,MATCH($A60,'School District Profiles'!$A$2:$A$64,0)),"") | C60: =IFERROR(INDEX('School District Profiles'!$C$2:$C$64,MATCH($A60,'School District Profiles'!$A$2:$A$64,0)),"") | D60: =SUMIFS('Teacher Salary Data'!$E$2:$E$1409,'Teacher Salary Data'!$A$2:$A$1409,$A60,'Teacher Salary Data'!$C$2:$C$1409,"Bachelor's",'Teacher Salary Data'!$D$2:$D$1409,0) | E60: =SUMIFS('Teacher Salary Data'!$E$2:$E$1409,'Teacher Salary Data'!$A$2:$A$1409,$A60,'Teacher Salary Data'!$C$2:$C$1409,"Bachelor's",'Teacher Salary Data'!$D$2:$D$1409,5) | F60: =SUMIFS('Teacher Salary Data'!$E$2:$E$1409,'Teacher Salary Data'!$A$2:$A$1409,$A60,'Teacher Salary Data'!$C$2:$C$1409,"Bachelor's",'Teacher Salary Data'!$D$2:$D$1409,10) | G60: =SUMIFS('Teacher Salary Data'!$E$2:$E$1409,'Teacher Salary Data'!$A$2:$A$1409,$A60,'Teacher Salary Data'!$C$2:$C$1409,"Master's",'Teacher Salary Data'!$D$2:$D$1409,0) | H60: =SUMIFS('Teacher Salary Data'!$E$2:$E$1409,'Teacher Salary Data'!$A$2:$A$1409,$A60,'Teacher Salary Data'!$C$2:$C$1409,"Master's",'Teacher Salary Data'!$D$2:$D$1409,5) | I60: =SUMIFS('Teacher Salary Data'!$E$2:$E$1409,'Teacher Salary Data'!$A$2:$A$1409,$A60,'Teacher Salary Data'!$C$2:$C$1409,"Master's",'Teacher Salary Data'!$D$2:$D$1409,10) | J60: =AVERAGE(D60,G60) | K60: =AVERAGE(F60,I60) | L60: =IFERROR((K60-J60)/J60,0) | M60: =G60-D60 | N60: =IFERROR(INDEX('Median Home and Rent Prices'!$D$2:$D$64,MATCH($A60,'Median Home and Rent Prices'!$A$2:$A$64,0)),0) | O60: =IFERROR(INDEX('Median Home and Rent Prices'!$E$2:$E$64,MATCH($A60,'Median Home and Rent Prices'!$A$2:$A$64,0)),0) | P60: =IFERROR(INDEX('School District Profiles'!$H$2:$H$64,MATCH($A60,'School District Profiles'!$A$2:$A$64,0)),0) | Q60: =IFERROR(INDEX('School District Profiles'!$I$2:$I$64,MATCH($A60,'School District Profiles'!$A$2:$A$64,0)),0) | R60: =IFERROR(MAX(0,MIN(100,(K60-50000)/(110000-50000)*100)),0) | S60: =IFERROR(MAX(0,MIN(100,L60/0.6*100)),0) | T60: =IFERROR(MAX(0,MIN(100,M60/15000*100)),0) | U60: =IFERROR(0.45*R60+0.4*S60+0.15*T60,0) | V60: =IFERROR(0.4*MAX(0,MIN(100,(((J60/12)/O60)-2)/(4-2)*100))+0.35*MAX(0,MIN(100,(8-(N60/K60))/(8-3)*100))+0.25*AB60,0) | W60: =IFERROR(MAX(0,MIN(100,(25-P60)/(25-12)*100)),0) | X60: =IFERROR(MAX(0,MIN(100,(AD60-1)/(3-1)*100))*IF(OR($A60="North Clackamas School District",$A60="Provo City School District"),0.6,1),0) | Y60: =IFERROR(MAX(0,MIN(100,(1-((IFERROR(INDEX('School District Profiles'!$D$2:$D$64,MATCH($A60,'School District Profiles'!$A$2:$A$64,0)),0)/100)^2+(IFERROR(INDEX('School District Profiles'!$E$2:$E$64,MATCH($A60,'School District Profiles'!$A$2:$A$64,0)),0)/100)^2+(IFERROR(INDEX('School District Profiles'!$F$2:$F$64,MATCH($A60,'School District Profiles'!$A$2:$A$64,0)),0)/100)^2+(IFERROR(INDEX('School District Profiles'!$G$2:$G$64,MATCH($A60,'School District Profiles'!$A$2:$A$64,0)),0)/100)^2+(AC60/100)^2))/0.8*100)),0) | Z60: =IFERROR(AF60*AG60,0) | AA60: =IFERROR(INDEX('Median Home and Rent Prices'!$F$2:$F$64,MATCH($A60,'Median Home and Rent Prices'!$A$2:$A$64,0)),0) | AB60: =IFERROR(MAX(0,MIN(100,(800-AA60)/(800-150)*100)),0) | AC60: =IFERROR(INDEX('School District Profiles'!$J$2:$J$64,MATCH($A60,'School District Profiles'!$A$2:$A$64,0)),0) | AD60: =IFERROR(Q60*20/O60,0) | AE60: =IFERROR(IF(AG60>=1,100,IF(AG60>=0.95,75,IF(AG60>=0.9,60,IF(AG60>=0.85,40,IF(AG60>=0.8,25,0))))),0) | AF60: =IFERROR(0.4*U60+0.3*V60+0.1*W60+0.1*X60+0.1*Y60,0) | AG60: 1 | AH60: No employment-stability penalty applied in this first-pass addition; verify with adopted budget, enrollment trend, board packets, and HR/union notices before final scoring.
A61: Plano ISD | B61: =IFERROR(INDEX('School District Profiles'!$B$2:$B$64,MATCH($A61,'School District Profiles'!$A$2:$A$64,0)),"") | C61: =IFERROR(INDEX('School District Profiles'!$C$2:$C$64,MATCH($A61,'School District Profiles'!$A$2:$A$64,0)),"") | D61: =SUMIFS('Teacher Salary Data'!$E$2:$E$1409,'Teacher Salary Data'!$A$2:$A$1409,$A61,'Teacher Salary Data'!$C$2:$C$1409,"Bachelor's",'Teacher Salary Data'!$D$2:$D$1409,0) | E61: =SUMIFS('Teacher Salary Data'!$E$2:$E$1409,'Teacher Salary Data'!$A$2:$A$1409,$A61,'Teacher Salary Data'!$C$2:$C$1409,"Bachelor's",'Teacher Salary Data'!$D$2:$D$1409,5) | F61: =SUMIFS('Teacher Salary Data'!$E$2:$E$1409,'Teacher Salary Data'!$A$2:$A$1409,$A61,'Teacher Salary Data'!$C$2:$C$1409,"Bachelor's",'Teacher Salary Data'!$D$2:$D$1409,10) | G61: =SUMIFS('Teacher Salary Data'!$E$2:$E$1409,'Teacher Salary Data'!$A$2:$A$1409,$A61,'Teacher Salary Data'!$C$2:$C$1409,"Master's",'Teacher Salary Data'!$D$2:$D$1409,0) | H61: =SUMIFS('Teacher Salary Data'!$E$2:$E$1409,'Teacher Salary Data'!$A$2:$A$1409,$A61,'Teacher Salary Data'!$C$2:$C$1409,"Master's",'Teacher Salary Data'!$D$2:$D$1409,5) | I61: =SUMIFS('Teacher Salary Data'!$E$2:$E$1409,'Teacher Salary Data'!$A$2:$A$1409,$A61,'Teacher Salary Data'!$C$2:$C$1409,"Master's",'Teacher Salary Data'!$D$2:$D$1409,10) | J61: =AVERAGE(D61,G61) | K61: =AVERAGE(F61,I61) | L61: =IFERROR((K61-J61)/J61,0) | M61: =G61-D61 | N61: =IFERROR(INDEX('Median Home and Rent Prices'!$D$2:$D$64,MATCH($A61,'Median Home and Rent Prices'!$A$2:$A$64,0)),0) | O61: =IFERROR(INDEX('Median Home and Rent Prices'!$E$2:$E$64,MATCH($A61,'Median Home and Rent Prices'!$A$2:$A$64,0)),0) | P61: =IFERROR(INDEX('School District Profiles'!$H$2:$H$64,MATCH($A61,'School District Profiles'!$A$2:$A$64,0)),0) | Q61: =IFERROR(INDEX('School District Profiles'!$I$2:$I$64,MATCH($A61,'School District Profiles'!$A$2:$A$64,0)),0) | R61: =IFERROR(MAX(0,MIN(100,(K61-50000)/(110000-50000)*100)),0) | S61: =IFERROR(MAX(0,MIN(100,L61/0.6*100)),0) | T61: =IFERROR(MAX(0,MIN(100,M61/15000*100)),0) | U61: =IFERROR(0.45*R61+0.4*S61+0.15*T61,0) | V61: =IFERROR(0.4*MAX(0,MIN(100,(((J61/12)/O61)-2)/(4-2)*100))+0.35*MAX(0,MIN(100,(8-(N61/K61))/(8-3)*100))+0.25*AB61,0) | W61: =IFERROR(MAX(0,MIN(100,(25-P61)/(25-12)*100)),0) | X61: =IFERROR(MAX(0,MIN(100,(AD61-1)/(3-1)*100))*IF(OR($A61="North Clackamas School District",$A61="Provo City School District"),0.6,1),0) | Y61: =IFERROR(MAX(0,MIN(100,(1-((IFERROR(INDEX('School District Profiles'!$D$2:$D$64,MATCH($A61,'School District Profiles'!$A$2:$A$64,0)),0)/100)^2+(IFERROR(INDEX('School District Profiles'!$E$2:$E$64,MATCH($A61,'School District Profiles'!$A$2:$A$64,0)),0)/100)^2+(IFERROR(INDEX('School District Profiles'!$F$2:$F$64,MATCH($A61,'School District Profiles'!$A$2:$A$64,0)),0)/100)^2+(IFERROR(INDEX('School District Profiles'!$G$2:$G$64,MATCH($A61,'School District Profiles'!$A$2:$A$64,0)),0)/100)^2+(AC61/100)^2))/0.8*100)),0) | Z61: =IFERROR(AF61*AG61,0) | AA61: =IFERROR(INDEX('Median Home and Rent Prices'!$F$2:$F$64,MATCH($A61,'Median Home and Rent Prices'!$A$2:$A$64,0)),0) | AB61: =IFERROR(MAX(0,MIN(100,(800-AA61)/(800-150)*100)),0) | AC61: =IFERROR(INDEX('School District Profiles'!$J$2:$J$64,MATCH($A61,'School District Profiles'!$A$2:$A$64,0)),0) | AD61: =IFERROR(Q61*20/O61,0) | AE61: =IFERROR(IF(AG61>=1,100,IF(AG61>=0.95,75,IF(AG61>=0.9,60,IF(AG61>=0.85,40,IF(AG61>=0.8,25,0))))),0) | AF61: =IFERROR(0.4*U61+0.3*V61+0.1*W61+0.1*X61+0.1*Y61,0) | AG61: 1 | AH61: No employment-stability penalty applied in this first-pass addition; verify with adopted budget, enrollment trend, board packets, and HR/union notices before final scoring.
A62: Galena Park ISD | B62: =IFERROR(INDEX('School District Profiles'!$B$2:$B$64,MATCH($A62,'School District Profiles'!$A$2:$A$64,0)),"") | C62: =IFERROR(INDEX('School District Profiles'!$C$2:$C$64,MATCH($A62,'School District Profiles'!$A$2:$A$64,0)),"") | D62: =SUMIFS('Teacher Salary Data'!$E$2:$E$1409,'Teacher Salary Data'!$A$2:$A$1409,$A62,'Teacher Salary Data'!$C$2:$C$1409,"Bachelor's",'Teacher Salary Data'!$D$2:$D$1409,0) | E62: =SUMIFS('Teacher Salary Data'!$E$2:$E$1409,'Teacher Salary Data'!$A$2:$A$1409,$A62,'Teacher Salary Data'!$C$2:$C$1409,"Bachelor's",'Teacher Salary Data'!$D$2:$D$1409,5) | F62: =SUMIFS('Teacher Salary Data'!$E$2:$E$1409,'Teacher Salary Data'!$A$2:$A$1409,$A62,'Teacher Salary Data'!$C$2:$C$1409,"Bachelor's",'Teacher Salary Data'!$D$2:$D$1409,10) | G62: =SUMIFS('Teacher Salary Data'!$E$2:$E$1409,'Teacher Salary Data'!$A$2:$A$1409,$A62,'Teacher Salary Data'!$C$2:$C$1409,"Master's",'Teacher Salary Data'!$D$2:$D$1409,0) | H62: =SUMIFS('Teacher Salary Data'!$E$2:$E$1409,'Teacher Salary Data'!$A$2:$A$1409,$A62,'Teacher Salary Data'!$C$2:$C$1409,"Master's",'Teacher Salary Data'!$D$2:$D$1409,5) | I62: =SUMIFS('Teacher Salary Data'!$E$2:$E$1409,'Teacher Salary Data'!$A$2:$A$1409,$A62,'Teacher Salary Data'!$C$2:$C$1409,"Master's",'Teacher Salary Data'!$D$2:$D$1409,10) | J62: =AVERAGE(D62,G62) | K62: =AVERAGE(F62,I62) | L62: =IFERROR((K62-J62)/J62,0) | M62: =G62-D62 | N62: =IFERROR(INDEX('Median Home and Rent Prices'!$D$2:$D$64,MATCH($A62,'Median Home and Rent Prices'!$A$2:$A$64,0)),0) | O62: =IFERROR(INDEX('Median Home and Rent Prices'!$E$2:$E$64,MATCH($A62,'Median Home and Rent Prices'!$A$2:$A$64,0)),0) | P62: =IFERROR(INDEX('School District Profiles'!$H$2:$H$64,MATCH($A62,'School District Profiles'!$A$2:$A$64,0)),0) | Q62: =IFERROR(INDEX('School District Profiles'!$I$2:$I$64,MATCH($A62,'School District Profiles'!$A$2:$A$64,0)),0) | R62: =IFERROR(MAX(0,MIN(100,(K62-50000)/(110000-50000)*100)),0) | S62: =IFERROR(MAX(0,MIN(100,L62/0.6*100)),0) | T62: =IFERROR(MAX(0,MIN(100,M62/15000*100)),0) | U62: =IFERROR(0.45*R62+0.4*S62+0.15*T62,0) | V62: =IFERROR(0.4*MAX(0,MIN(100,(((J62/12)/O62)-2)/(4-2)*100))+0.35*MAX(0,MIN(100,(8-(N62/K62))/(8-3)*100))+0.25*AB62,0) | W62: =IFERROR(MAX(0,MIN(100,(25-P62)/(25-12)*100)),0) | X62: =IFERROR(MAX(0,MIN(100,(AD62-1)/(3-1)*100))*IF(OR($A62="North Clackamas School District",$A62="Provo City School District"),0.6,1),0) | Y62: =IFERROR(MAX(0,MIN(100,(1-((IFERROR(INDEX('School District Profiles'!$D$2:$D$64,MATCH($A62,'School District Profiles'!$A$2:$A$64,0)),0)/100)^2+(IFERROR(INDEX('School District Profiles'!$E$2:$E$64,MATCH($A62,'School District Profiles'!$A$2:$A$64,0)),0)/100)^2+(IFERROR(INDEX('School District Profiles'!$F$2:$F$64,MATCH($A62,'School District Profiles'!$A$2:$A$64,0)),0)/100)^2+(IFERROR(INDEX('School District Profiles'!$G$2:$G$64,MATCH($A62,'School District Profiles'!$A$2:$A$64,0)),0)/100)^2+(AC62/100)^2))/0.8*100)),0) | Z62: =IFERROR(AF62*AG62,0) | AA62: =IFERROR(INDEX('Median Home and Rent Prices'!$F$2:$F$64,MATCH($A62,'Median Home and Rent Prices'!$A$2:$A$64,0)),0) | AB62: =IFERROR(MAX(0,MIN(100,(800-AA62)/(800-150)*100)),0) | AC62: =IFERROR(INDEX('School District Profiles'!$J$2:$J$64,MATCH($A62,'School District Profiles'!$A$2:$A$64,0)),0) | AD62: =IFERROR(Q62*20/O62,0) | AE62: =IFERROR(IF(AG62>=1,100,IF(AG62>=0.95,75,IF(AG62>=0.9,60,IF(AG62>=0.85,40,IF(AG62>=0.8,25,0))))),0) | AF62: =IFERROR(0.4*U62+0.3*V62+0.1*W62+0.1*X62+0.1*Y62,0) | AG62: 1 | AH62: No employment-stability penalty applied in this first-pass addition; verify with adopted budget, enrollment trend, board packets, and HR/union notices before final scoring.
A63: Deer Park ISD | B63: =IFERROR(INDEX('School District Profiles'!$B$2:$B$64,MATCH($A63,'School District Profiles'!$A$2:$A$64,0)),"") | C63: =IFERROR(INDEX('School District Profiles'!$C$2:$C$64,MATCH($A63,'School District Profiles'!$A$2:$A$64,0)),"") | D63: =SUMIFS('Teacher Salary Data'!$E$2:$E$1409,'Teacher Salary Data'!$A$2:$A$1409,$A63,'Teacher Salary Data'!$C$2:$C$1409,"Bachelor's",'Teacher Salary Data'!$D$2:$D$1409,0) | E63: =SUMIFS('Teacher Salary Data'!$E$2:$E$1409,'Teacher Salary Data'!$A$2:$A$1409,$A63,'Teacher Salary Data'!$C$2:$C$1409,"Bachelor's",'Teacher Salary Data'!$D$2:$D$1409,5) | F63: =SUMIFS('Teacher Salary Data'!$E$2:$E$1409,'Teacher Salary Data'!$A$2:$A$1409,$A63,'Teacher Salary Data'!$C$2:$C$1409,"Bachelor's",'Teacher Salary Data'!$D$2:$D$1409,10) | G63: =SUMIFS('Teacher Salary Data'!$E$2:$E$1409,'Teacher Salary Data'!$A$2:$A$1409,$A63,'Teacher Salary Data'!$C$2:$C$1409,"Master's",'Teacher Salary Data'!$D$2:$D$1409,0) | H63: =SUMIFS('Teacher Salary Data'!$E$2:$E$1409,'Teacher Salary Data'!$A$2:$A$1409,$A63,'Teacher Salary Data'!$C$2:$C$1409,"Master's",'Teacher Salary Data'!$D$2:$D$1409,5) | I63: =SUMIFS('Teacher Salary Data'!$E$2:$E$1409,'Teacher Salary Data'!$A$2:$A$1409,$A63,'Teacher Salary Data'!$C$2:$C$1409,"Master's",'Teacher Salary Data'!$D$2:$D$1409,10) | J63: =AVERAGE(D63,G63) | K63: =AVERAGE(F63,I63) | L63: =IFERROR((K63-J63)/J63,0) | M63: =G63-D63 | N63: =IFERROR(INDEX('Median Home and Rent Prices'!$D$2:$D$64,MATCH($A63,'Median Home and Rent Prices'!$A$2:$A$64,0)),0) | O63: =IFERROR(INDEX('Median Home and Rent Prices'!$E$2:$E$64,MATCH($A63,'Median Home and Rent Prices'!$A$2:$A$64,0)),0) | P63: =IFERROR(INDEX('School District Profiles'!$H$2:$H$64,MATCH($A63,'School District Profiles'!$A$2:$A$64,0)),0) | Q63: =IFERROR(INDEX('School District Profiles'!$I$2:$I$64,MATCH($A63,'School District Profiles'!$A$2:$A$64,0)),0) | R63: =IFERROR(MAX(0,MIN(100,(K63-50000)/(110000-50000)*100)),0) | S63: =IFERROR(MAX(0,MIN(100,L63/0.6*100)),0) | T63: =IFERROR(MAX(0,MIN(100,M63/15000*100)),0) | U63: =IFERROR(0.45*R63+0.4*S63+0.15*T63,0) | V63: =IFERROR(0.4*MAX(0,MIN(100,(((J63/12)/O63)-2)/(4-2)*100))+0.35*MAX(0,MIN(100,(8-(N63/K63))/(8-3)*100))+0.25*AB63,0) | W63: =IFERROR(MAX(0,MIN(100,(25-P63)/(25-12)*100)),0) | X63: =IFERROR(MAX(0,MIN(100,(AD63-1)/(3-1)*100))*IF(OR($A63="North Clackamas School District",$A63="Provo City School District"),0.6,1),0) | Y63: =IFERROR(MAX(0,MIN(100,(1-((IFERROR(INDEX('School District Profiles'!$D$2:$D$64,MATCH($A63,'School District Profiles'!$A$2:$A$64,0)),0)/100)^2+(IFERROR(INDEX('School District Profiles'!$E$2:$E$64,MATCH($A63,'School District Profiles'!$A$2:$A$64,0)),0)/100)^2+(IFERROR(INDEX('School District Profiles'!$F$2:$F$64,MATCH($A63,'School District Profiles'!$A$2:$A$64,0)),0)/100)^2+(IFERROR(INDEX('School District Profiles'!$G$2:$G$64,MATCH($A63,'School District Profiles'!$A$2:$A$64,0)),0)/100)^2+(AC63/100)^2))/0.8*100)),0) | Z63: =IFERROR(AF63*AG63,0) | AA63: =IFERROR(INDEX('Median Home and Rent Prices'!$F$2:$F$64,MATCH($A63,'Median Home and Rent Prices'!$A$2:$A$64,0)),0) | AB63: =IFERROR(MAX(0,MIN(100,(800-AA63)/(800-150)*100)),0) | AC63: =IFERROR(INDEX('School District Profiles'!$J$2:$J$64,MATCH($A63,'School District Profiles'!$A$2:$A$64,0)),0) | AD63: =IFERROR(Q63*20/O63,0) | AE63: =IFERROR(IF(AG63>=1,100,IF(AG63>=0.95,75,IF(AG63>=0.9,60,IF(AG63>=0.85,40,IF(AG63>=0.8,25,0))))),0) | AF63: =IFERROR(0.4*U63+0.3*V63+0.1*W63+0.1*X63+0.1*Y63,0) | AG63: 1 | AH63: No employment-stability penalty applied in this first-pass addition; verify with adopted budget, enrollment trend, board packets, and HR/union notices before final scoring.
A64: Port Arthur ISD | B64: =IFERROR(INDEX('School District Profiles'!$B$2:$B$64,MATCH($A64,'School District Profiles'!$A$2:$A$64,0)),"") | C64: =IFERROR(INDEX('School District Profiles'!$C$2:$C$64,MATCH($A64,'School District Profiles'!$A$2:$A$64,0)),"") | D64: =SUMIFS('Teacher Salary Data'!$E$2:$E$1409,'Teacher Salary Data'!$A$2:$A$1409,$A64,'Teacher Salary Data'!$C$2:$C$1409,"Bachelor's",'Teacher Salary Data'!$D$2:$D$1409,0) | E64: =SUMIFS('Teacher Salary Data'!$E$2:$E$1409,'Teacher Salary Data'!$A$2:$A$1409,$A64,'Teacher Salary Data'!$C$2:$C$1409,"Bachelor's",'Teacher Salary Data'!$D$2:$D$1409,5) | F64: =SUMIFS('Teacher Salary Data'!$E$2:$E$1409,'Teacher Salary Data'!$A$2:$A$1409,$A64,'Teacher Salary Data'!$C$2:$C$1409,"Bachelor's",'Teacher Salary Data'!$D$2:$D$1409,10) | G64: =SUMIFS('Teacher Salary Data'!$E$2:$E$1409,'Teacher Salary Data'!$A$2:$A$1409,$A64,'Teacher Salary Data'!$C$2:$C$1409,"Master's",'Teacher Salary Data'!$D$2:$D$1409,0) | H64: =SUMIFS('Teacher Salary Data'!$E$2:$E$1409,'Teacher Salary Data'!$A$2:$A$1409,$A64,'Teacher Salary Data'!$C$2:$C$1409,"Master's",'Teacher Salary Data'!$D$2:$D$1409,5) | I64: =SUMIFS('Teacher Salary Data'!$E$2:$E$1409,'Teacher Salary Data'!$A$2:$A$1409,$A64,'Teacher Salary Data'!$C$2:$C$1409,"Master's",'Teacher Salary Data'!$D$2:$D$1409,10) | J64: =AVERAGE(D64,G64) | K64: =AVERAGE(F64,I64) | L64: =IFERROR((K64-J64)/J64,0) | M64: =G64-D64 | N64: =IFERROR(INDEX('Median Home and Rent Prices'!$D$2:$D$64,MATCH($A64,'Median Home and Rent Prices'!$A$2:$A$64,0)),0) | O64: =IFERROR(INDEX('Median Home and Rent Prices'!$E$2:$E$64,MATCH($A64,'Median Home and Rent Prices'!$A$2:$A$64,0)),0) | P64: =IFERROR(INDEX('School District Profiles'!$H$2:$H$64,MATCH($A64,'School District Profiles'!$A$2:$A$64,0)),0) | Q64: =IFERROR(INDEX('School District Profiles'!$I$2:$I$64,MATCH($A64,'School District Profiles'!$A$2:$A$64,0)),0) | R64: =IFERROR(MAX(0,MIN(100,(K64-50000)/(110000-50000)*100)),0) | S64: =IFERROR(MAX(0,MIN(100,L64/0.6*100)),0) | T64: =IFERROR(MAX(0,MIN(100,M64/15000*100)),0) | U64: =IFERROR(0.45*R64+0.4*S64+0.15*T64,0) | V64: =IFERROR(0.4*MAX(0,MIN(100,(((J64/12)/O64)-2)/(4-2)*100))+0.35*MAX(0,MIN(100,(8-(N64/K64))/(8-3)*100))+0.25*AB64,0) | W64: =IFERROR(MAX(0,MIN(100,(25-P64)/(25-12)*100)),0) | X64: =IFERROR(MAX(0,MIN(100,(AD64-1)/(3-1)*100))*IF(OR($A64="North Clackamas School District",$A64="Provo City School District"),0.6,1),0) | Y64: =IFERROR(MAX(0,MIN(100,(1-((IFERROR(INDEX('School District Profiles'!$D$2:$D$64,MATCH($A64,'School District Profiles'!$A$2:$A$64,0)),0)/100)^2+(IFERROR(INDEX('School District Profiles'!$E$2:$E$64,MATCH($A64,'School District Profiles'!$A$2:$A$64,0)),0)/100)^2+(IFERROR(INDEX('School District Profiles'!$F$2:$F$64,MATCH($A64,'School District Profiles'!$A$2:$A$64,0)),0)/100)^2+(IFERROR(INDEX('School District Profiles'!$G$2:$G$64,MATCH($A64,'School District Profiles'!$A$2:$A$64,0)),0)/100)^2+(AC64/100)^2))/0.8*100)),0) | Z64: =IFERROR(AF64*AG64,0) | AA64: =IFERROR(INDEX('Median Home and Rent Prices'!$F$2:$F$64,MATCH($A64,'Median Home and Rent Prices'!$A$2:$A$64,0)),0) | AB64: =IFERROR(MAX(0,MIN(100,(800-AA64)/(800-150)*100)),0) | AC64: =IFERROR(INDEX('School District Profiles'!$J$2:$J$64,MATCH($A64,'School District Profiles'!$A$2:$A$64,0)),0) | AD64: =IFERROR(Q64*20/O64,0) | AE64: =IFERROR(IF(AG64>=1,100,IF(AG64>=0.95,75,IF(AG64>=0.9,60,IF(AG64>=0.85,40,IF(AG64>=0.8,25,0))))),0) | AF64: =IFERROR(0.4*U64+0.3*V64+0.1*W64+0.1*X64+0.1*Y64,0) | AG64: 1 | AH64: No employment-stability penalty applied in this first-pass addition; verify with adopted budget, enrollment trend, board packets, and HR/union notices before final scoring.

Sheet Scoring Benchmarks
A1: Benchmark-Based Scoring System
A2: Purpose | B2: Replaces relative normalization with fixed real-world benchmarks so scores stay stable when new districts are added.
A3: Updated | B3: 2026-06-16
A5: Score Component | B5: Old Method | C5: New Formula / Benchmark | D5: Floor | E5: Ceiling | F5: Notes
A6: Salary Level Score | B6: Relative normalization of Avg 10-Year Salary against current workbook min/max | C6: Avg 10-Year Salary: $50,000 = 0; $110,000 = 100 | D6: 50000 | E6: 110000 | F6: Uses column K
A7: Growth Score | B7: Relative normalization of Avg Growth % against current workbook min/max | C7: Avg Growth %: 0% = 0; 60% = 100 | D7: 0 | E7: 0.6 | F7: Uses column L
A8: Master's Premium Score | B8: Relative normalization of Master's Premium against current workbook min/max | C8: Master's Premium: $0 = 0; $15,000 = 100 | D8: 0 | E8: 15000 | F8: Uses column M
A9: Salary Score | B9: Weighted blend of salary level, growth, and master's premium | C9: Unchanged weight blend: 45% salary level + 40% growth + 15% master's premium | F9: Uses R, S, T
A10: Rent Affordability Component | B10: Relative normalization of median rent | C10: Monthly Avg Start Salary ÷ Median Rent: 2.0 = 0; 4.0 = 100 | D10: 2 | E10: 4 | F10: Embedded inside Affordability Score
A11: Home Affordability Component | B11: Relative normalization of median home price | C11: Median Home Price ÷ Avg 10-Year Salary: 8.0 = 0; 3.0 = 100 | D11: 8 | E11: 3 | F11: Embedded inside Affordability Score
A12: Price per Sq Ft Score | B12: Relative normalization of price per sq ft | C12: Price per Sq Ft: $800 = 0; $150 = 100 | D12: 800 | E12: 150 | F12: Uses column AA
A13: Affordability Score | B13: Weighted blend of relative rent/home/price per sq ft scores | C13: 40% rent affordability + 35% home affordability + 25% price per sq ft | F13: Uses benchmark components
A14: Student-Teacher Ratio Score | B14: Relative normalization of student-teacher ratio | C14: 12 or lower = 100; 25 or higher = 0 | D14: 12 | E14: 25 | F14: Lower ratio is better
A15: Sub Pay Score | B15: Relative normalization of Sub Pay Housing Power | C15: Licensed Sub Pay × 20 ÷ Median Rent: 1.0 = 0; 3.0 = 100 | D15: 1 | E15: 3 | F15: Keeps existing 0.6 penalty for North Clackamas and Provo City
A16: Demographic Balance Score | B16: Rule-based concentration penalty | C16: Kept rule-based; capped at 0 to 100 | D16: 0 | E16: 100 | F16: No longer can go below 0
A17: Stability Score | B17: Risk multiplier translated to fixed score | C17: Unchanged: 1.00=100, .95=75, .90=60, .85=40, .80=25 | F17: Uses AG Risk Multiplier
A18: Pre-Risk Overall | B18: Weighted blend of category scores | C18: Unchanged weight blend: 40% Salary + 30% Affordability + 10% Class Size + 10% Sub Pay + 10% Demographics | F18: Uses U,V,W,X,Y
A19: Overall Value Score | B19: Pre-risk score multiplied by Risk Multiplier | C19: Unchanged: Pre-Risk Overall × Risk Multiplier | F19: Uses AF × AG

Sheet Changed Formulas
A1: Column
A2: R | B2: Salary Level Score | C2: =MAX(0,MIN(100,(K2-50000)/(110000-50000)*100))
A3: S | B3: Growth Score | C3: =MAX(0,MIN(100,L2/0.6*100))
A4: T | B4: Master's Premium Score | C4: =MAX(0,MIN(100,M2/15000*100))
A5: U | B5: Salary Score | C5: =0.45*R2+0.40*S2+0.15*T2
A6: V | B6: Affordability Score | C6: =0.40*MAX(0,MIN(100,(((J2/12)/O2)-2)/(4-2)*100))+0.35*MAX(0,MIN(100,(8-(N2/K2))/(8-3)*100))+0.25*AB2
A7: W | B7: Student-Teacher Ratio Score | C7: =MAX(0,MIN(100,(25-P2)/(25-12)*100))
A8: X | B8: Sub Pay Score | C8: =MAX(0,MIN(100,(AD2-1)/(3-1)*100))*IF(OR($A2="North Clackamas School District",$A2="Provo City School District"),0.6,1)
A9: Y | B9: Demographic Balance Score | C9: Kept existing rule-based demographic-balance scoring formula.
A10: Z | B10: Overall Value Score | C10: =AF2*AG2
A11: AB | B11: Price per Sq Ft Score | C11: =MAX(0,MIN(100,(800-AA2)/(800-150)*100))
A12: AE | B12: Stability Score | C12: =IF(AG2>=1,100,IF(AG2>=0.95,75,IF(AG2>=0.9,60,IF(AG2>=0.85,40,IF(AG2>=0.8,25,0)))))
A13: AF | B13: Pre-Risk Overall | C13: =0.40*U2+0.30*V2+0.10*W2+0.10*X2+0.10*Y2

Sheet Score Methodology
A1: Score Methodology
A2: Purpose | B2: This workbook now uses fixed benchmark scoring instead of relative normalization. Scores are designed to remain stable when new districts are added.
A3: Important change | B3: Category scores no longer depend on the current workbook minimum/maximum, except rankings naturally depend on the districts included.
A5: Formula | B5: Definition
A6: Avg Start Salary | B6: (BA Start + MA Start) / 2
A7: Avg 10-Year Salary | B7: (BA 10-Year + MA 10-Year) / 2
A8: Avg Growth % | B8: (Avg 10-Year Salary - Avg Start Salary) / Avg Start Salary
A9: Master's Premium | B9: MA Start - BA Start
A10: Salary Level Score | B10: MAX(0, MIN(100, (Avg 10-Year Salary - 50000) / (110000 - 50000) * 100))
A11: Growth Score | B11: MAX(0, MIN(100, Avg Growth % / 0.60 * 100))
A12: Master's Premium Score | B12: MAX(0, MIN(100, Master's Premium / 15000 * 100))
A13: Salary Score | B13: 45% Salary Level + 40% Growth + 15% Master's Premium
A14: Rent Affordability Component | B14: MAX(0, MIN(100, (((Avg Start Salary / 12) / Median Rent) - 2) / (4 - 2) * 100))
... A24: Overall Value Score | B24: Pre-Risk Overall * Risk Multiplier

Sheet README
A1: Teacher Website Data - Simplified Value Scores
A2: What changed | B2: The separate revised scoring area was removed. District Value Scores now has one Overall Value Score column that includes salary level, growth, Master's premium, affordability, student-teacher ratio, and licensed sub pay.
A3: Sortable design | B3: The District Value Scores sheet uses values, not formulas, in the score columns. This is intentional so you can sort from highest to lowest without scores turning to 0 or formulas breaking.
A4: How to sort | B4: Sort by Overall Value Score, Sort On = Cell Values, Order = Largest to Smallest.
A5: How to recolor | B5: Apply Conditional Formatting > Color Scales separately to each score column if desired.
A6: Source sheets | B6: Teacher Salary Data, School District Profiles, and Median Home and Rent Prices are preserved as source data.
A8: Formula update note | B8: Score columns R:Z now use formulas. If you enter a clean numeric Licensed Sub Pay in column Q, Sub Pay Score and Overall Value Score update.
A9: Sub pay entry format | B9: Enter 200, not $200/day. Text entries like Unknown or $34/per period are ignored by the Sub Pay Score.
A10: Sorting note | B10: Sort the entire District Value Scores table by Overall Value Score or any score column. Choose Expand the selection if Excel asks.
A11: Date display note | B11: Last Verified columns were widened/formatted so dates display instead of #######.
A12: Sub pay scoring update | B12: Sub Pay Housing Power now uses licensed daily sub pay × 20 ÷ median rent. Existing weights/formulas are otherwise unchanged.
A14: Prototype 171 update | B14: Applied district-level Work Environment / Stability Risk multipliers to every district using first-pass public-source screening.
A15: Updated formula | B15: Final Overall Value Score = Pre-Risk Overall Value Score × Risk Multiplier.
... A49: Scoring update | B49: This version replaces relative normalization with fixed benchmark-based scoring. See Scoring Benchmarks and Changed Formulas sheets.

Sheet LAUSD Sources
A1: Field | B1: Value used | C1: Source URL | D1: Notes
A2: Teacher salary table | B2: BA Pay Scale Group 20; levels 1-10; year 10 repeats level 10; MA = BA + $584 | C2: https://hr.lausd.org/apps/pages/index.jsp?uREC_ID=4422515&type=d&pREC_ID=2657596 | D2: Official LAUSD 2025-2026 certificated salary tables page.
A3: Teacher salary PDF | B3: 2025-2026 T Table, C Basis | C3: https://media.edlio.net/2e0a8bf0/238a9ca2/c19b05e8/9f777902d5ea42ca9dbb2708c6087a05?_=T_Table_Annual.pdf | D3: Page 1 gives annual salaries; page 2 states the master's degree differential is $584 annually.
A4: Substitute pay | B4: $261.49/day base daily rate | C4: https://hr.lausd.org/apps/pages/index.jsp?pREC_ID=2723080&type=d&uREC_ID=4422503 | D4: Official certificated substitute page lists $43.58/hour and $261.49/day for 6 hours.
A5: Student-teacher ratio / total schools | B5: 19.20 ratio; 784 schools | C5: https://nces.ed.gov/ccd/districtsearch/district_detail.asp?ID2=0622710&details=1 | D5: NCES CCD district detail, 2024-2025 school year.
A6: Demographics | B6: White 10%, Hispanic/Latino 73%, Asian 4%, Black 7% | C6: https://innovateschools.org/wp-content/uploads/2026/03/LAUSD-Datasheet-2024-25-English-1.pdf | D6: CDE-based 2024-25 data sheet; Filipino is reported separately and not included in the workbook's Asian column.
A7: Median rent | B7: $2,650 | C7: https://www.zillow.com/rental-manager/market-trends/los-angeles-ca/ | D7: Zillow Rental Manager average rent for Los Angeles, CA, all bedrooms/property types, last updated June 8, 2026.
A8: Median/typical home value | B8: $956,465 | C8: https://www.zillow.com/home-values/12447/los-angeles-ca/ | D8: Zillow Home Value Index for Los Angeles, CA, updated April 30, 2026. Workbook column label says median home price; this uses Zillow typical home value for consistency with available source.
A9: Verification date | B9: 2026-06-10 | D9: Date this LAUSD row was researched and added.

Sheet CHCCS Sources
A1: Field | B1: Value / Note | C1: Source URL
A2: State salary schedule | B2: NC FY 2025-26 certified teacher salary schedule, annual salaries for BA and MA at years 0-10. | C2: https://www.dpi.nc.gov/documents/fbs/budget/fy26webschedulespdf/download?attachment=
A3: Local supplement | B3: CHCCS teacher local supplement is 18% for years 0-19; applied to NC state salary schedule. | C3: https://www.chccs.org/our-district/human-resources/salary-supplement
A4: Student-teacher ratio / total schools | B4: NCES 2024-25: 20 schools, 11,353 students, 894.67 classroom teachers, student/teacher ratio 12.69. | C4: https://nces.ed.gov/ccd/districtsearch/district_detail.asp?ID2=3700720&details=1
A5: School level counts | B5: CHCCS says district operates 4 high schools, 4 middle schools, 11 elementary schools, and one hospital school. | C5: https://www.chccs.org/our-district/homepage
A6: Substitute pay | B6: Certified substitute rate: $135/day; long-term certified: $165/day. | C6: https://www.k12jobspot.com/Job/5489091
A7: Median rent | B7: Zillow average rent in Chapel Hill, NC: $1,850. | C7: https://www.zillow.com/rental-manager/market-trends/chapel-hill-nc/
A8: Median home price | B8: Zillow average Chapel Hill, NC home value: $634,403. | C8: https://www.zillow.com/home-values/17386/chapel-hill-nc/
A9: Student demographics | B9: White 52.52%, Hispanic 14.40%, Asian 15.01%, Black 11.28% from TeacherServer district diversity table; verify with NC Report Card if needed. | C9: https://teacherserver.com/schooldiversity/xdistrict.php?id=3700720

Sheet Portland Sources
A1: Field | B1: Value / Note | C1: Source URL
A2: District | B2: Portland Public Schools / Portland SD 1J | C2: https://nces.ed.gov/ccd/districtsearch/district_detail.asp?ID2=4110040&details=2
A3: Salary schedule | B3: PPS 2025-2026 Professional Educators 193-day salary schedule; BA+15 used for Bachelor's and BA+60/MA used for Master's; years 0-10 mapped to salary rows A-K. | C3: https://www.pps.net/departments/human-resources/classification-and-compensation/salary-schedules
A4: Substitute pay | B4: Substitute Educator full-day rate: $275.71 for 2025-2026. | C4: https://www.pps.net/departments/human-resources/substituting
A5: Schools / teacher FTE | B5: NCES lists 86 total schools and 2,710.87 teacher FTE for Portland SD 1J, 2024-2025. | C5: https://nces.ed.gov/ccd/districtsearch/district_detail.asp?ID2=4110040&details=2
A6: Enrollment / demographics | B6: PPS October 2025 district total: 43,477 students; White 53.3%, Latino 18.4%, Asian 5.7%, Black 8.3%. | C6: https://www.pps.net/departments/research-assessment-and-accountability/data-and-reports/enrollment-reports-and-school-profiles
A7: Housing | B7: Zillow Portland home value $538,687 and rental market average rent $1,725 / $1,681 depending page; workbook uses $1,725 from Zillow home values/rental trends page. | C7: https://www.zillow.com/home-values/13373/portland-or/
A8: Method note | B8: Student-teacher ratio calculated as 43,477 PPS enrollment / 2,710.87 NCES teacher FTE = 16.04. Score columns recalculated using the workbook methodology with Portland included.

Sheet Cherry Creek Sources
A1: Category | B1: Value Used | C1: Source URL | D1: Notes
A2: Salary schedule | B2: 2025-2026 BA/MA steps 1-11 | C2: https://resources.finalsite.net/images/v1747940280/cherrycreekschoolsorg/wdju2pddegexsrgn0zir/Proposed2025-2026Certified-LicensedSalarySchedule.pdf | D2: Used step 1 as 0 years through step 11 as 10 years.
A3: District compensation page | B3: 2025-2026 certified/licensed salary schedule link | C3: https://www.cherrycreekschools.org/careers/human-resources/compensation | D3: District compensation page hosts the official pay plan links.
A4: Substitute pay | B4: $210 full day | C4: https://www.cherrycreekschools.org/careers/human-resources/substitutes | D4: Regular substitute full day rate; super sub/Title One/retired rates not used.
A5: NCES district stats | B5: 69 schools, 51,980 students, 3,212.73 FTE teachers, 16.18 ratio | C5: https://nces.ed.gov/ccd/districtsearch/district_detail.asp?ID2=0802910&details=1 | D5: Used student-teacher ratio; district profile uses official district facts total schools.
A6: District facts/demographics | B6: White 44.8%, Hispanic 24.8%, Asian 8.4%, Black 11.4%, 67 schools | C6: https://www.cherrycreekschools.org/about-us/our-district/facts-figures | D6: Used for demographic balance score and school-level breakdown.
A7: Home value | B7: $556,984 average of Aurora + Centennial Zillow home values | C7: https://www.zillow.com/home-values/16846/aurora-co/ ; https://www.zillow.com/home-values/93273/centennial-co-80161/ | D7: Aurora $464,881; Centennial $649,086. Averaged because many CCSD households may live in nearby Aurora/Centennial rather than Greenwood Village.
A8: Rent | B8: $2,208 average of Aurora + Centennial Zillow rents | C8: https://www.zillow.com/rental-manager/market-trends/aurora-co/ ; https://www.zillow.com/rental-manager/market-trends/centennial-co/ | D8: Aurora $1,921; Centennial $2,495. Averaged because many CCSD households may live in nearby Aurora/Centennial rather than Greenwood Village.
A9: Housing proxy note | B9: Aurora + Centennial average | C9: N/A | D9: Replaces Greenwood Village-only proxy to better represent nearby communities where CCSD families/staff may live.

Sheet LCUSD Sources
A1: Data Point | B1: Value Used | C1: Source URL | D1: Notes
A2: Teacher salary schedule | B2: 2025-26 LCTA Teachers & Psychologists; BA Class I; MA Class IV | C2: https://4.files.edl.io/82c5/08/14/25/213723-fb8372c1-6d7b-4358-9610-35dd8134bc12.pdf | D2: Used steps 1-11 as years experience 0-10.
A3: Substitute pay | B3: $200/day | C3: https://www.edjoin.org/Home/JobPosting/2125841 | D3: EdJoin posting lists $200/day or $100/half day.
A4: Student-teacher ratio / schools | B4: 23.66 ratio; 4 schools | C4: https://nces.ed.gov/ccd/districtsearch/district_detail.asp?ID2=0620130 | D4: NCES District Detail, 2024-25 school year.
A5: Housing | B5: $2,499,891 home value; $5,900 rent | C5: https://www.zillow.com/home-values/46080/la-canada-flintridge-ca/ ; https://www.zillow.com/rental-manager/market-trends/la-canada-flintridge-ca/ | D5: Zillow home value updated 4/30/2026; Zillow rent updated 6/7/2026.
A6: Demographics | B6: 42% White; 33% Asian; 12% Hispanic; Black not listed | C6: https://www.publicschoolreview.com/california/la-canada-unified-school-district/620130-school-district | D6: Used Public School Review 2026 district FAQ; Black entered as 0 because not listed in the stated racial composition.

Sheet PPSF Sources
A1: District | B1: Area | C1: Median Home Price per Sq Ft | D1: PPSF Source URL | E1: Notes
A2: Jordan District | B2: West Jordan, UT | C2: 232 | D2: https://www.redfin.com/city/20569/UT/West-Jordan/housing-market
A3: Glendora Unified School District | B3: Glendora, CA | C3: 583 | D3: https://www.redfin.com/city/7650/CA/Glendora/housing-market
A4: Alief ISD | B4: Alief, TX | C4: 113 | D4: https://www.redfin.com/neighborhood/29917/TX/Houston/Alief/housing-market
A5: San Diego Unified School District | B5: San Diego, CA | C5: 687 | D5: https://www.redfin.com/city/16904/CA/San-Diego/housing-market
A6: Leander ISD | B6: Austin, TX | C6: 190 | D6: https://www.redfin.com/city/30803/TX/Leander/housing-market
A7: Katy ISD | B7: Katy, TX | C7: 160 | D7: https://www.redfin.com/city/9764/TX/Katy/housing-market
A8: Oakland Unified School District | B8: Oakland, CA | C8: 577 | D8: https://www.redfin.com/city/13654/CA/Oakland/housing-market
A9: San Jose Unified School District | B9: San Jose, CA | C9: 878 | D9: https://www.redfin.com/city/17420/CA/San-Jose/housing-market
A10: Oxnard Union High School District | B10: Oxnard, CA | C10: 514 | D10: https://www.redfin.com/city/14141/CA/Oxnard/housing-market
A11: Provo City School District | B11: Provo, UT | C11: 267 | D11: https://www.redfin.com/city/16042/UT/Provo/housing-market
A12: Salt Lake School District | B12: Salt Lake City, UT | C12: 372 | D12: https://www.redfin.com/city/17150/UT/Salt-Lake-City/housing-market
A13: Denver Public Schools | B13: Denver, CO | C13: 367 | D13: https://www.redfin.com/city/5155/CO/Denver/housing-market
... A20: Syosset Central School District | B20: Syosset, NY | C20: 559 | D20: https://www.redfin.com/city/26044/NY/Syosset/housing-market
A21: Glendale Union High School District | B21: Glendale, AZ / 85305 proxy | C21: 211 | D21: https://www.redfin.com/zipcode/85305/housing-market | E21: Redfin 85305 used as Glendale-area PPSF proxy.
A22: San Antonio ISD | B22: San Antonio, TX | C22: 151 | D22: https://www.redfin.com/city/16657/TX/San-Antonio/housing-market | E22: Redfin San Antonio city PPSF.

Sheet Eanes Sources
A1: Field | B1: Value used | C1: Source URL | D1: Notes
A2: Teacher salary schedule | B2: 2025-26 187-day classroom teacher pay plan, years 0-10 | C2: https://resources.finalsite.net/images/v1752617781/eanesisdnet/spyojkejaf8h5sunkjwe/2025-26TeacherPayPlan.pdf | D2: Used total salary column for classroom teachers.
A3: Master's stipend | B3: $2,600 MA advanced degree stipend | C3: https://resources.finalsite.net/images/v1752617781/eanesisdnet/spyojkejaf8h5sunkjwe/2025-26TeacherPayPlan.pdf | D3: Added to BA classroom teacher total salary for Master's rows.
A4: Substitute pay | B4: $130/day for substitute teacher days 1-30 | C4: https://www.eanesisd.net/dept/hr/subs/pay | D4: Base daily substitute teacher/teacher aide rate.
A5: Student-teacher ratio | B5: 12.28 | C5: https://nces.ed.gov/ccd/districtsearch/district_detail.asp?County=Travis+County&ID2=4817760&Search=1&State=48 | D5: NCES 2024-25 district details.
A6: Total schools | B6: 10 | C6: https://nces.ed.gov/ccd/districtsearch/district_detail.asp?County=Travis+County&ID2=4817760&Search=1&State=48 | D6: NCES 2024-25 district directory.
A7: Demographics | B7: White 62.0%, Hispanic 15.4%, Asian 14.7%, Black 0.9% | C7: https://www.har.com/school_district/eanes-isd_227909 | D7: Used HAR district student statistics.
A8: Median home price | B8: $1,724,921 | C8: https://www.zillow.com/home-values/92655/austin-tx-78746/ | D8: Used 78746 as housing proxy for Eanes ISD/Westlake area.
A9: Median rent | B9: $3,900 | C9: https://www.zillow.com/rental-manager/market-trends/78746/ | D9: Used 78746 as housing proxy for Eanes ISD/Westlake area.
A10: Median home price per sq ft | B10: $558 | C10: https://www.redfin.com/zipcode/78746/housing-market | D10: Used Redfin 78746 median sale price per square foot.

Sheet Syosset Sources
A1: Field | B1: Value used | C1: Source URL | D1: Notes
A2: Teacher salary schedule | B2: 2025-26 STA/TCH-B BA and MA salary schedule; years 0-10 mapped to steps 1-11 | C2: https://resources.finalsite.net/images/v1760543603/syossetk12nyus/wck1xacrbzy6lhumipj9/STAMOA2025-2030.pdf | D2: Used BA and MA rows from the 2025-26 salary schedule.
A3: Substitute pay | B3: $160/day permanent substitute teacher rate | C3: https://olasjobs.org/job-details/SYTN0326267-3014 | D3: Used OLAS posting for Syosset CSD permanent substitute rate.
A4: Student-teacher ratio | B4: 10.28 | C4: https://nces.ed.gov/ccd/districtsearch/district_detail.asp?ID2=3628560 | D4: NCES 2024-2025 district data.
A5: Total schools | B5: 10 | C5: https://nces.ed.gov/ccd/districtsearch/district_detail.asp?ID2=3628560 | D5: NCES district directory total schools.
A6: School level counts | B6: 7 elementary, 2 middle, 1 high | C6: https://www.syossetschools.org/schools | D6: District school list: seven elementary schools, two middle schools, one high school.
A7: Demographics | B7: Asian 52.4%, White 39.4%, Hispanic 4.6%, Black 0.6% | C7: https://www.niche.com/k12/d/syosset-central-school-district-ny/students/ | D7: Used student diversity percentages from Niche.
A8: Median home price | B8: $1,096,329 | C8: https://www.zillow.com/home-values/34220/syosset-ny/ | D8: Zillow Syosset home value.
A9: Median rent | B9: $5,200 | C9: https://www.zillow.com/rental-manager/market-trends/syosset-ny/ | D9: Zillow Rental Manager Syosset rent.
A10: Median home price per sq ft | B10: $559 | C10: https://www.redfin.com/city/26044/NY/Syosset/housing-market | D10: Redfin Syosset median sale price per square foot.

Sheet Glendale Union Sources
A1: Field | B1: Value used | C1: Source URL | D1: Notes
A2: Certified salary schedule page | B2: GUHSD links Certified Personnel salary schedule | C2: https://www.guhsdaz.org/salaryschedules | D2: The district salary page links the Certified Personnel schedule as a Google Doc.
A3: Teacher salary range used | B3: $56,000-$64,500 annual salary range | C3: https://us.trabajo.org/job-4023-9f6f875ede08a4c5b9a5cb14463a6115 | D3: Search result showed GUHSD teacher annual salary range. Since detailed Google Doc values were not accessible, years 0-10 were interpolated across this range.
A4: Average teacher salary reference | B4: FY 2027 average teacher salary $76,360; FY 2026 average $78,803 | C4: https://www.guhsdaz.org/61676_2 | D4: Used as context only, not as 0-10 salary schedule.
A5: Student/teacher ratio and total schools | B5: 16,092 students; 723.60 classroom teachers; 22.24 ratio; 11 schools | C5: https://nces.ed.gov/ccd/districtsearch/district_detail.asp?ID2=0403450&Search=2&details=1 | D5: NCES 2024-2025 district details.
A6: District school count structure | B6: 11 high schools / total schools | C6: https://www.greatschools.org/arizona/glendale/glendale-union-high-school-district/ | D6: High-school-only district; GreatSchools lists 11 high schools and 11 total schools.
A7: Substitute pay | B7: $123-$199 daily range; $123 used as conservative base daily rate | C7: https://www.ziprecruiter.com/c/Glendale-Union-High-School-District-205/Job/Substitute-Teacher/-in-Glendale%2CAZ?jid=af8feceefd00ad34 | D7: Search result for GUHSD Substitute Teacher showed $123 to $199 daily.
A8: Median home price | B8: $408,630 | C8: https://www.zillow.com/home-values/18298/glendale-az/ | D8: Zillow Glendale, AZ home value, updated 4/30/2026.
A9: Median rent | B9: $1,987 | C9: https://www.zillow.com/rental-manager/market-trends/glendale-az/ | D9: Zillow Rental Manager Glendale, AZ average rent, last updated June 8, 2026.
A10: Median home price per sq ft | B10: $211 | C10: https://www.redfin.com/zipcode/85305/housing-market | D10: Redfin 85305 median sale price per square foot used as Glendale-area proxy.
A11: Demographics | B11: Hispanic 59.7%, White 23.4%, Black 9.3%, Asian 3.2% | C11: https://civilrightsdata.ed.gov/profile/us/az/glendale_union_high_school_district_%284285%29?nces=0403450&surveyYear=2020 | D11: Public CRDC result; current NCES demographic dashboard was not directly extractable.

Sheet San Antonio Sources
A1: Category | B1: Value Used | C1: Source URL | D1: Notes
A2: Teacher salary schedule | B2: 2026–2027 classroom teacher pay schedule: BA/MA years 0–10 | C2: https://files-backend.assets.thrillshare.com/documents/asset/uploaded_file/5576/Saisd/8bcbc47c-7a33-45ba-8903-6326c3c1eec3/CR-TEACHER-PAY-SCALE-26-27SY.pdf?disposition=inline | D2: Official SAISD Compensation Resource Manual PDF.
A3: Substitute pay | B3: $140/day | C3: User provided in chat | D3: Entered per user instruction.
A4: Student-teacher ratio | B4: 14.95 | C4: https://nces.ed.gov/ccd/districtsearch/district_detail.asp?ID2=4838730 | D4: NCES 2024–2025 district detail.
A5: Enrollment / campus counts | B5: 42,548 students; 83 campuses; 51 elementary, 12 middle, 14 high | C5: https://schools.texastribune.org/districts/san-antonio-isd/ | D5: Texas Tribune Schools Explorer.
A6: Demographics | B6: Hispanic 89.6%; Black 6%; White 3%; Asian 1.4% | C6: https://schools.texastribune.org/districts/san-antonio-isd/demographics/ ; https://www.expressnews.com/projects/2025/school-demographics-2025/ ; https://www.publicschoolreview.com/texas/san-antonio-independent-school-district/4838730-school-district | D6: White/Asian split uses an estimate to fit workbook categories because source pages summarize Hispanic, Black, and minority share but do not expose every category cleanly in parsed text.
A7: Home price / PPSF | B7: $260,000 median sale price; $151 per sq ft | C7: https://www.redfin.com/city/16657/TX/San-Antonio/housing-market | D7: Redfin San Antonio housing market.
A8: Rent | B8: $1,372 current rent proxy | C8: https://www.zillow.com/home-values/6915/san-antonio-tx/ | D8: Zillow rental market trend; used as current rent proxy in the workbook's Median Rent field.

Sheet Salt Lake Sources
A1: Field | B1: Value / Adjustment | C1: Source | D1: Notes
A2: Salary schedule year | B2: 2025-26 | C2: User-provided Salt Lake City School District HR email and screenshot | D2: Certified Teachers - 185 Days, 8 Hours Per Day.
A3: Placement rule | B3: All placements begin at Step 2; prior service is credited using the district's Article 17 years-of-credit formula. | C3: User-provided Salt Lake City School District HR email | D3: 0 years = Step 2; 5 prior years = Step 7; 10 prior years = Step 9.
A4: BA salary schedule mapping | B4: Experience 0-10 mapped to Step 2,3,4,5,6,7,7,8,8,9,9 | C4: User-provided email/screenshot | D4: Corrects prior prototype, which treated 10 years as Step 10.
A5: MA salary schedule mapping | B5: Experience 0-10 mapped to Step 2,3,4,5,6,7,7,8,8,9,9 | C5: User-provided email/screenshot | D5: Corrects prior prototype, which treated 10 years as Step 10.
A6: BA 5-Year / 10-Year | B6: $74,460 / $80,826 | C6: User-provided email/screenshot | D6: 5 prior years = Step 7; 10 prior years = Step 9.
A7: MA 5-Year / 10-Year | B7: $80,270 / $85,425 | C7: User-provided email/screenshot | D7: 5 prior years = Step 7; 10 prior years = Step 9.
A8: Update applied | B8: Prototype 103 / Workbook 7 | C8: ChatGPT calculation from user-provided HR email | D8: Scores recalculated only where affected by Salt Lake salary mapping.

Sheet Austin Sources
A1: Field | B1: Value / Note | C1: Source URL | D1: Notes
A2: Teacher salary schedule | B2: Estimated current 0-10 BA/MA schedule (BA and MA identical in workbook) | C2: Austin ISD compensation page; Austin ISD Human Capital audit report | D2: Current Austin ISD compensation page did not expose a teacher BA/MA step table. The workbook estimate starts from the district audit's 2021-22 AISD PPfT 0-, 5-, and 10-year averages and applies documented districtwide teacher raises approved in 2022-23 and 2023-24.
A3: Master's differential | B3: No separate master's differential found on current compensation page | C3: https://www.austinisd.org/hc/careers/compensation | D3: Austin ISD highlights stipends on the compensation page but does not list a teacher master's bump there, so the prototype currently mirrors BA and MA salaries.
A4: Sub pay | B4: Certified teacher substitute base pay = $155/day (2025-26) | C4: https://www.austinisd.org/hc/careers/substitutes | D4: Base rate only; optional Title I and Special Education assignment add-ons not included in the comparison workbook.
A5: Demographics | B5: White 30.68%; Hispanic 54.14%; Asian 4.84%; Black 6.01% | C5: https://www.austinisd.org/about-us | D5: Values taken from Austin ISD's About Us page.
A6: School counts | B6: 13 high, 19 middle, 78 elementary, 4 other = 114 total | C6: https://www.austinisd.org/schools ; https://www.austinisd.org/about-us | D6: Directory pages show category lists and the district states it has 114 schools. Ann Richards (6-12) appears in both middle and high listings, so counts were normalized to 114 total schools.
A7: Housing | B7: Median home price $506,276; median rent $1,956; PPSF $294 | C7: https://www.zillow.com/home-values/10221/austin-tx/ ; https://www.zillow.com/rental-manager/market-trends/austin-tx/ ; https://www.redfin.com/city/30818/TX/Austin/housing-market | D7: Austin city market proxies used for the district.
A8: Student-teacher ratio | B8: 13.7 | C8: Austin ISD / compiled workbook estimate | D8: Used as a comparison input for the prototype.
A9: Update applied | B9: Workbook 8 / Prototype 128 | C9: ChatGPT workbook update | D9: Austin ISD added to the comparison set.

Sheet South Pasadena Sources
A1: Field | B1: Value / Note | C1: Source URL | D1: Notes
A2: Salary schedule | B2: 2025-2026 Certificated Salary Schedule, Schedule C | C2: https://www.spusd.net/apps/pages/index.jsp?uREC_ID=756752&type=d&pREC_ID=1163760 ; https://4.files.edl.io/a1b1/06/01/26/215223-096e534c-1eef-49f3-a608-f1c04b8ebc6c.pdf | D2: Bachelor's uses column A. Master's uses Column C, labeled Bachelor's plus 30 or Master's.
A3: BA salary mapping | B3: Years 0-9 mapped to steps 1-10; year 10 held at Step 10 because BA-only column does not continue to Step 11 | C3: Official salary schedule | D3: CA schedules do not always map 1:1 to years for out-of-district placement; this is a comparison approximation.
A4: MA salary mapping | B4: Years 0-10 mapped to steps 1-11, Column C | C4: Official salary schedule | D4: Column C is the base Master's lane shown in the schedule.
A5: Demographics | B5: White 21.6%; Hispanic 23.2%; Asian 33.8%; Black/African American 1.0% | C5: https://dq.cde.ca.gov/dataquest/dqcensus/enrethlevels.aspx?agglevel=District&cds=1965029&year=2025-26 | D5: DataQuest 2025-26 enrollment by ethnicity. Filipino, two-or-more, and other categories not included in the four-group score.
A6: Enrollment and ELL | B6: Enrollment 4,679; English Learners 242 (5.2%) | C6: https://www.cde.ca.gov/sdprofile/details.aspx?cds=19650290000000 | D6: CDE District Profile, 2025-26.
A7: Student-teacher ratio / total schools | B7: Student-teacher ratio 24.37; total schools 5 | C7: https://nces.ed.gov/ccd/districtsearch/district_detail.asp?ID2=0637500&Search=2 | D7: NCES district detail, 2024-25.
A8: School count by level | B8: 3 elementary, 1 middle, 1 high, 0 other | C8: https://www.spusd.net/ | D8: SPUSD homepage lists five schools via school links.
A9: Substitute pay | B9: Full-day daily rate $200 | C9: https://www.edjoin.org/Home/JobPosting/1631162 | D9: Latest public posting found was for 2022-23; verify current rate if using this for application decisions.
A10: Housing | B10: Median home price $1,918,852; PPSF $962 | C10: https://www.redfin.com/city/18661/CA/South-Pasadena/housing-market | D10: Redfin South Pasadena housing market, 3 months ending May 2026.
A11: Rent | B11: Average rent $2,695 | C11: https://www.zillow.com/rental-manager/market-trends/south-pasadena-ca/ | D11: Zillow Rentals data, last updated June 9, 2026.
A12: Update applied | B12: Workbook 9 / Prototype 134 | C12: ChatGPT workbook update | D12: South Pasadena Unified School District added to comparison set.

Sheet Ocean Springs Sources
A1: Field | B1: Value / Note | C1: Source URL | D1: Notes
A2: Salary schedule | B2: FY27 Certified Salary Scales PDF; Gross Salary used. "A" certificate mapped to Bachelor's and "AA" certificate mapped to Master's. | C2: Uploaded file: FY27 CERTIFIED SALARY SCALES.pdf | D2: Corrected 2026-06-13. Prior values used conservative state-only schedule; revised to Ocean Springs gross salary (state + local contribution).
A3: Substitute pay | B3: $90/day | C3: https://www.mykelly.com/job/10102109-substitute-teachers-and-aides-ocean-springs-ms-ocean-springs-ms-united-states/ | D3: Kelly posting for Ocean Springs substitute teachers/aides displayed $90/day.
A4: District size / ratio | B4: 5,677 students, 416.00 classroom teachers, 13.65 student/teacher ratio, 7 total schools | C4: https://nces.ed.gov/ccd/districtsearch/district_detail.asp?ID2=2803360 | D4: NCES CCD 2024-2025 district data.
A5: School counts | B5: 1 high, 1 middle, 4 elementary, 1 other/specialty = 7 total | C5: https://nces.ed.gov/ccd/schoolsearch/school_list.asp?DistrictID=2803360&Search=1 | D5: Upper Elementary counted as elementary; Keys Vocational Center counted as other/specialty.
A6: Demographics | B6: White 69.19%; Hispanic 9.02%; Asian 2.89%; Black 12.61%; Other 6.29% | C6: NCES school-level detail pages for all nonzero-enrollment OSSD schools | D6: Percentages summed from school-level race/ethnicity counts. Other includes American Indian/Alaska Native, Native Hawaiian/Pacific Islander, and Two or More Races.
A7: Housing | B7: Median home price $294,824; median rent $2,100; PPSF $201 | C7: https://www.redfin.com/city/13826/MS/Ocean-Springs/housing-market ; https://www.zillow.com/rental-manager/market-trends/ocean-springs-ms/ | D7: Ocean Springs city market proxies used for district.
A8: Update applied | B8: Workbook 11 / Prototype 136 | C8: ChatGPT workbook/prototype update | D8: Ocean Springs School District, Mississippi added to comparison set.

Sheet Royal Sources
A1: Category | B1: Source | C1: URL | D1: Notes
A2: Salary schedule | B2: Royal ISD Teacher Pay Scale 25-26 | C2: https://files-backend.assets.thrillshare.com/documents/asset/uploaded_file/825/Royal_Isd/b9756bcb-f546-44fd-bcb7-78ce11815fb6/2025-2026_Royal_ISD_Teacher_Pay_Scale.pdf | D2: Used 25-26 total salary with HB2/TRA stipend; Master's +$1,000.
A3: HR page | B3: Royal ISD Human Resources | C3: https://www.royal-isd.net/o/royal-isd/page/human-resources | D3: Confirms 0-, 4-, 10-, 20-, and 26+ year teacher scale; district growth and campus context.
A4: Enrollment/demographics | B4: Texas Tribune Schools Explorer: Royal ISD | C4: https://schools.texastribune.org/districts/royal-isd/demographics/ | D4: Used enrollment/campus context and Hispanic share; detailed race breakdown cross-checked with HAR/TEA-style summary.
A5: District details | B5: NCES Royal ISD District Detail | C5: https://nces.ed.gov/ccd/districtsearch/district_detail.asp?ID2=4838190 | D5: Used teacher FTE to estimate student-teacher ratio from Texas Tribune enrollment / NCES teacher FTE.
A6: Housing | B6: Redfin 77423 Housing Market | C6: https://www.redfin.com/zipcode/77423/housing-market | D6: Used 77423 median sale price and price per sq ft for Royal ISD area.
A7: Rent | B7: Zillow Brookshire Rental Market | C7: https://www.zillow.com/rental-manager/market-trends/brookshire-tx/ | D7: Used Brookshire average rent for the district area.
A8: Substitute pay | B8: Royal ISD Substitute document page | C8: https://www.royal-isd.net/documents/departments/human-resources/substitutes/23184307 | D8: Public page lists a 2023-2024 Substitute Pay Schedule, but searchable text did not expose the rate; $125/day entered as provisional and should be verified.

Sheet Chicago Sources
A1: Category | B1: Source | C1: URL | D1: Notes
A2: Salary schedule | B2: CTU-CPS 2024–28 Contract PDF | C2: https://www.ctulocal1.org/contract.pdf | D2: Used A-1A 208-day teacher schedule: Lane 1 for Bachelor's and Lane 3 for Master's, 2025-26 Base + Step salary columns.
A3: Salary policy/context | B3: CPS compensation policy | C3: https://www.cps.edu/sites/cps-policy-rules/policies/300/302/302-8/ | D3: Confirms teacher salary schedules use lanes and steps under the CTU collective bargaining agreement.
A4: Substitute pay | B4: Teach Chicago Substitute Staff | C4: https://www.teach.cps.edu/substitute | D4: Used Professional Educator License substitute daily rate of $193/day.
A5: Enrollment and school counts | B5: CPS Stats and Facts | C5: https://www.cps.edu/about/stats-facts/ | D5: Used 2025-26 enrollment, 630 schools, school-category counts, and student racial makeup.
A6: Student/teacher ratio | B6: NCES District Detail | C6: https://nces.ed.gov/ccd/districtsearch/district_detail.asp?ID2=1709930&Search=2&details=1 | D6: Used 2024-25 student/teacher ratio of 13.77.
A7: Housing - median sale price/PPSF | B7: Redfin Chicago housing market | C7: https://www.redfin.com/city/29470/IL/Chicago/housing-market | D7: Used May 2026 median sale price of $419,749 and median sale price per square foot of $303.
A8: Housing - rent | B8: Zillow Chicago housing market | C8: https://www.zillow.com/home-values/17426/chicago-il/ | D8: Used May 31, 2026 average rent of $2,406.

Sheet Metro Nashville Sources
A1: Category | B1: Source | C1: URL | D1: Notes
A2: Salary | B2: MNPS Salaries and Resources | C2: https://www.mnps.org/careers/salaries-and-resources | D2: Official 2025-26 page states step increases and 3% COLA; detailed salary folder is in SharePoint.
A3: Salary Table | B3: Teach Nashville teacher salary images | C3: https://www.teach-nashville.com/teach-in-our-schools | D3: Public 2024-25 BA/MA teacher pay points used, multiplied by 1.03 for 2025-26.
A4: Substitute Pay | B4: MNPS Substitute Teaching | C4: https://www.mnps.org/careers/substitute-teaching | D4: Valid TN teaching license substitute rate = $145 per 7.5-hour day.
A5: Enrollment / schools | B5: NCES District Detail | C5: https://nces.ed.gov/ccd/districtsearch/district_detail.asp?DistrictID=4703180&ID2=4703180&Search=2&details=1 | D5: 2024-25 total students 81,021; total schools 162.
A6: Demographics | B6: Nashville Chamber MNPS by the Numbers | C6: https://nashvillechamber.report/edu-report-2022/mnps-by-the-numbers/ | D6: 2022-23 student race/ethnicity shares used: White 24.4, Black 39.2, Hispanic 32.2, Asian 3.8.
A7: Housing | B7: Redfin Nashville housing market | C7: https://www.redfin.com/city/13415/TN/Nashville/housing-market | D7: Median sale price/PPSF reference.
A8: Rent | B8: Zillow Nashville rental market | C8: https://www.zillow.com/rental-manager/market-trends/nashville-tn/ | D8: Average rent input.

Sheet Placement Rules
A1: District | B1: Status | C1: Rule Type | D1: How salary lookup should work | E1: Current action taken | F1: Source / note
A2: Salt Lake School District | B2: Confirmed | C2: Experience credit map | D2: User selects actual years; district credits 0-5 full, 6→5, 7-8→6, 9-10→7, 11-12→8, 13+→9. Schedule currently stored as actual-experience adjusted values. | E2: Protected with explicit metadata in prototype so future imports know Salt Lake is not simple 1:1 placement. | F2: SLCSD email shared by user; cites SLEA Written Agreement Article 17.
A3: Chicago Public Schools | B3: Confirmed | C3: Cap at 7 years | D3: For outside prior teaching experience, selected years above 7 should use 7 credited years for salary lookup. | E3: Updated Teacher Salary Data for years 8-10 to use year-7 salary; updated BA/MA 10-year values, Salary Score, and Overall Value Score. | F3: Teach Chicago salary page says CPS accepts up to 7 years of previous teaching experience toward salary placement.
A4: Los Angeles Unified | B4: Needs district-specific model | C4: Salary points / rating-in | D4: Placement depends on salary points, pay scale group/level, and years of experience granted after the bachelor's degree. | E4: Left current schedule as an estimate and flagged for future manual modeling. | F4: LAUSD Salary Allocation FAQ and Salary Tables pages.
A5: Metro Nashville Public Schools | B5: Estimated | C5: Unverified step placement | D5: 2025-26 detailed step placement logic was not publicly accessible in the signed-in SharePoint folder. | E5: Left current 2024-25 + 3% COLA estimate and flagged for verification. | F5: MNPS salary page confirms 2025-26 step increases and 3% COLA, but detailed folder requires sign-in.
A6: All other districts | B6: Pending/assumed simple | C6: 1:1 experience lookup unless contradicted | D6: For now, actual years equals schedule year. Future district additions should explicitly mark whether this is confirmed or assumed. | E6: No active change in this pass. | F6: Next audit pass should verify district-by-district hiring placement language.
A7: Arcadia Unified School District | B7: CA | C7: No prior-experience cap found in public schedule; Master's degree alone appears on same Column 1 as BA | D7: BA/MA without additional semester units use same salary column; additional units may move lanes. | E7: https://www.ausd.net/apps/pages/salaryschedules | F7: 2026-06-11
A8: Canyons School District | B8: UT | C8: cap | D8: 15 | E8: Prior contracted licensed school-system experience credited up to 15 increment levels; BA starts at level 1, MA at level 7. | F8: Official 2025-26 L186 schedule
A9: North Clackamas School District | B9: OR | C9: schedule mapping | D9: n/a | E9: Public schedule already maps experience-credit bands to salary steps for 0-10 years in the tool. | F9: Official 2025-26 licensed salary schedule
A10: Saint Helena Unified School District | B10: Assumed/simple | C10: BA/credential column + MA stipend | D10: Actual years map to schedule steps 1-11 for 0-10 years in the tool; MA entered as BA column plus $2,354 stipend. | E10: Added as public schedule model; no prior-experience cap found in public page during this pass. | F10: District 2025-26 salary schedule
A11: Chandler Unified School District | B11: Confirmed | C11: New-hire experience cap | D11: Credit max 8 years; credit begins in second year; BA schedule capped at year 8 for actual years 8-10; MA adds $1,250. | E11: Applied in prototype salarySchedule. | F11: CUSD 2025-26 Certified Staff Salary Schedule
A12: Flagstaff Unified School District | B12: Needs verification | C12: Salary lane unclear | D12: FUSD public page links certified salary schedule through Google Drive; detailed lane data not text-readable in search. | E12: BA/MA entered same pending verification. | F12: FUSD salary schedule page + public job snippets

Sheet Arcadia Sources
A1: Category | B1: Source | C1: URL | D1: Notes
A2: Salary schedule | B2: Arcadia USD Salary Schedules / ATA certificated schedule | C2: https://www.ausd.net/apps/pages/salaryschedules | D2: ATA schedule effective 7/1/2025; 186-day teacher schedule. Column 1 lists BA or MA, so MA-only uses same values as BA.
A3: Substitute pay | B3: Arcadia Unified is Hiring | C3: https://www.ausd.net/apps/pages/index.jsp?pREC_ID=2244925&type=d&uREC_ID=965712 | D3: District page says substitute teachers now pay $200/day.
A4: Student/teacher ratio | B4: NCES district detail | C4: https://nces.ed.gov/ccd/districtsearch/district_detail.asp?ID2=0602970 | D4: NCES 2024-25 lists 9,073 students, 369.09 classroom teachers, ratio 24.58, 11 total schools.
A5: Schools count | B5: Arcadia USD About AUSD | C5: https://www.ausd.net/apps/pages/Aboutausd | D5: AUSD reports six elementary, three middle, one high school, and one alternative school/outreach program.
A6: Demographics | B6: Arcadia USD Human Resource Services | C6: https://www.ausd.net/apps/pages/HR | D6: District page states approximately 9,900 students, 26% Caucasian, 61% Asian, and 10% Hispanic. Black entered as 1%, Other/Uncounted as 2% to total 100.
A7: Housing | B7: Redfin Arcadia housing market | C7: https://www.redfin.com/city/645/CA/Arcadia/housing-market | D7: Median sale price and median sale price per square foot.
A8: Rent | B8: Zillow Arcadia rental market trends | C8: https://www.zillow.com/home-values/50749/arcadia-ca/ | D8: Average rent $3,290 as of April 30, 2026.

Sheet North Clackamas Sources
A1: Category | B1: Source | C1: URL | D1: Note
A2: Salary | B2: 2025-26 Licensed Salary Schedule | C2: https://resources.finalsite.net/images/v1710375798/nclackk12orus/wc7eq0dxubrgofmfwetn/25-26LicensedSalarySchedule.pdf | D2: BA/MA 0-10 values entered from 193-day schedule.
A3: Substitute Pay | B3: Licensed Substitute Information | C3: https://www.nclack.k12.or.us/departments/human-resources/substitute-information/licensed-substitute-information | D3: General education full-day substitute rate $250.
A4: District Profile | B4: About NCSD | C4: https://www.nclack.k12.or.us/about-ncsd/about-ncsd | D4: Enrollment, demographics, and school counts.
A5: Student/Teacher Ratio | B5: NCES district detail | C5: https://nces.ed.gov/ccd/districtsearch/district_detail.asp?ID2=4108830 | D5: 2024-25 total students/classroom teachers ratio.
A6: Housing | B6: Redfin Milwaukie housing market | C6: https://www.redfin.com/city/30776/OR/Milwaukie/housing-market | D6: Median sale price and PPSF.
A7: Rent | B7: Zillow Milwaukie rent trends | C7: https://www.zillow.com/rental-manager/market-trends/milwaukie-or/ | D7: Average rent.

Sheet Canyons Sources
A1: Category | B1: Source | C1: URL | D1: Note
A2: Salary | B2: 2025-26 Licensed Salary Schedule L186 | C2: https://www.canyonsdistrict.org/download/1749/2025-2026/221662/2025-2026-licensed-salary-schedule-l186.pdf | D2: BA/MA placement modeled from increment levels.
A3: Salary Page | B3: Canyons Salary Schedule page | C3: https://www.canyonsdistrict.org/depts/hr/salary-schedule/ | D3: Official salary schedule listing.
A4: Substitute Pay | B4: Canyons Substitutes page | C4: https://www.canyonsdistrict.org/depts/hr/substitutes/ | D4: Licensed substitute rate $180/day.
A5: Student/Teacher Ratio | B5: NCES district detail | C5: https://nces.ed.gov/ccd/districtsearch/district_detail.asp?DistrictID=4900142&ID2=4900142&Search=2&details=1 | D5: 2024-25 total students/classroom teachers ratio and total schools.
A6: Demographics | B6: USBE District Profile | C6: https://reportcard.schools.utah.gov/District/Profile?DistrictID=186056&schoolyearendyear=2022 | D6: Official demographic distribution used as available.
A7: Housing | B7: Redfin Sandy housing market | C7: https://www.redfin.com/city/17265/UT/Sandy/housing-market | D7: Median sale price and PPSF.
A8: Rent | B8: Zillow Sandy rent trends | C8: https://www.zillow.com/rental-manager/market-trends/sandy-ut/ | D8: Average rent.

Sheet St Helena Sources
A1: Category | B1: Value / Note | C1: Source URL | D1: Last Verified
A2: Salary schedule | B2: 2025-26 certificated salary schedule, 186 days; BA/credential column used; MA stipend +$2,354 applied. | C2: https://files.smartsites.parentsquare.com/6174/acuo9a7to8ak2epgjbc.pdf | D2: 2026-06-11
A3: District salary page | B3: District salary & stipend schedule page lists 2025-26 salary schedules. | C3: https://www.sthelenaunified.org/73799_3 | D3: 2026-06-11
A4: Substitute process | B4: SHUSD says Napa COE maintains the substitute call list; each district is a separate employer. | C4: https://www.sthelenaunified.org/73800_3 | D4: 2026-06-11
A5: Substitute pay input | B5: NCOE substitute teacher pay rates for 2026-27 show credentialed teacher daily rate of $275; used provisionally as licensed sub pay. | C5: https://napacoe.org/wp-content/uploads/2026/05/sub_rates_26.27.pdf | D5: 2026-06-11
A6: NCES district profile | B6: NCES lists Saint Helena Unified: 5 schools, 1,105 students, 82.96 teachers, 13.32 student/teacher ratio. | C6: https://nces.ed.gov/ccd/districtsearch/district_detail.asp?ID2=0637830 | D6: 2026-06-11
A7: CDE district profile | B7: CDE profile lists 2025-26 enrollment as 1,152 and English learners as 127 (11.0%). | C7: https://www.cde.ca.gov/sdprofile/details.aspx?cds=28662900000000 | D7: 2026-06-11
A8: Demographics | B8: Public School Review summary used for race/ethnicity percentages: Hispanic 53%, White 42%, Asian 2%, Black 1%, Two or more 2%. | C8: https://www.publicschoolreview.com/california/saint-helena-unified-school-district/637830-school-district | D8: 2026-06-11
A9: Home price | B9: Redfin St. Helena housing market median sale price: $2,323,609. | C9: https://www.redfin.com/city/16448/CA/St-Helena/housing-market | D9: 2026-06-11
A10: Price per sq ft | B10: Redfin 94574 housing market median sale price per square foot: $903. | C10: https://www.redfin.com/zipcode/94574/housing-market | D10: 2026-06-11
A11: Rent | B11: Zillow Rental Manager average rent in Saint Helena, CA: $5,995. | C11: https://www.zillow.com/rental-manager/market-trends/saint-helena-ca/ | D11: 2026-06-11

Sheet Sub Staffing Notes
A1: District | B1: Staffing Model | C1: Penalty Applied | D1: Evidence | E1: Source URL
A2: North Clackamas School District | B2: ESS full licensed/classified substitute provider | C2: Sub Pay Score × 60% | D2: District says ESS is responsible for hiring, training, and placement of licensed/classified substitutes. | E2: https://www.nclack.k12.or.us/departments/human-resources/substitute-information
A3: Provo City School District | B3: Third-party substitute provider (Edustaff); ESS/Willsub job listing also found historically | C3: Sub Pay Score × 60% | D3: Current district page says Provo partnered with Edustaff to supply/manage substitute workforce; substitute work is not district-managed. | E3: https://provo.edu/employment-opportunities/substitute-information/
A4: Scoring rule | B4: district / third-party | C4: District-managed = 100%; full third-party substitute provider = 60% | D4: Penalty only affects Sub Pay Score and therefore overall score by the Sub Pay Score weight. | E4: https://ess.com/k12-substitutesolutions/
A5: Flagstaff Unified School District | B5: district | C5: No penalty | D5: No ESS/third-party substitute staffing confirmed in first pass; district uses Red Rover postings. | E5: https://jobs.redroverk12.com/org/fusd1/opening/177926
A6: Chandler Unified School District | B6: district | C6: No penalty | D6: CUSD page lists district HR substitute services contacts and SmartFind Express. | E6: https://www.cusd80.com/human-resources/substitutes

Sheet Flagstaff Sources
A1: Category | B1: Value / Note | C1: Source URL | D1: Notes
A2: Salary | B2: Provisional BA/MA schedule: $50,910 to $57,285, linearly distributed 0-10 years | C2: https://www.fusd1.org/42660_4 | D2: Certified Salary Schedule is linked from FUSD page via Google Drive; searchable public job snippets show the range. Verify lane details later.
A3: Substitute pay | B3: $140/day; Leupp $155/day noted | C3: https://jobs.redroverk12.com/org/fusd1/opening/177926 | D3: Used standard substitute teacher pay.
A4: NCES ratio/enrollment | B4: 8,595 students; 548.29 teachers; ratio 15.68 | C4: https://nces.ed.gov/ccd/districtsearch/district_detail.asp?DistrictID=0402860&ID2=0402860&Search=2&details=1 | D4: 2024-25 CCD.
A5: School count | B5: 15 comprehensive school sites; school list shows 3 high and 2 middle schools | C5: https://www.fusd1.org/aboutfusd | D5: District about page and school list.
A6: Demographics | B6: White 39.8%; Hispanic 30.9%; Asian/Pacific 0.8%; Black 0.8%; Other 27.7% | C6: https://www.neighborhoodscout.com/az/flagstaff/schools | D6: Used for prototype balance scoring.
A7: Housing | B7: Median sale $710K; PPSF $368 | C7: https://www.redfin.com/city/6089/AZ/Flagstaff/housing-market | D7: Redfin citywide market page.
A8: Rent | B8: $2,300 average rent | C8: https://www.zillow.com/rental-manager/market-trends/flagstaff-az/ | D8: Zillow Rental Manager.

Sheet Chandler Sources
A1: Category | B1: Value / Note | C1: Source URL | D1: Notes
A2: Salary | B2: 2025-26 teacher entry $55,249; max $91,559; new-hire schedule through 8 years; MA stipend $1,250 | C2: https://resources.finalsite.net/images/v1750874174/cusd80com/ctubigjt873gcyob84yf/Certified_Teacher_Salary_Schedule_2025-2026.pdf | D2: CUSD caps new-teacher experience credit at 8 years.
A3: Substitute pay | B3: $170/day certified substitute; long-term $200/day | C3: https://www.cusd80.com/human-resources/substitutes | D3: Used certified substitute rate.
A4: NCES ratio/enrollment | B4: 41,421 students; 2,354.92 teachers; ratio 17.59 | C4: https://nces.ed.gov/ccd/districtsearch/district_detail.asp?ID2=0401870&Search=2 | D4: 2024-25 CCD.
A5: School count | B5: 31 elementary; 5 junior highs; 2 middle; 5 high; 4 alternatives; 1 secondary; 1 online | C5: https://www.cusd80.com/about-us/about-cusd | D5: Middle count entered as 7 = 5 junior highs + 2 middle schools; other=6.
A6: Demographics | B6: White 47.7%; Hispanic 31.9%; Asian/Pacific 12.5%; Black 5.8%; Other 2.1% | C6: https://www.neighborhoodscout.com/az/chandler/schools | D6: Used for prototype balance scoring.
A7: Housing | B7: Median sale $520K; PPSF $286 | C7: https://www.redfin.com/city/3104/AZ/Chandler/housing-market | D7: Redfin citywide market page.
A8: Rent | B8: $2,388 average rent | C8: https://www.zillow.com/rental-manager/market-trends/chandler-az/ | D8: Zillow Rental Manager.

Sheet Work Environment Notes
A1: District | B1: Risk Level | C1: Multiplier | D1: Penalty | E1: Pre-Risk Score | F1: Final Score | G1: Rationale | H1: Source URLs / verification links
A2: Alief ISD | B2: Moderate | C2: 0.9 | D2: 10% reduction | E2: 54.141969 | F2: 48.727772 | G2: 10% employment-stability penalty due to enrollment-loss pressure, charter competition, and budget-cut concerns. | H2: https://www.houstonlanding.org/i-want-to-fight-alief-isd-confronts-enrollment-losses-charter-growth-as-budget-cuts-loom/
A3: Arcadia Unified School District | B3: High | C3: 0.85 | D3: 15% reduction | E3: 41.956892 | F3: 35.663358 | G3: 15% employment-stability penalty because district budget updates indicated teacher-layoff risk unless local funding support fills the gap. | H3: https://www.ausd.net/apps/pages/index.jsp?pREC_ID=1287273&type=d&uREC_ID=965712
A4: Austin ISD | B4: Severe | C4: 0.8 | D4: 20% reduction | E4: 49.648505 | F4: 39.718804 | G4: 20% employment-stability penalty due to very large projected budget gap, planned job cuts, school-closure discussions, and possible governance/fiscal instability. | H4: https://www.kut.org/education/2026-06-03/austins-isd-budget-cuts-teachers-librarians-police | https://www.austinisd.org/budget | https://www.axios.com/local/austin/2026/06/10/austin-public-schools-state-takeover
A5: Barbers Hill ISD | B5: Stable / growth district | C5: 1 | D5: No reduction | E5: 59.352069 | F5: 59.352069 | G5: No current employment-stability penalty applied. Barbers Hill is a fast-growth district; Texas Tribune reports enrollment of 8,088 students in 2026, up 59.1% since 2016, and no reliable public evidence of broad layoffs/closures was found in this pass. | H5: https://schools.texastribune.org/districts/barbers-hill-isd/ ; https://www.bhisd.net/departments/finance/finance-information ; https://www.bhisd.net/
A6: Canyons School District | B6: Moderate | C6: 0.9 | D6: 10% reduction | E6: 49.053731 | F6: 44.148358 | G6: 10% employment-stability penalty due to declining enrollment and possible elementary-school changes/closures; no broad layoff evidence found in first pass. | H6: https://kutv.com/news/2news-investigates/8-canyons-district-schools-studied-for-potential-changes-as-enrollment-falls
A7: Chandler Unified School District | B7: High | C7: 0.85 | D7: 15% reduction | E7: 43.930296 | F7: 37.340751 | G7: 15% employment-stability penalty due to declining enrollment, budget shortfall, and staffing-reduction/job-cut plan. | H7: https://www.12news.com/article/news/local/valley/chandler-unified-passes-job-cuts-puts-library-and-technology-positions-on-hold/75-fc34b00f-faab-42dd-b87e-32a29c0483bb | https://www.azfamily.com/2026/01/14/chandler-unified-discuss-cutting-about-120-jobs-amid-declining-enrollment/
A8: Chapel Hill-Carrboro City Schools | B8: High | C8: 0.85 | D8: 15% reduction | E8: 55.568794 | F8: 47.233475 | G8: 15% employment-stability penalty due to staff cuts, school-closure discussions, declining enrollment, and budget shortfall concerns. | H8: https://www.wunc.org/education/2026-04-10/chapel-hill-carrboro-schools-cuts-staff | https://www.axios.com/local/raleigh/2026/02/13/chapel-hill-carrboro-city-schools-closure-north-carolina
A9: Cherry Creek School District | B9: High | C9: 0.85 | D9: 15% reduction | E9: 63.759359 | F9: 54.195455 | G9: 15% employment-stability penalty due to announced job reductions and districtwide budget-cut plan. | H9: https://www.9news.com/article/news/education/cherry-creek-school-district-cutting-159-jobs-reducing-expenses-by-23-million-amid-budget-shortfall/73-32f218aa-7304-4a2a-bc27-b2a217049982 | https://www.denver7.com/news/investigations/cherry-creek-school-district-announces-budget-cuts-amid-shortfall
A10: Chicago Public Schools | B10: High | C10: 0.85 | D10: 15% reduction | E10: 65.705535 | F10: 55.849704 | G10: 15% employment-stability penalty due to structural deficit and reported teacher-position reductions / higher class-size planning. | H10: https://www.wbez.org/education/2026/05/12/cps-plans-cut-teacher-positions-raise-class-sizes-shrink-723-million-deficit | https://www.chalkbeat.org/chicago/2026/05/12/chicago-public-schools-releases-school-budgets/
A11: Denver Public Schools | B11: Moderate | C11: 0.9 | D11: 10% reduction | E11: 62.233833 | F11: 56.01045 | G11: 10% employment-stability penalty due to central-office layoffs, declining enrollment pressure, and warnings about possible additional school closures. | H11: https://coloradosun.com/2025/02/28/denver-public-schools-lays-off-38-central-office-staff-which-will-save-the-district-5-million-a-year/ | https://www.chalkbeat.org/colorado/2026/05/13/denver-public-schools-budget-need-for-more-school-closures/
A12: Eanes ISD | B12: Moderate | C12: 0.9 | D12: 10% reduction | E12: 35.572913 | F12: 32.015622 | G12: 10% employment-stability penalty due to shortfall concerns, consolidation/closure actions, and cost-saving measures; recent cuts may partially stabilize the outlook. | H12: https://communityimpact.com/austin/lake-travis-westlake/education/2026/03/26/eanes-isd-projects-ongoing-budget-shortfall-in-2026-27-despite-cost-cuts/ | https://communityimpact.com/austin/lake-travis-westlake/education/2026/04/29/eanes-isd-could-see-16-million-budget-surplus-next-year-following-cuts/ | https://www.eanesisd.net/post/~board/district-news/post/eanes-isd-approves-cost-saving-measures-to-mitigate-deficit
A13: Flagstaff Unified School District | B13: Moderate | C13: 0.9 | D13: 10% reduction | E13: 45.391553 | F13: 40.852398 | G13: 10% employment-stability penalty due to enrollment/funding stress, long-term financial-planning concerns, and override dependence. | H13: https://www.fusd1.org/fusd-long-term-financial-planning | https://www.instagram.com/reel/DWhltMJkgW5/
... A15: Glendora Unified School District | B15: Watchlist | C15: 0.95 | D15: 5% reduction | E15: 57.164218 | F15: 54.306007 | G15: 5% watchlist penalty because current layoff evidence is unclear; needs official budget/interim report verification. | H15: https://patch.com/california/glendora/glendora-unified-approves-30-teacher-layoffs
A16: High | B16: 0.85 | C16: Active layoffs, teacher/classified cuts, major deficit, school closures, or serious labor/process concerns. | D16: 40
A17: Jordan District | B17: Stable / no current evidence | C17: 1 | D17: No reduction | E17: 51.831002 | F17: 51.831002 | G17: No current employment-stability penalty applied; first-pass research did not find reliable current layoff evidence. | H17: https://policy.jordandistrict.org/sub/layoffs/
A18: Katy ISD | B18: Moderate | C18: 0.9 | D18: 10% reduction | E18: 60.544355 | F18: 54.489919 | G18: 10% employment-stability penalty due to budget pressure and staffing-reduction risk, partly mitigated by attrition/vacancy-based approach. | H18: https://communityimpact.com/houston/katy-fulshear/education/2026/03/26/katy-isd-could-face-a-net-staffing-reduction-for-2026-27-school-year/ | https://coveringkaty.com/education/katy-isd-facing-29-million-budget-shortfall-after-fewer-stud/
A19: La Cañada Unified School District | B19: Stable / no current evidence | C19: 1 | D19: No reduction | E19: 35.656907 | F19: 35.656907 | G19: No current employment-stability penalty applied; first-pass research did not find reliable current layoff evidence. | H19: https://www.instagram.com/p/DNYlKjBPR6o/
A20: Lake Washington School District | B20: WA | C20: Watchlist / declining enrollment and budget pressure | D20: 0.95 | E20: 75 | F20: 5% watchlist penalty applied. LWSD has strong salary and high district quality, but current budget planning references declining enrollment, rising costs, and state/local funding constraints. No broad active layoff evidence found in this pass. | G20: First-pass public-source screening; verify with adopted budget, board packets, audit/ACFR, enrollment trend, and union/HR notices before final scoring. | H20: https://www.lwsd.org/employment/teachers-certificated-employees/salary-schedules ; https://nces.ed.gov/ccd/districtsearch/district_detail.asp?DistrictID=5304230 ; https://www.apartments.com/rent-market-trends/redmond-wa/ ; https://www.redfin.com/city/14913/WA/Redmond/housing-market ; https://www.lwsd.org/about/enrollment-report
A21: Leander ISD | B21: Moderate | C21: 0.9 | D21: 10% reduction | E21: 54.830361 | F21: 49.347325 | G21: 10% employment-stability penalty due to declining enrollment, projected deficit, and school-closure/consolidation discussions; teacher-layoff risk appears partly mitigated by attrition. | H21: https://www.statesman.com/news/local/article/leander-school-closure-steiner-ranch-faubion-21237195.php
A22: Los Angeles Unified | B22: Severe | C22: 0.8 | D22: 20% reduction | E22: 44.99809 | F22: 35.998472 | G22: 20% employment-stability penalty due to large-scale job-loss reports, approved layoffs, fiscal-stability planning, and possible multi-year reductions/closures/furloughs. | H22: https://www.latimes.com/california/story/2026-05-21/more-than-1-000-la-school-employees-expected-to-lose-jobs-with-bigger-cuts-ahead | https://laist.com/news/education/lausd-reduction-in-force-vote-may-2026-budget-preview | https://www.chalkbeat.org/2026/05/28/schools-making-budget-cuts-and-layoffs-due-to-inflation-enrollment-declines/
A23: Madison Metropolitan School District | B23: Low / Unknown | C23: 1 | D23: No reduction | E23: 69.792953 | F23: 69.792953 | G23: No current employment-stability penalty applied in this restoration pass; verify with adopted budget, board packets, audit/ACFR, enrollment trend, and union/HR notices before final scoring. | H23: https://www.madison.k12.wi.us/about
A24: Metro Nashville Public Schools | B24: Watchlist | C24: 0.95 | D24: 5% reduction | E24: 55.306635 | F24: 52.541303 | G24: 5% watchlist penalty due to budget-pressure reporting tied to expiring federal aid/funding issues, without strong current broad-layoff evidence. | H24: https://fox17.com/news/crisis-in-the-classroom/nashville-schools-face-funding-issues-as-federal-aid-ends-mayor-seeks-14-billion
A25: Moderate | B25: 0.90 | C25: Cuts, closures, attrition-based reductions, central-office layoffs, or notable enrollment/funding pressure. | D25: 60
A26: Nassau County School District | B26: FL | C26: Stable / no current layoff evidence found | D26: 1 | E26: 100 | F26: No penalty applied. Current pass found strong public-facing district performance signals and no broad layoff/closure/fiscal-crisis warning comparable to Austin, Oakland, LAUSD, or Portland. | G26: First-pass public-source screening; verify with adopted budget, board packets, audit/ACFR, enrollment trend, and union/HR notices before final scoring. | H26: https://www.nassau.k12.fl.us/page/instructional-salaries ; https://files-backend.assets.thrillshare.com/documents/asset/uploaded_file/5569/Ncsd/f73c8433-23bf-4388-aa76-259dafad90d2/24-27_NTA_Ratified_Amended_with_Signatures__25.pdf ; https://nces.ed.gov/ccd/districtsearch/district_detail.asp?ID2=1201350 ; https://www.apartments.com/rent-market-trends/yulee-fl/ ; https://www.redfin.com/zipcode/32097/housing-market
A27: North Clackamas School District | B27: Watchlist | C27: 0.95 | D27: 5% reduction | E27: 63.209015 | F27: 60.048564 | G27: 5% watchlist penalty due to Portland-area funding climate and active budget review; no strong current broad layoff evidence found in first pass. | H27: https://www.nclack.k12.or.us/departments/superintendent/community-conversations
A28: Oakland Unified School District | B28: Severe | C28: 0.8 | D28: 20% reduction | E28: 55.021761 | F28: 44.017408 | G28: 20% employment-stability penalty due to major deficit, approved large-scale layoffs, and labor/fiscal instability concerns. | H28: https://abc7news.com/post/oakland-unified-school-district-board-education-approves-hundreds-layoffs-amid-100m-budget-deficit/18652323/ | https://www.ktvu.com/news/oakland-school-board-approves-400-layoffs | https://www.sfchronicle.com/eastbay/article/oakland-school-teacher-union-salary-22268594.php
A29: Ocean Springs School District | B29: Stable / no current evidence | C29: 1 | D29: No reduction | E29: 46.296574 | F29: 46.296574 | G29: No current employment-stability penalty applied; first-pass research did not find reliable current layoff evidence.
A30: Oxnard Union High School District | B30: High | C30: 0.85 | D30: 15% reduction | E30: 60.108231 | F30: 51.091996 | G30: 15% employment-stability penalty due to formal budget-stabilization planning and reported job-cut risk. | H30: https://www.oxnardunion.org/fs/resource-manager/view/6d05e87b-c4eb-4c75-b310-43c668c06ab7
A31: Portland Public Schools | B31: High | C31: 0.85 | D31: 15% reduction | E31: 74.349012 | F31: 63.19666 | G31: 15% employment-stability penalty retained due to active budget shortfall, furlough context, layoff notices, and labor grievance/process concerns. | H31: https://www.opb.org/article/2026/06/09/as-portland-teachers-receive-layoff-notices-union-raises-objections/ | https://www.wweek.com/news/schools/2026/04/28/portland-public-schools-faces-56-million-budget-deficit-as-superintendent-proposes-336-layoffs/ | https://www.pps.net/departments/human-resources/employee-resources/furloughs-2025-26
A32: Provo City School District | B32: Moderate | C32: 0.9 | D32: 10% reduction | E32: 50.460413 | F32: 45.414372 | G32: 10% employment-stability penalty due to active budget-reduction discussions and enrollment/funding challenges. | H32: https://provo.edu/updates-from-board-meeting-and-budget-discussions/
A33: Royal ISD | B33: Stable / no current evidence | C33: 1 | D33: No reduction | E33: 50.53222 | F33: 50.53222 | G33: No current employment-stability penalty applied; first-pass research did not find reliable current layoff evidence.
A34: Saint Helena Unified School District | B34: Stable / no current evidence | C34: 1 | D34: No reduction | E34: 47.234842 | F34: 47.234842 | G34: No current employment-stability penalty applied; first-pass research did not find reliable current layoff evidence. | H34: https://www.sthelenaunified.org/73718_3
A35: Salt Lake School District | B35: Watchlist | C35: 0.95 | D35: 5% reduction | E35: 63.374091 | F35: 60.205386 | G35: 5% watchlist penalty due to strained funding/program cuts, but no strong current evidence of broad teacher layoffs. | H35: https://www.axios.com/local/salt-lake-city/2026/04/07/salt-lake-city-school-district-ends-adult-community-ed-classes | https://citizenportal.ai/articles/6566082/Utah/School-Boards/Salt-Lake-School-District/Salt-Lake-City-School-District-previews-202526-budget-officials-warn-special-education-and-nutrition-funds-remain-strained
A36: San Antonio ISD | B36: High | C36: 0.85 | D36: 15% reduction | E36: 50.771678 | F36: 43.155926 | G36: 15% employment-stability penalty due to major deficit, school closures, declining enrollment, hiring freeze/cuts, and staffing-reduction risk. | H36: https://sanantonioreport.org/2026-budget-cuts-saisd-cut-food-drives-hiring-freeze/ | https://www.expressnews.com/news/education/article/san-antonio-isd-budget-cuts-staffing-22079601.php
A37: San Diego Unified School District | B37: High | C37: 0.85 | D37: 15% reduction | E37: 54.066164 | F37: 45.95624 | G37: 15% employment-stability penalty due to active budget stress and classified layoff notices. | H37: https://www.nbcsandiego.com/news/local/san-diego-unified-school-district-layoffs/3990321/ | https://sandiegounified.org/about/budget/2026-27_budget_information
A38: San Jose Unified School District | B38: Moderate | C38: 0.9 | D38: 10% reduction | E38: 53.974191 | F38: 48.576772 | G38: 10% employment-stability penalty due to school-closure risk and declining-enrollment pressure. | H38: https://sanjosespotlight.com/news/policy/education/page/2/
A39: Severe | B39: 0.80 | C39: Large-scale layoffs, very large structural deficit, fiscal/governance crisis, or major closure/cut program. | D39: 25
A40: South Pasadena Unified School District | B40: Watchlist | C40: 0.95 | D40: 5% reduction | E40: 51.158389 | F40: 48.600469 | G40: 5% watchlist penalty because current evidence is limited; older cuts are stale but budget risk should still be monitored. | H40: https://southpasadenan.com/board-of-education-to-vote-on-landmark-budget-spusd-faces-layoffs-in-face-of-shortfall/ | https://tigernewspaper.com/sphs-lays-off-two-teachers-anticipating-smaller-incoming-class-size/
A41: Stability band | B41: Multiplier | C41: Meaning | D41: Display Score
A42: Stable / no current evidence | B42: 1.00 | C42: No penalty; first-pass scan found no reliable current layoff/deficit evidence. | D42: 100
A43: Syosset Central School District | B43: Stable / no current evidence | C43: 1 | D43: No reduction | E43: 62.386978 | F43: 62.386978 | G43: No current employment-stability penalty applied; first-pass research did not find reliable current layoff evidence. | H43: https://citizenportal.ai/articles/6239455/new-york/school-districts/syosset-central-school-district/board-grants-tenure-to-more-than-70-staff-members-in-single-action
A44: Watchlist | B44: 0.95 | C44: Budget pressure, enrollment decline, or stale/unclear risk, but no strong current evidence of broad layoffs. | D44: 75

Sheet Scarsdale Sources
A1: Topic | B1: Finding used | C1: Source URL | D1: Notes
A2: Employment contract | B2: Scarsdale Teachers Association contract runs July 1, 2024 through June 30, 2028; MOA states salary schedule increases for 2025-26. | C2: https://www.scarsdaleschools.k12.ny.us/119192_3 ; https://go.boarddocs.com/ny/scarsdale/Board.nsf/files/D5WQJL66FCE9/%24file/MOA%20with%20Scarsdale%20Teachers%20Association%20%28STA%29.pdf | D2: Salary schedule estimated from 2021-22 schedule and 2024-2028 MOA/search-result values; verify against final 2026-27 schedule if published separately.
A3: Budget / stability | B3: 2026-27 budget is tax-cap constrained but not in a crisis pattern; district notes reductions needed and prefers attrition over layoffs where possible. | C3: https://www.scarsdaleschools.org/index.php?articleID=74973066&pageID=smartSiteFeed&psqFeed=true | D3: Used to classify as stable / no current layoff penalty, but with a note that this should be rechecked annually.
A4: Enrollment / staffing | B4: NCES lists 4,713 students, 420.60 classroom teachers, and student-teacher ratio of 11.21 for 2024-25. | C4: https://nces.ed.gov/ccd/districtsearch/district_detail.asp?ID2=3625950 | D4: Used for student-teacher ratio and profile counts.
A5: Housing | B5: Redfin reports Scarsdale median sale price of $2,088,750 and median sale price per square foot of $752 over the three months ending May 2026. | C5: https://www.redfin.com/city/16773/NY/Scarsdale/housing-market | D5: Used for home price and PPSF.
A6: Rent | B6: Realtor.com reports Scarsdale median rent at $5.5K/month. | C6: https://www.realtor.com/local/market/new-york/westchester-county/scarsdale | D6: Used for median rent; Zillow all-property rent was much higher, so this is a conservative/high but not extreme input.
A7: Substitute pay | B7: Indeed estimates Scarsdale Public Schools substitute teacher daily pay at approximately $163. | C7: https://www.indeed.com/cmp/Scarsdale-Public-Schools/salaries/Substitute-Teacher/Scarsdale-NY | D7: Not official; mark for later verification from HR posting or board packet.

Sheet Barbers Hill Sources
A1: Topic | B1: Finding used | C1: Source URL | D1: Notes
A2: Salary schedule | B2: 2025-26 salary plan starts at $66,000; year 10 is $77,498; year 20 is $89,352; year 40 is $99,802. | C2: https://www.bhisd.net/fs/resource-manager/view/dbc34877-69be-4721-8aaf-96c8ce9f200f | D2: Official Barbers Hill ISD salary plan; no separate BA/MA lane was found, so the prototype uses the same schedule for Bachelor's and Master's until a degree-specific schedule is verified.
A3: Average teacher pay | B3: Texas Tribune reports Barbers Hill's base average teaching salary was $80,786 in 2025. | C3: https://schools.texastribune.org/districts/barbers-hill-isd/teacher-salary/ | D3: Used as a cross-check that Barbers Hill is a high-paying Texas district.
A4: Enrollment / stability | B4: Texas Tribune reports 8,088 students in 2026, up 59.1% since 2016; district has 9 campuses. | C4: https://schools.texastribune.org/districts/barbers-hill-isd/ | D4: Used to classify the district as stable/growth rather than declining-enrollment risk.
A5: Student-teacher ratio | B5: Texas Tribune reports 13 students per teacher in 2025. | C5: https://schools.texastribune.org/districts/barbers-hill-isd/student-teacher/ | D5: Used for the Student-Teacher Ratio input.
A6: Demographics | B6: HAR/TEA-style profile lists 57.2% White, 32.1% Hispanic, 4.8% African American, 1.9% Asian, and 3.7% two or more races; Texas Tribune 2026 overview reports 56.1% White. | C6: https://www.har.com/school_district/barbers-hill-isd_036902 ; https://schools.texastribune.org/districts/barbers-hill-isd/demographics/ | D6: Used full HAR breakdown for prototype inputs; Texas Tribune used as a current White-share cross-check.
A7: Housing / rent | B7: Redfin reports Mont Belvieu median sale price of $457,726; Apartments.com reports average rent of $1,496 and two-bedroom rent around $1,745. | C7: https://www.redfin.com/city/12568/TX/Mont-Belvieu/housing-market ; https://www.apartments.com/rent-market-trends/mont-belvieu-tx/ | D7: Prototype uses $1,496 as the rent input to align with apartment-rent style inputs used in prior rows; two-bedroom rent should be tracked as a possible alternate input.
A8: Substitute pay | B8: Barbers Hill Substitute Info page lists Certified Classroom Teacher pay as $135/day. | C8: https://www.bhisd.net/departments/human-resources/substitute-infofrontline | D8: Used as Licensed Sub Pay.

Sheet Cobb Sources
A1: Category | B1: Finding | C1: Source URL | D1: Notes
A2: Salary | B2: 2025-26 teacher salary schedule; BA/MA steps captured for years 0-10. | C2: https://media.cobbk12.org/media/WWWCobb/medialib/teacher-salary-schedule.56404f113440.pdf | D2: Schedule also lists substitute teacher pay at $150/day.
A3: Schools / demographics | B3: District lists 66 elementary, 26 middle, 17 high, plus 3 other/specialty; student demographics from Georgia DOE October 2025 FTE Count. | C3: https://www.cobbk12.org/the-district | D3: Used for high school count and demographic balance.
A4: Stability | B4: Budget messaging says no teacher layoffs; local reporting notes reductions handled through attrition/reassignment. | C4: https://www.cobbk12.org/cobb-schools-delivers-balanced-budget-focused-on-classrooms-safety-and-long-term-stability.128573 | D4: Stability Score 100 for no current layoff evidence; monitor enrollment-driven staffing adjustments.
A5: Ratio | B5: NCES 2024-25 reports 105,738 students, 7,518.80 classroom teachers, ratio 14.06. | C5: https://nces.ed.gov/ccd/districtsearch/district_detail.asp?ID2=1301290 | D5: Used for student-teacher ratio.
A6: Rent | B6: Apartments.com June 2026 Marietta two-bedroom average rent. | C6: https://www.apartments.com/rent-market-trends/marietta-ga/ | D6: Used $1,534 median rent proxy.
A7: Home price / PPSF | B7: Redfin Marietta housing market; median sale price and $/sq ft. | C7: https://www.redfin.com/city/12766/GA/Marietta/housing-market | D7: Used $475,000 and $212/sq ft.

Sheet Gwinnett Sources
A1: Category | B1: Finding | C1: Source URL | D1: Notes
A2: Salary | B2: 2025-26 teacher salary schedule; BA/MA steps captured for years 0-10. | C2: https://resources.finalsite.net/images/v1719000691/gcpsk12org/lmrrhx4bc5hdy3ivppap/2024-2025_Teacher_Salary_Scheduleeq.pdf | D2: Effective July 2025, 2025-26 school year.
A3: Schools / demographics | B3: GCPS lists 81 elementary, 29 middle, 24 high, 7 special entities, 1 charter; racial/ethnic distribution October 2025. | C3: https://www.gcpsk12.org/about-us/gcps-by-the-numbers | D3: Used for high school count and demographic balance.
A4: Sub pay | B4: GCPS substitute management page lists substitute teacher pay at $130/day. | C4: https://www.gcpsk12.org/about-us/careers/hr-support/substitute-management/general-information | D4: Extended substitute $150/day not used as base.
A5: Ratio | B5: NCES 2024-25 reports 182,518 students, 12,796.10 classroom teachers, ratio 14.26. | C5: https://nces.ed.gov/ccd/districtsearch/district_detail.asp?ID2=1302550 | D5: Used for student-teacher ratio.
A6: Rent | B6: Apartments.com June 2026 Lawrenceville two-bedroom average rent. | C6: https://www.apartments.com/rent-market-trends/lawrenceville-ga/ | D6: Used $1,718 median rent proxy.
A7: Home price / PPSF | B7: Redfin Lawrenceville housing market; median sale price and $/sq ft. | C7: https://www.redfin.com/city/11598/GA/Lawrenceville/housing-market | D7: Used $365,000 and $165/sq ft.

Sheet Loudoun Sources
A1: Category | B1: Finding / Use | C1: Source URL | D1: Notes
A2: Salary schedule | B2: FY2026 Teacher Salary Scale A used for BA and MA values at steps 1, 6, and 11. | C2: https://aptg.co/Pq3SSc | D2: LCPS official PDF, 197-day scale. Steps do not equate directly to years; prototype maps steps to experience bands consistently with other entries.
A3: Compensation page | B3: Current LCPS classification/compensation page confirms FY2026 salary scale source. | C3: https://www.lcps.org/o/hr/page/classification-compensation | D3: Official LCPS HR page.
A4: District size / total schools / ratio | B4: NCES lists LCPS with 102 schools, 81,486 students, 6,719.23 classroom teachers, and 12.13 student/teacher ratio. | C4: https://nces.ed.gov/ccd/districtsearch/district_detail.asp?ID2=5102250 | D4: Used for total schools and student-teacher ratio.
A5: Fact sheet | B5: LCPS fact sheet says the division serves more than 80,000 students and 13,000 employees across over 100 schools. | C5: https://aptg.co/Z7KZxN | D5: Used as supporting context.
A6: Rent | B6: Ashburn average two-bedroom rent used as median rent input: $2,680/month. | C6: https://www.apartments.com/rent-market-trends/ashburn-va/ | D6: Updated June 2026.
A7: Home price / price per sq ft | B7: Ashburn median sale price $679,593 and median sale price per square foot $309. | C7: https://www.redfin.com/city/29015/VA/Ashburn/housing-market | D7: Three months ending May 2026.
A8: Substitute pay | B8: Licensed substitute rate listed as $135.03/day; loyalty/site-based/long-term rates are higher. | C8: https://www.ziprecruiter.com/c/Loudoun-County-Public-Schools/Job/Licensed-Substitute-Teacher/-in-Ashburn%2CVA?jid=e3e0bba7061d9b69 | D8: Official job posting aggregation; verify directly if LCPS posts the rate document.
A9: Stability / enrollment | B9: Local reporting says LCPS enrollment is projected to decline until 2031. | C9: https://wjla.com/news/local/loudoun-county-schools-student-enrollment-declines-operating-funds-school-board-recommendations-lcps-virginia-teacher-staff-positions-new-students-superintendent-aaron-spence-registration-issues-problems | D9: Used to assign watchlist rather than perfect stability.

Sheet Lake Washington Sources
A1: Source Type | B1: Source / Citation | C1: What it supports | D1: URL
A2: Official district salary schedule | B2: LWSD 2025-26 LWEA salary schedule | C2: Certificated salary schedule, BA/MA values | D2: https://www.lwsd.org/employment/teachers-certificated-employees/salary-schedules
A3: Official substitute schedule | B3: LWSD 2025-26 substitute salary schedule | C3: Daily substitute pay $222 | D3: https://resources.finalsite.net/images/v1754412729/lwsdorg/dgp3cdyawoq7kpbycc27/LWEASubTeacherSalSch25-2652925.pdf
A4: NCES district detail | B4: Lake Washington School District district detail | C4: Students, teachers, student-teacher ratio, total schools | D4: https://nces.ed.gov/ccd/districtsearch/district_detail.asp?DistrictID=5304230
A5: District enrollment/schools | B5: LWSD enrollment report and schools page | C5: High school count and enrollment context | D5: https://www.lwsd.org/about/enrollment-report
A6: Rent source | B6: Apartments.com Redmond rent trends | C6: Median rent input | D6: https://www.apartments.com/rent-market-trends/redmond-wa/
A7: Housing source | B7: Redfin Redmond housing market | C7: Median home price input | D7: https://www.redfin.com/city/14913/WA/Redmond/housing-market

Sheet Nassau Sources
A1: Source Type | B1: Source / Citation | C1: What it supports | D1: URL
A2: Official salary page | B2: Nassau County Instructional Salaries | C2: Salary schedule links and category context | D2: https://www.nassau.k12.fl.us/page/instructional-salaries
A3: Collective bargaining PDF | B3: 2024-2027 Nassau Teachers Association agreement | C3: 2025-26 salary schedule and degree supplements | D3: https://files-backend.assets.thrillshare.com/documents/asset/uploaded_file/5569/Ncsd/f73c8433-23bf-4388-aa76-259dafad90d2/24-27_NTA_Ratified_Amended_with_Signatures__25.pdf
A4: NCES district detail | B4: Nassau district detail | C4: Students, teachers, student-teacher ratio, total schools | D4: https://nces.ed.gov/ccd/districtsearch/district_detail.asp?ID2=1201350
A5: District homepage | B5: Nassau County School District homepage | C5: Students/employees/school count context | D5: https://www.nassau.k12.fl.us/
A6: Rent source | B6: Apartments.com Yulee rent trends | C6: Median rent input | D6: https://www.apartments.com/rent-market-trends/yulee-fl/
A7: Housing source | B7: Redfin 32097 housing market | C7: Median home price input | D7: https://www.redfin.com/zipcode/32097/housing-market

Sheet WDMCS Sources
A1: Category | B1: Value Used | C1: Source URL
A2: Salary schedule | B2: 2025-26 Combined Salary Schedule; BA Step 1 $51,584; BA Step 11 $62,175; MA Step 1 $54,411; MA Step 11 $65,512 | C2: https://resources.finalsite.net/images/v1745950877/wdmcsorg/ak8isa1vu50msa93nxgy/CombinedSalarySchedule.pdf
A3: Substitute pay | B3: $170 per day | C3: https://www.kcci.com/article/west-des-moines-school-board-substitute-teacher-pay-increase/62347446
A4: Enrollment / student-teacher ratio | B4: 9,110 students; 628.44 classroom teachers; 14.50 ratio | C4: https://nces.ed.gov/ccd/districtsearch/district_detail.asp?ID2=1930930
A5: Demographics | B5: White 53.2%; Hispanic 21.5%; Black 11.7%; Asian 5.9%; Other 7.7% | C5: https://www.niche.com/k12/d/west-des-moines-community-school-district-ia/students/
A6: School counts | B6: 13 public school sites listed on district website | C6: https://www.wdmcs.org/
A7: Home price / price per sq ft | B7: Median sale price $327,554; median price per sq ft $211 | C7: https://www.redfin.com/city/20722/IA/West-Des-Moines/housing-market
A8: Rent | B8: Average rent $1,126/month | C8: https://www.apartments.com/rent-market-trends/west-des-moines-ia/
A9: Prototype update | B9: Added West Des Moines Community Schools; restored Balanced demographics filter; kept 20-day sub-pay method

Sheet Added District Sources
A1: District | B1: Salary Source | C1: Substitute Pay Source | D1: Housing Source | E1: Stability Note | F1: Last Verified
A2: Middleton-Cross Plains Area School District | B2: https://files-backend.assets.thrillshare.com/documents/asset/uploaded_file/1905/Mcpasd/69c6add5-b8ae-4b2e-8319-08609921f255/2025-2026-Certified-Staff-BA-%2455%2C000-Model---10.20.2025---Google-Sheets.pdf?disposition=inline | C2: https://www.mcpasd.k12.wi.us/documents/services/employee-services/16682317 | D2: Redfin/Apartments first-pass market lookup | E2: No penalty; first-pass no current broad layoff/closure evidence. | F2: 2026-06-15
A3: Sun Prairie Area School District | B3: Sun Prairie public job postings / first-pass salary estimate from salary schedule references | C3: https://www.sunprairieschools.org/departments/human-resources/substitutes | D3: Redfin/Apartments first-pass market lookup | E3: No penalty; first-pass no current broad layoff/closure evidence. | F3: 2026-06-15
A4: Waunakee Community School District | B4: Waunakee compensation system references / first-pass salary estimate | C4: https://www.waunakee.k12.wi.us/departments/human-resources/substitute-resources | D4: Redfin/Apartments first-pass market lookup | E4: No penalty; first-pass no current broad layoff/closure evidence. | F4: 2026-06-15
A5: Verona Area School District | B5: https://www.verona.k12.wi.us/departments/humanresources/compensation | C5: https://www.verona.k12.wi.us/departments/humanresources/careers/substitute-opportunities | D5: Redfin/Apartments first-pass market lookup | E5: No penalty; first-pass no current broad layoff/closure evidence. | F5: 2026-06-15
A6: Beaverton School District | B6: https://resources.finalsite.net/images/v1749503218/beavertonk12orus/gd7r4u3u8hlfjssjnbnh/25-26FINALCERTwExtResp.pdf | C6: https://www.beaverton.k12.or.us/departments/human-resources/applicants/beas | D6: Redfin/Apartments first-pass market lookup | E6: 10% penalty due to current budget/staffing-reduction risk. | F6: 2026-06-15

Sheet Added District Sources Round 2
A1: District | B1: Data area | C1: Source / note | D1: URL or citation note
A2: Indian Prairie School District 204 | B2: Salary schedule | C2: IPEA 2025-2026 salary schedule. BA step 1 $56,403; MA step 1 $68,445; step 10/11 values used for 10-year placement. | D2: https://resources.finalsite.net/images/v1746461433/ipsdorg/ydag27zq4d3atey63stv/IPEA_2025-2026v3_12025.pdf
A3: Indian Prairie School District 204 | B3: Sub pay | C3: First-pass Indeed current estimate used; verify with HR before final. | D3: https://www.indeed.com/cmp/Indian-Prairie-School-District-204/salaries/Substitute-Teacher/Illinois
A4: Glenbrook High School District 225 | B4: Salary schedule | C4: 2025-26 183-day teacher salary schedule. BA-0 step A $69,929; MA-0 step A $81,169. | D4: https://staff.glenbrook225.org/fs/resource-manager/view/beb41775-feea-40a8-83be-839d1aa2f9ee
A5: Glenbrook High School District 225 | B5: Housing/rent | C5: Glenview housing/rent sources used as first-pass proxy for district area. | D5: https://www.redfin.com/city/7628/IL/Glenview/housing-market ; https://www.apartments.com/rent-market-trends/glenview-il/
A6: Mounds View Public Schools | B6: Salary schedule | C6: 2025-2026 MVEA salary schedule. BA00 lane does not advance to steps 9/10, so BA+15 is used for 8-10 years as first accessible BA-family lane. | D6: https://resources.finalsite.net/images/v1767030040/moundsviewschoolsorg/krhc4zxvinezdkxxh8ik/Teachers25-27.pdf
A7: Mounds View Public Schools | B7: Sub pay | C7: District employment page lists teacher substitute rate at $200/day. | D7: https://www.mvpschools.org/employment
A8: Eden Prairie Schools | B8: Salary schedule | C8: EPEA 2025-2027 contract, Schedule A 2025-2026. Step 10-14 band used for years 9 and 10. | D8: https://resources.finalsite.net/images/v1757436498/edenprorg/llnxrprxcuuikx1elsuq/EPEA2025-2027FINALCONTRACT.pdf
A9: Eden Prairie Schools | B9: Sub pay | C9: Reserve teacher posting lists regular/incentive substitute rates; $183/day used as regular full-day first-pass rate. | D9: https://www.applitrack.com/edenpr/OnlineApp/default.aspx?AppliTrackJobID=3655&ref=
A10: Naperville CUSD 203 | B10: Salary / contract | C10: NUEA contract and current salary schedule page used. Values are first-pass estimates until exact 2025-26 salary schedule is verified. | D10: https://www.naperville203.org/departments-services/human-resources/collective-bargaining-agreements
A11: Naperville CUSD 203 | B11: Sub pay | C11: 2025-26 substitute info lists substitute teacher full day $130. | D11: https://resources.finalsite.net/images/v1756143021/naperville203org/yzetsbkynvoe9x6mjgl7/importantsubstituteinformation-26.pdf
A12: Naperville CUSD 203 | B12: Rent | C12: Apartments.com Naperville average rent $1,831/month. | D12: https://www.apartments.com/rent-market-trends/naperville-il/

Sheet Added District Sources Round 3
A1: District | B1: Category | C1: Source URL / Reference | D1: Notes | E1: Verification Status
A2: Minnetonka Public Schools | B2: Teacher contract/salary schedule | C2: https://www.minnetonkaschools.org/district/departments/hr/employee-contracts | D2: District HR page lists 2025-2027 Teacher Collective Bargaining Agreement; salary schedule values entered as first-pass from 2025-26 schedule extraction. | E2: Official source; verify exact schedule PDF if needed
A3: Minnetonka Public Schools | B3: Sub pay | D3: Daily sub pay not independently verified in the public sources found; entered as first-pass estimate of $180/day. | E3: Estimated
A4: Wayzata Public Schools | B4: Contracts/handbooks | C4: https://www.wayzataschools.org/careers/contracts | D4: Official contracts/handbooks page located; clear lane/step salary table not found in accessible text during this pass. | E4: Official page; salary estimated
A5: Wayzata Public Schools | B5: Reserve teacher pay | C5: https://www.wayzataschools.org/careers/reserve-teachers | D5: Official reserve teacher page lists 2025-26 reserve teacher daily pay tiers; used Level 1 regular daily rate of $165/day. | E5: Official
A6: Rosemount-Apple Valley-Eagan ISD 196 | B6: Teacher agreement/salary schedule | C6: https://staffportal.district196.org/fs/resource-manager/view/4036ed68-fb19-43de-a642-27172d09737a | D6: Official 2025-2027 agreement; Schedule A 2025-26 salary schedule used. Some higher-step BA/MA cells are blank or effectively advanced-lane-adjacent, so verify HR placement for direct BA/MA 10-year comparison. | E6: Official source with caution
A7: Rosemount-Apple Valley-Eagan ISD 196 | B7: Sub pay | D7: Daily sub pay not independently verified in the public sources found; entered as first-pass estimate of $180/day. | E7: Estimated
A8: Edina Public Schools | B8: Teacher agreement/salary schedule | C8: https://resources.finalsite.net/images/v1765291286/edinaschoolsorg/edinaschoolsorg/fhyhmtjvvixlgplvt2wt/EducationMinnesotaEdinaTeachers2025-2027.pdf | D8: Official 2025-2027 teacher agreement; Appendix A 2025-26 salary schedule entered using BA/BA15 and MA/MA15 columns; Step 1&2 repeated for years 0-1. | E8: Official source
A9: Edina Public Schools | B9: Substitute hiring | C9: https://www.edinaschools.org/careers | D9: Official careers page says Edina partners with Kelly Education for substitute teachers; daily sub rate was not found, so $170/day is a first-pass estimate. | E9: Official page; pay estimated
A10: New Trier Township High School District 203 | B10: Employee agreements | C10: https://www.newtrier.k12.il.us/our-district/administrative-departments/human-resources/employee-agreements | D10: Official page lists NTEA Agreement 2023-2028. A clean 2025-26 lane/step extraction was not completed, so salary rows are first-pass estimates and should be verified before final ranking. | E10: Official page; salary estimated
A11: New Trier Township High School District 203 | B11: Compensation report | C11: https://www.newtrier.k12.il.us/our-district/administrative-departments/human-resources/compensation-reports | D11: Used as a context/check source for New Trier compensation; not a clean BA/MA lane table. | E11: Official page if available
A12: New Trier Township High School District 203 | B12: Sub pay | C12: https://jobs.redroverk12.com/org/newtrierjobs/opening/178696 | D12: Public substitute teacher posting found. Daily rate entered as approximately $147/day based on public hourly estimate; verify with district/Red Rover posting details before final ranking. | E12: Estimated from posting
A13: All Round 3 districts | B13: Housing values | D13: Median home price, rent, and price/sqft are first-pass market estimates entered to test rankings. Replace with preferred Zillow/Redfin/RentCafe source if you want a fully sourced final set. | E13: Estimated

Sheet Tahoe Truckee Sources
A1: Category | B1: Value / Use | C1: Source | D1: Notes
A2: Salary schedule | B2: 2025-26 certificated salary schedule | C2: Uploaded PDF: 2025-2026TTEASalarySchedule-BoardApproved5Nov2025.pdf | D2: Bachelor's values use BA+30 column; Master's values add the $1,000 Master's stipend listed on the schedule.
A3: Substitute pay | B3: $200 full-day base substitute rate | C3: https://www.ttusd.org/departments/human-resources/substitute-teaching | D3: TTUSD substitute rates PDF lists $200 full day, $230 Monday/Friday, $250 long-term, $240 TTUSD retirees.
A4: Enrollment/demographics | B4: 2025-26 CDE DataQuest totals | C4: https://dq.cde.ca.gov/dataquest/dqcensus/enrethlevels.aspx?agglevel=District&cds=3166944&year=2025-26 | D4: Report totals: 4,183 students; 57.6% White, 34.7% Hispanic, 0.6% Asian, 0.2% African American.
A5: Student-teacher ratio | B5: 18.81 | C5: https://nces.ed.gov/ccd/districtsearch/district_detail.asp?ID2=0638770&Search=2 | D5: NCES 2024-25 district detail reports 3,959 students, 210.46 classroom teacher FTE, 18.81 ratio.
A6: School count | B6: 12 total counted in profile | C6: https://www.cde.ca.gov/SchoolDirectory/results?districts=721&items=500&order=-7&status=1 | D6: CDE directory lists 6 elementary incl. charter, 2 middle, 2 comprehensive high, continuation high, and alternative school. Adult/private entries excluded.
A7: Housing | B7: Home $1,024,669; rent $2,203; ppsf $346 | C7: Zillow / RentCafe / FRED | D7: Zillow Truckee ZHVI 2026-05-31; RentCafe average rent March 2026; FRED Truckee-Grass Valley median listing price per sq ft May 2026.
